Workbook
Name DATA1: #REF!
Name _Key2: '[2]DK TRD'!#REF!
Name DATA13: #REF!
Name 层级: [3]筛选项!$B:$B
Name 职位名称列表: [4]筛选项!$A:$A
Name DATA1: #REF!
Name DATA13: #REF!
Name DATA1: #REF!
Name DATA13: #REF!

Sheet 业务情况
A1: Douyin weekly report Sales Performance（3.11-3.17）
B2: Date | C2: GMV | D2: Activity (h) | E2: Live room GMV | F2: Live room GMV/hour | G2: UV | H2: 短视频UV | I2: 短视频UV/UV | J2: Disc%（可删除） | K2: ATV | L2: CR% | M2: New Followers | N2: Return | O2: Return% | P2: 口碑分
B3: 44983 | C3: 73380.22 | D3: 16.5 | E3: 45660 | F3: 2767.27 | G3: 19999 | J3: 0.70352933 | K3: 543.55719 | L3: 0.00463 | M3: 77 | N3: 42889 | O3: =N3/C3 -> 0.58447631
B4: 44984 | C4: 85199 | D4: 17 | E4: 61198 | F4: =E4/D4 -> 3599.8824 | G4: 17755 | J4: 0.71 | K4: 665.61719 | L4: 0.00485 | M4: 113 | N4: 58698.9 | O4: =N4/C4 -> 0.68896231
B5: 44985 | C5: 56797 | D5: 17 | E5: 39498 | F5: =E5/D5 -> 2323.4118 | G5: 16942 | J5: 0.64361352 | K5: 397.18182 | L5: 0.00645 | M5: 102 | N5: 40803.5 | O5: =N5/C5 -> 0.71840942
B6: 44986 | C6: 207640.02 | D6: 17 | E6: 158005.71 | F6: =E6/D6 -> 9294.4535 | G6: 23542 | J6: 0.67001339 | K6: 598.38622 | L6: 0.0102 | M6: 223 | N6: 80786.75 | O6: =N6/C6 -> 0.38907119
B7: 44987 | C7: 182259.17 | D7: 17 | E7: 155976.19 | F7: =E7/D7 -> 9175.07 | G7: 26084 | J7: 0.67952639 | K7: 660.35931 | L7: 0.00825 | M7: 229 | N7: 89585.31 | O7: =N7/C7 -> 0.49152704
B8: 44988 | C8: 103773.21 | D8: 15.7 | E8: 73422.95 | F8: =E8/D8 -> 4676.621 | G8: 20450 | J8: 0.63150349 | K8: 356.1346 | L8: 0.00666 | M8: 184 | N8: 60058.06 | O8: =N8/C8 -> 0.5787434
B9: 44989 | C9: 99005.42 | D9: 11.5 | E9: 76249.77 | F9: =E9/D9 -> 6630.4148 | G9: 22937 | J9: 0.60282778 | K9: 392.69006 | L9: 0.0098 | M9: 236 | N9: 44304.48 | O9: =N9/C9 -> 0.4474955
B10: WK9- Actual TTL | C10: =C9+C8+C7+C6+C5+C4+C3 -> 808054.04 | D10: =SUM(D3:D9) -> 111.7 | E10: =SUM(E3:E9) -> 610010.62 | F10: =E10/D10 -> 5461.1515 | G10: =SUM(G3:G9) -> 147709 | J10: =AVERAGE(J3:J9) -> 0.66300198 | K10: =AVERAGE(K3:K9) -> 516.2752 | L10: =AVERAGE(L3:L9) -> 0.0072628571 | M10: =SUM(M3:M9) -> 1164 | N10: =SUM(N3:N9) -> 417126 | O10: =N10/C10 -> 0.51621052
A11: WK30 | B11: WK8- Actual TTL | C11: 672816 | D11: 110 | E11: 495309 | F11: 4502.8091 | G11: 1266046 | J11: 0.69754209 | K11: 547.70591 | L11: 0.0053571429 | M11: 1243 | N11: 403067.5 | O11: 0.59907538
B12: Weekly Target | C12: =SUM([1]运营日报!$G$97:$G$103) -> 1180000 | D12: =D3+D4+D5+D6+D7+D8+D9 -> 111.7 | E12: =C12*75% -> 885000
B13: Weekly Achv% | C13: =C10/C12 -> 0.68479156 | E13: =E10/E12 -> 0.68927754
A14: WK31 vs WK30 | B14: W-O-W G% | C14: =C10/C11-1 -> 0.20100301 | D14: =D10/D11-1 -> 0.015454545 | E14: =E10/E11-1 -> 0.23157588 | F14: =F10/F11-1 -> 0.21283212 | G14: =G10/G11-1 -> -0.88333046 | J14: =J10-J11 -> -0.034540103 | K14: =K10/K11-1 -> -0.057386105 | L14: =L10/L11-1 -> 0.35573333 | M14: =M10/M11-1 -> -0.063555913 | N14: =N10/N11-1 -> 0.034878773 | O14: =O10-O11 -> -0.082864854
B15: Feu. actual GMV | C15: 2674225.9
B16: MTD GMV target | C16: 3670000
B17: MTD Achv% | C17: =C15/C16 -> 0.7286719
B18: Feu. target GMV | C18: 3370000
B19: GMV Achv% | C19: =C15/C18 -> 0.79353884
B20: Feu actual Net Sales | C20: 1021958.4
B21: Feu target Net Sales | C21: 1685000
B22: Net Sales Achv% | C22: =C20/C21 -> 0.6065035
A25: 本周TOP10商品
A26: 销排 | B26: 短货号（可删除） | C26: 图片 | D26: 风格（可删除） | E26: 系列（可删除） | F26: 新老品 | G26: 成交件数 | H26: 成交金额 | I26: 件单价 | J26: 平折扣 | K26: 售罄率 | L26: 曝光点击率 | M26: 点击成交转化率 | N26: 退货率 | O26: 成交退款率
A27: 1 | B27: 823814 | C27: 82381460569 | D27: 户外 | E27: 健步2.1山地男鞋系列 | F27: 新品 | G27: 766 | H27: 1768007 | I27: 2308 | J27: 0.89 | K27: 0.7 | L27: 0.19 | M27: 0.0105 | N27: 0.39 | O27: 0.39
A28: 2 | B28: 824254 | C28: 82425451052 | D28: 户外 | E28: 奥途男鞋系列 | F28: 新品 | G28: 679 | H28: 1292271 | I28: 1903 | J28: 0.87 | K28: 0.62 | L28: 0.24 | M28: 0.0076 | N28: 0.44 | O28: 0.41
A29: 3 | B29: 524204 | C29: 52420402001 | D29: 休闲 | E29: 科摩男鞋系列 | F29: 231新品 | G29: 678 | H29: 1120088 | I29: 1652 | J29: 0.92 | K29: 0.99 | L29: 0.13 | M29: 0.0121 | N29: 0.45 | O29: 0.45
A30: 4 | B30: 520814 | C30: 52081401001 | D30: 休闲 | E30: 街头720男鞋系列 | F30: 新品 | G30: 583 | H30: 1080476 | I30: 1853 | J30: 0.77 | K30: 0.57 | L30: 0.12 | M30: 0.0161 | N30: 0.28 | O30: 0.28
A31: 5 | B31: 470484 | C31: 47048456787 | D31: 休闲 | E31: 柔酷7号男鞋系列 | F31: 231新品 | G31: 527 | H31: 760657 | I31: 1443 | J31: 0.8 | K31: 0.95 | L31: 0.16 | M31: 0.0139 | N31: 0.33 | O31: 0.33
A32: 6 | B32: 802864 | C32: 80286450869 | D32: 户外 | E32: 健步探索男鞋系列 | F32: 老品 | G32: 361 | H32: 501311 | I32: 1389 | J32: 0.5 | K32: 0.89 | L32: 0.07 | M32: 0.0095 | N32: 0.62 | O32: 0.52
A33: 7 | B33: 800424 | C33: 80042401001 | D33: 户外 | E33: 健步C男鞋系列 | F33: 新品 | G33: 143 | H33: 469192 | I33: 3281 | J33: 0.97 | K33: 0.46 | L33: 0.17 | M33: 0.0034 | N33: 0.45 | O33: 0.39
A34: 8 | B34: 822804 | C34: 82280460414 | D34: 户外 | E34: 健步2.1越野男鞋系列 | F34: 老品 | G34: 202 | H34: 371353 | I34: 1838 | J34: 0.77 | K34: 0.4 | L34: 0.14 | M34: 0.0164 | N34: 0.15 | O34: 0.15
A35: 9 | B35: 91504 | C35: 9150451707 | D35: 户外 | E35: 健步C男鞋系列 | F35: 新品 | G35: 113 | H35: 370491 | I35: 3279 | J35: 0.96 | K35: 0.25 | L35: 0.15 | M35: 0.0031 | N35: 0.48 | O35: 0.45
A36: 10 | B36: 207124 | C36: 20712401001 | D36: 正装 | E36: 雅仕系列 | F36: 新品 | G36: 225 | H36: 348770 | I36: 1550 | J36: 0.78 | K36: 0.38 | L36: 0.12 | M36: 0.0078 | N36: 0.42 | O36: 0.35
A39: 本周主播数据
A40: 主播名称 | B40: 大玉儿 | C40: 偲佟 | D40: 哈多 | E40: 王可 | F40: 白白 | G40: Anna
A41: 开播时长（小时数） | B41: 115 | C41: 106 | D41: 85 | E41: 69 | F41: 8 | G41: 30
A42: 直播间成交金额 | B42: 2030900 | C42: 820427 | D42: 783503 | E42: 523438 | F42: 81293 | G42: 347161
A43: 单小时成交金额 | B43: 17650 | C43: 7672 | D43: 9196 | E43: 7568 | F43: 10140 | G43: 11205
A44: 最高在线人数 | B44: 826 | C44: 631 | D44: 735 | E44: 97 | F44: 146 | G44: 92
A45: 平均在线人数 | B45: 84 | C45: 42 | D45: 50 | E45: 34 | F45: 57 | G45: 38
A46: 平均件单价 | B46: 621 | C46: 632 | D46: 578 | E46: 551 | F46: 595 | G46: 554
A47: 引流能力 展现进入率 | B47: 0.1414 | C47: 0.136 | D47: 0.1165 | E47: 0.1322 | F47: 0.1059 | G47: 0.1168
A48: 留人能力 留存率 | B48: 0.3368 | C48: 0.3446 | D48: 0.3443 | E48: 0.3701 | F48: 0.3592 | G48: 0.3996
A49: 互动能力 评论率 | B49: 0.0389 | C49: 0.0383 | D49: 0.0421 | E49: 0.038 | F49: 0.0341 | G49: 0.0499
A50: 吸粉能力 新增粉丝数 | B50: 4468 | C50: 2382 | D50: 2129 | E50: 1041 | F50: 237 | G50: 551
A51: 吸粉能力 新加团人数 | B51: 56 | C51: 64 | D51: 33 | E51: 15 | F51: 1 | G51: 16
A52: 转化能力 单UV价值(元) | B52: 4 | C52: 3 | D52: 3 | E52: 4 | F52: 3 | G52: 5
A53: 成交人数 | B53: 3244 | C53: 1279 | D53: 1368 | E53: 955 | F53: 134 | G53: 614
A54: 策略人群TOP3 | B54: 新锐白领（23.30%） | C54: genz（24.26%） | D54: genz（31.20%） | E54: 新锐白领（29.63%） | F54: 小镇青年（27.48%） | G54: 新锐白领（30.01%）
B55: genz（22.09%） | C55: 新锐白领（22.69%） | D55: 小镇青年（20.88%） | E55: 精致妈妈（20.21%） | F55: 新锐白领（20.61%） | G55: genz（21.53%）
B56: 精致妈妈（21.93%） | C56: 精致妈妈（19.21%） | D56: 精致妈妈（17.90%） | E56: 小镇青年（18.62%） | F56: genz（20.61%） | G56: 小镇青年（18.76%）
A57: 性别 | B57: 男（33.90%） | C57: 男（39.34%） | D57: 男（29.87%） | E57: 男（46.85%） | F57: 男（33.83%） | G57: 男（49.84%）
B58: 女（66.10%） | C58: 女（60.66%） | D58: 女（70.13%） | E58: 女（53.15%） | F58: 女（66.17%） | G58: 女（50.16%）
A59: 年龄段TOP3 | B59: 25-30（34.95%） | C59: 25-30（31.02%） | D59: 18-24（40.30%） | E59: 25-30（39.01%） | F59: 25-30（34.09%） | G59: 25-30（38.00%）
B60: 18-24（28.86%） | C60: 18-24（30.55%） | D60: 25-30（29.21%） | E60: 31-35（25.66%） | F60: 18-24（31.82%） | G60: 18-24（26.92%）
B61: 31-35（23.08%） | C61: 31-35（23.07%） | D61: 31-35（17.44%） | E61: 18-24（23.55%） | F61: 31-35（18.94%） | G61: 31-35（23.82%）
A62: 城市等级TOP3 | B62: 新一线（24.61%） | C62: 三线（24.70%） | D62: 新一线（23.03%） | E62: 新一线（22.18%） | F62: 四线（22.72%） | G62: 三线（25.24%）
B63: 三线（24.03%） | C63: 新一线（24.55%） | D63: 三线（21.41%） | E63: 三线（21.75%） | F63: 二线（19.70%） | G63: 新一线（23.13%）
B64: 二线（19.06%） | C64: 二线（18.25%） | D64: 二线（19.19%） | E64: 二线（19.85%） | F64: 新一线（19.70%） | G64: 二线（17.59%）
A65: 地域分布TOP3 | B65: 江苏（14.94%） | C65: 江苏（15.89%） | D65: 江苏（12.07%） | E65: 江苏（13.09%） | F65: 山东（8.33%） | G65: 江苏（14.17%）
B66: 浙江（7.99%） | C66: 浙江（8.42%） | D66: 四川（8.22%） | E66: 山东（8.55%） | F66: 江苏（8.30%） | G66: 四川（8.63%）
B67: 四川（7.37%） | C67: 四川（7.47%） | D67: 浙江（7.33%） | E67: 浙江（7.29%） | F67: 湖南（7.58%） | G67: 浙江（7.82%）

Sheet 2026年-年度目标 
A1: 项目 | D1: 1月 | E1: 2月 | F1: 3月 | G1: 4月 | H1: 5月 | I1: 6月 | J1: 7月 | K1: 8月 | L1: 9月 | M1: 10月 | N1: 11月 | O1: 12月 | P1: MTD | Q1: TOTAL
A2: GXG | B2: 实际 | C2: GMV | D2: =SUMIF('GXG-日报'!$D:$D,D$1,'GXG-日报'!$F:$F) -> 18651172 | E2: =SUMIF('GXG-日报'!$D:$D,E$1,'GXG-日报'!$F:$F) -> 15084424 | F2: =SUMIF('GXG-日报'!$D:$D,F$1,'GXG-日报'!$F:$F) -> 2140928.6 | P2: =SUM(D2:F2) -> 35876525 | Q2: =SUM(D2:O2) -> 35876525
C3: NET | D3: =SUMIF('GXG-日报'!$D:$D,D$1,'GXG-日报'!$H:$H) -> 8286015.5 | E3: =SUMIF('GXG-日报'!$D:$D,E$1,'GXG-日报'!$H:$H) -> 5733417.1 | F3: =SUMIF('GXG-日报'!$D:$D,F$1,'GXG-日报'!$H:$H) -> 996198.25 | P3: =SUM(D3:F3) -> 15015631 | Q3: =SUM(D3:O3) -> 15015631
C4: 退货率 | D4: =1-D3/D2 -> 0.55573756 | E4: =1-E3/E2 -> 0.61991143 | F4: =1-F3/F2 -> 0.53468871 | P4: =1-P3/P2 -> 0.58146362 | Q4: =1-Q3/Q2 -> 0.58146362
C5: 商品卡GMV | D5: =SUMIF('GXG-日报'!$D:$D,D$1,'GXG-日报'!$I:$I) -> 2723069.9 | E5: =SUMIF('GXG-日报'!$D:$D,E$1,'GXG-日报'!$I:$I) -> 2451956.5 | F5: =SUMIF('GXG-日报'!$D:$D,F$1,'GXG-日报'!$I:$I) -> 261475.9 | P5: =SUM(D5:F5) -> 5436502.3 | Q5: =SUM(D5:O5) -> 5436502.3
C6: 商品卡占比 | D6: =D5/D2 -> 0.14599993 | E6: =E5/E2 -> 0.1625489 | F6: =F5/F2 -> 0.122132 | P6: =P5/P2 -> 0.15153369 | Q6: =Q5/Q2 -> 0.15153369
C7: 投放消耗金额 | D7: =SUMIF('GXG-日报'!$D:$D,D$1,'GXG-日报'!$K:$K) -> 549643.94 | E7: =SUMIF('GXG-日报'!$D:$D,E$1,'GXG-日报'!$K:$K) -> 400283.8 | F7: =SUMIF('GXG-日报'!$D:$D,F$1,'GXG-日报'!$K:$K) -> 63607.54 | P7: =SUM(D7:F7) -> 1013535.3 | Q7: =SUM(D7:O7) -> 1013535.3
C8: 投放费比 | D8: =D7/D3 -> 0.066333926 | E8: =E7/E3 -> 0.069815922 | F8: =F7/F3 -> 0.063850283 | P8: =P7/P3 -> 0.067498681 | Q8: =Q7/Q3 -> 0.067498681
B9: 目标 | C9: GMV | D9: 15000000 | E9: 9000000 | F9: 4600000 | G9: 5400000 | H9: 6500000 | I9: 6500000 | J9: 6000000 | K9: 6500000 | L9: 7000000 | M9: 12000000 | N9: 16000000 | O9: 15000000 | P9: =SUM(D9:F9) -> 28600000 | Q9: =SUM(D9:O9) -> 109500000
C10: NET | D10: 6750000 | E10: 3870000 | F10: 2162000 | G10: 2808000 | H10: 3380000 | I10: 3380000 | J10: 3120000 | K10: 3250000 | L10: 3500000 | M10: 5400000 | N10: 6400000 | O10: 6000000 | P10: =SUM(D10:F10) -> 12782000 | Q10: =SUM(D10:O10) -> 50020000
C11: 退货率 | D11: =1-D10/D9 -> 0.55 | E11: =1-E10/E9 -> 0.57 | F11: =1-F10/F9 -> 0.53 | G11: =1-G10/G9 -> 0.48 | H11: =1-H10/H9 -> 0.48 | I11: =1-I10/I9 -> 0.48 | J11: =1-J10/J9 -> 0.48 | K11: =1-K10/K9 -> 0.5 | ... Q11: =1-Q10/Q9 -> 0.54319635
C12: 投放费比 | D12: 0.06 | E12: 0.06 | F12: 0.06 | G12: 0.06 | H12: 0.06 | I12: 0.06 | J12: 0.06 | K12: 0.06 | L12: 0.06 | M12: 0.06 | N12: 0.06 | O12: 0.06 | P12: 0.06 | Q12: 0.06
B13: 目标达成率 | C13: GMV | D13: =D2/D9 -> 1.2434115 | E13: =E2/E9 -> 1.6760471 | F13: =F2/F9 -> 0.46541926 | G13: =G2/G9 -> 0 | H13: =H2/H9 -> 0 | I13: =I2/I9 -> 0 | J13: =J2/J9 -> 0 | K13: =K2/K9 -> 0 | ... Q13: =Q2/Q9 -> 0.3276395
C14: NET | D14: =D3/D10 -> 1.2275578 | E14: =E3/E10 -> 1.4815031 | F14: =F3/F10 -> 0.46077625 | G14: =G3/G10 -> 0 | H14: =H3/H10 -> 0 | I14: =I3/I10 -> 0 | J14: =J3/J10 -> 0 | K14: =K3/K10 -> 0 | ... Q14: =Q3/Q10 -> 0.30019254
C15: 退货率 | D15: =D4/D11 -> 1.0104319 | E15: =E4/E11 -> 1.0875639 | F15: =F4/F11 -> 1.0088466 | G15: =G4/G11 -> 0 | H15: =H4/H11 -> 0 | I15: =I4/I11 -> 0 | J15: =J4/J11 -> 0 | K15: =K4/K11 -> 0 | ... Q15: =Q4/Q11 -> 1.0704483
C16: 投放费比 | D16: =D8/D12 -> 1.1055654 | E16: =E8/E12 -> 1.1635987 | F16: =F8/F12 -> 1.0641714 | G16: =G8/G12 -> 0 | H16: =H8/H12 -> 0 | I16: =I8/I12 -> 0 | J16: =J8/J12 -> 0 | K16: =K8/K12 -> 0 | ... Q16: =Q8/Q12 -> 1.124978
B17: YOY | C17: GMV | D17: =D2/D80-1 -> 0.2404478 | E17: =E2/E80-1 -> 1.4696094 | F17: =F2/F80-1 -> -0.66698759 | G17: =G2/G80-1 -> -1 | H17: =H2/H80-1 -> -1 | I17: =I2/I80-1 -> -1 | J17: =J2/J80-1 -> -1 | K17: =K2/K80-1 -> -1 | ... Q17: =Q2/Q80-1 -> -0.64429276
C18: NET | D18: =D3/D81-1 -> 0.17629221 | E18: =E3/E81-1 -> 0.81603907 | F18: =F3/F81-1 -> -0.69731347 | G18: =G3/G81-1 -> -1 | H18: =H3/H81-1 -> -1 | I18: =I3/I81-1 -> -1 | J18: =J3/J81-1 -> -1 | K18: =K3/K81-1 -> -1 | ... Q18: =Q3/Q81-1 -> -0.70163201
C19: 退货率 | D19: =D4-D82 -> 0.024230305 | E19: =E4-E82 -> 0.13678924 | F19: =F4-F82 -> 0.046619096 | G19: =G4-G82 -> -0.36143145 | H19: =H4-H82 -> -0.43705456 | I19: =I4-I82 -> -0.36090667 | J19: =J4-J82 -> -0.35611135 | K19: =K4-K82 -> -0.48703971 | ... Q19: =Q4-Q82 -> 0.080432769
A20: DAZZLE 抖音 | B20: 实际 | C20: GMV | D20: =SUMIF('DAZZLE-日报'!$D:$D,D$1,'DAZZLE-日报'!$F:$F) -> 22583187 | E20: =SUMIF('DAZZLE-日报'!$D:$D,E$1,'DAZZLE-日报'!$F:$F) -> 15289696 | F20: =SUMIF('DAZZLE-日报'!$D:$D,F$1,'DAZZLE-日报'!$F:$F) -> 4755169 | P20: =SUM(D20:F20) -> 42628052 | Q20: =SUM(D20:O20) -> 42628052
C21: NET | D21: =SUMIF('DAZZLE-日报'!$D:$D,D$1,'DAZZLE-日报'!$H:$H) -> 3027474.2 | E21: =SUMIF('DAZZLE-日报'!$D:$D,E$1,'DAZZLE-日报'!$H:$H) -> 2171222.5 | F21: =SUMIF('DAZZLE-日报'!$D:$D,F$1,'DAZZLE-日报'!$H:$H) -> 726221.35 | P21: =SUM(D21:F21) -> 5924918.2 | Q21: =SUM(D21:O21) -> 5924918.2
C22: 退货率 | D22: =1-D21/D20 -> 0.86594123 | E22: =1-E21/E20 -> 0.85799439 | F22: =1-F21/F20 -> 0.84727749 | P22: =1-P21/P20 -> 0.86100894 | Q22: =1-Q21/Q20 -> 0.86100894
C23: 商品卡GMV | D23: =SUMIF('DAZZLE-日报'!$D:$D,D$1,'DAZZLE-日报'!$I:$I) -> 6885434.3 | E23: =SUMIF('DAZZLE-日报'!$D:$D,E$1,'DAZZLE-日报'!$I:$I) -> 5390649.5 | F23: =SUMIF('DAZZLE-日报'!$D:$D,F$1,'DAZZLE-日报'!$I:$I) -> 1824750.8 | P23: =SUM(D23:F23) -> 14100835 | Q23: =SUM(D23:O23) -> 14100835
C24: 商品卡占比 | D24: =D23/D20 -> 0.30489205 | E24: =E23/E20 -> 0.35256748 | F24: =F23/F20 -> 0.38374048 | P24: =P23/P20 -> 0.33078769 | Q24: =Q23/Q20 -> 0.33078769
C25: 投放消耗金额 | D25: =SUMIF('DAZZLE-日报'!$D:$D,D$1,'DAZZLE-日报'!$K:$K) -> 72623.55 | E25: =SUMIF('DAZZLE-日报'!$D:$D,E$1,'DAZZLE-日报'!$K:$K) -> 45510.23 | F25: =SUMIF('DAZZLE-日报'!$D:$D,F$1,'DAZZLE-日报'!$K:$K) -> 12451.32 | P25: =SUM(D25:F25) -> 130585.1 | Q25: =SUM(D25:O25) -> 130585.1
C26: 投放费比 | D26: =D25/D21 -> 0.023988164 | E26: =E25/E21 -> 0.020960647 | F26: =F25/F21 -> 0.017145351 | P26: =P25/P21 -> 0.022039984 | Q26: =Q25/Q21 -> 0.022039984
B27: 目标 | C27: GMV | D27: 18860000 | E27: 11527500 | F27: 17240000 | G27: 13590882 | H27: 16215000 | I27: 18470333 | J27: 15457500 | K27: 12551667 | L27: 13434294 | M27: 17610882 | N27: 21693000 | O27: 20075677 | P27: =SUM(D27:F27) -> 47627500 | Q27: =SUM(D27:O27) -> 196726735
C28: NET | D28: 3041200 | E28: 1773800 | F28: 3033600 | G28: 2211000 | H28: 2602600 | I28: 2687800 | J28: 2477400 | K28: 2000600 | L28: 2258190 | M28: 2784150 | N28: 3051370 | O28: 3089940 | P28: =SUM(D28:F28) -> 7848600 | Q28: =SUM(D28:O28) -> 31011650
C29: 退货率 | D29: =1-D28/D27 -> 0.83874867 | E29: =1-E28/E27 -> 0.84612448 | F29: =1-F28/F27 -> 0.82403712 | G29: =1-G28/G27 -> 0.8373174 | H29: =1-H28/H27 -> 0.8394943 | I29: =1-I28/I27 -> 0.85448015 | J29: =1-J28/J27 -> 0.83972829 | K29: =1-K28/K27 -> 0.84061081 | ... Q29: =1-Q28/Q27 -> 0.84236179
C30: 投放费比 | D30: 0.03 | E30: 0.03 | F30: 0.03 | G30: 0.03 | H30: 0.03 | I30: 0.03 | J30: 0.03 | K30: 0.03 | L30: 0.03 | M30: 0.03 | N30: 0.03 | O30: 0.03 | P30: 0.03 | Q30: 0.03
B31: 目标达成率 | C31: GMV | D31: =D20/D27 -> 1.1974118 | E31: =E20/E27 -> 1.326367 | F31: =F20/F27 -> 0.27582187 | P31: =P20/P27 -> 0.89503022 | Q31: =Q20/Q27 -> 0.21668662
C32: NET | D32: =D21/D28 -> 0.99548673 | E32: =E21/E28 -> 1.2240515 | F32: =F21/F28 -> 0.23939259 | P32: =P21/P28 -> 0.75490128 | Q32: =Q21/Q28 -> 0.19105459
C33: 退货率 | D33: =D22/D29 -> 1.0324204 | E33: =E22/E29 -> 1.0140286 | F33: =F22/F29 -> 1.0282031 | P33: =P22/P29 -> 1.0308908 | Q33: =Q22/Q29 -> 1.0221367
C34: 投放费比 | D34: =D26/D30 -> 0.79960548 | E34: =E26/E30 -> 0.69868824 | F34: =F26/F30 -> 0.5715117 | P34: =P26/P30 -> 0.73466613 | Q34: =Q26/Q30 -> 0.73466613
B35: YOY | C35: GMV | D35: =D20/D84-1 -> 0.60324565 | E35: =E20/E84-1 -> 0.31297102 | F35: =F20/F84-1 -> -0.64868726 | G35: =G20/G84-1 -> -1 | H35: =H20/H84-1 -> -1 | I35: =I20/I84-1 -> -1 | J35: =J20/J84-1 -> -1 | K35: =K20/K84-1 -> -1 | ... Q35: =Q20/Q84-1 -> -0.78773921
C36: NET | D36: =D21/D85-1 -> 0.29591477 | E36: =E21/E85-1 -> 0.018429408 | F36: =F21/F85-1 -> -0.52468008 | G36: =G28/G85-1 -> -0.027179445 | H36: =H28/H85-1 -> -0.22268192 | I36: =I28/I85-1 -> 0.39115719 | J36: =J28/J85-1 -> 0.66472167 | K36: =K28/K85-1 -> 0.10484705 | L36: =L28/L85-1 -> -0.038380548 | M36: =M28/M85-1 -> -0.23660685 | N36: =N28/N85-1 -> 0.70037433 | O36: =O28/O85-1 -> -0.26475843 | P36: =P21/P85-1 -> 0.32604868 | Q36: =Q21/Q85-1 -> -0.79456211
C37: 退货率 | D37: =D22-D86 -> 0.031792522 | E37: =E22-E86 -> 0.041069671 | F37: =F22-F86 -> -0.039844085 | G37: =G22-G86 -> -0.79616059 | H37: =H22-H86 -> -0.84782612 | I37: =I22-I86 -> -0.88915968 | J37: =J22-J86 -> -0.90604028 | K37: =K22-K86 -> -0.83512547 | ... Q37: =Q22-Q86 -> 0.0046160984
A38: DAZZLE 视频号 | B38: 实际 | C38: GMV | D38: =SUMIF('DAZZLE（视频号）-日报'!$D:$D,D$1,'DAZZLE（视频号）-日报'!$F:$F) -> 1667428 | E38: =SUMIF('DAZZLE（视频号）-日报'!$D:$D,E$1,'DAZZLE（视频号）-日报'!$F:$F) -> 1281220 | P38: =SUM(D38:F38) -> 2948648 | Q38: =SUM(D38:O38) -> 2948648
C39: NET | D39: =SUMIF('DAZZLE（视频号）-日报'!$D:$D,D$1,'DAZZLE（视频号）-日报'!$G:$G) -> 210107.6 | E39: =SUMIF('DAZZLE（视频号）-日报'!$D:$D,E$1,'DAZZLE（视频号）-日报'!$G:$G) -> 347192.51 | P39: =SUM(D39:F39) -> 557300.11 | Q39: =SUM(D39:O39) -> 557300.11
C40: 退货率 | D40: =1-D39/D38 -> 0.873993 | E40: =1-E39/E38 -> 0.72901413 | P40: =1-P39/P38 -> 0.81099809 | Q40: =1-Q39/Q38 -> 0.81099809
B41: 目标 | C41: GMV | D41: 3000000 | E41: 2550000 | F41: 3400000 | G41: 3150000 | H41: 3950000 | I41: 3650000 | J41: 3050000 | K41: 3850000 | L41: 3280000 | M41: 3850000 | N41: 3550000 | O41: 2880000 | P41: =SUM(D41:F41) -> 8950000 | Q41: =SUM(D41:O41) -> 40160000
C42: NET | D42: 700000 | E42: 550000 | F42: 730000 | G42: 720000 | H42: 900000 | I42: 800000 | J42: 600000 | K42: 800000 | L42: 700000 | M42: 1000000 | N42: 900000 | O42: 600000 | P42: =SUM(D42:F42) -> 1980000 | Q42: =SUM(D42:O42) -> 9000000
C43: 退货率 | D43: =1-D42/D41 -> 0.76666667 | E43: =1-E42/E41 -> 0.78431373 | F43: =1-F42/F41 -> 0.78529412 | G43: =1-G42/G41 -> 0.77142857 | H43: =1-H42/H41 -> 0.7721519 | I43: =1-I42/I41 -> 0.78082192 | J43: =1-J42/J41 -> 0.80327869 | K43: =1-K42/K41 -> 0.79220779 | ... Q43: =1-Q42/Q41 -> 0.77589641
B44: 目标达成率 | C44: GMV | D44: =D38/D41 -> 0.55580933 | E44: =E38/E41 -> 0.50243922 | F44: =F38/F41 -> 0 | G44: =G38/G41 -> 0 | H44: =H38/H41 -> 0 | I44: =I38/I41 -> 0 | J44: =J38/J41 -> 0 | K44: =K38/K41 -> 0 | ... Q44: =Q38/Q41 -> 0.07342251
C45: NET | D45: =D39/D42 -> 0.30015371 | E45: =E39/E42 -> 0.63125911 | F45: =F39/F42 -> 0 | G45: =G39/G42 -> 0 | H45: =H39/H42 -> 0 | I45: =I39/I42 -> 0 | J45: =J39/J42 -> 0 | K45: =K39/K42 -> 0 | ... Q45: =Q39/Q42 -> 0.061922234
C46: 退货率 | D46: =D40/D43 -> 1.1399909 | E46: =E40/E43 -> 0.92949302 | F46: =F40/F43 -> 0 | G46: =G40/G43 -> 0 | H46: =H40/H43 -> 0 | I46: =I40/I43 -> 0 | J46: =J40/J43 -> 0 | K46: =K40/K43 -> 0 | ... Q46: =Q40/Q43 -> 1.0452402
B47: YOY | C47: GMV | D47: =D38/D87-1 -> #DIV/0! | E47: =E38/E87-1 -> #DIV/0! | F47: =F38/F87-1 -> #DIV/0! | G47: =G38/G87-1 -> #DIV/0! | H47: =H38/H87-1 -> #DIV/0! | I47: =I38/I87-1 -> #DIV/0! | J47: =J38/J87-1 -> -1 | K47: =K38/K87-1 -> -1 | ... Q47: =Q38/Q87-1 -> -0.80745932
C48: NET | D48: =D39/D88-1 -> #DIV/0! | E48: =E39/E88-1 -> #DIV/0! | F48: =F39/F88-1 -> #DIV/0! | G48: =G39/G88-1 -> #DIV/0! | H48: =H39/H88-1 -> #DIV/0! | I48: =I39/I88-1 -> #DIV/0! | J48: =J39/J88-1 -> -1 | K48: =K39/K88-1 -> -1 | ... Q48: =Q39/Q88-1 -> -0.84247875
C49: 退货率 | D49: =D40-D89 -> 0.873993 | E49: =E40-E89 -> 0.72901413 | F49: =F40-F89 -> 0 | G49: =G40-G89 -> 0 | H49: =H40-H89 -> 0 | I49: =I40-I89 -> 0 | J49: =J40-J89 -> -0.73079838 | K49: =K40-K89 -> -0.765771 | ... Q49: =Q40-Q89 -> 0.042018063
A50: Champion 抖音 | B50: 实际 | C50: GMV | D50: =SUMIF('Champion-日报'!$D:$D,D$1,'Champion-日报'!$F:$F) -> 3661347 | P50: =SUM(D50:E50) -> 3661347 | Q50: =SUM(D50:O50) -> 3661347
C51: NET | D51: =SUMIF('Champion-日报'!$D:$D,D$1,'Champion-日报'!$G:$G) -> 1513024.9 | P51: =SUM(D51) -> 1513024.9 | Q51: =SUM(D51:O51) -> 1513024.9
C52: 退货率 | D52: =1-D51/D50 -> 0.58675731 | P52: =1-P51/P50 -> 0.58675731 | Q52: =1-Q51/Q50 -> 0.58675731
C53: 商品卡GMV | D53: =SUMIF('Champion-日报'!$D:$D,D$1,'Champion-日报'!$H:$H) -> 1362881.5 | P53: =SUM(D53) -> 1362881.5 | Q53: =SUM(D53:O53) -> 1362881.5
C54: 商品卡占比 | D54: =D53/D50 -> 0.37223501 | P54: =P53/P50 -> 0.37223501 | Q54: =Q53/Q50 -> 0.37223501
C55: 投放消耗金额 | D55: =SUMIF('Champion-日报'!$D:$D,D$1,'Champion-日报'!$J:$J) -> 87894.11 | P55: =SUM(D55) -> 87894.11 | Q55: =SUM(D55:O55) -> 87894.11
C56: 投放费比 | D56: =D55/D51 -> 0.058091649 | P56: =P55/P51 -> 0.058091649 | Q56: =Q55/Q51 -> 0.058091649
B57: 目标 | C57: GMV | D57: 7000000 | P57: =SUM(D57) -> 7000000 | Q57: =SUM(D57:O57) -> 7000000
C58: NET | D58: =D57*40% -> 2800000 | P58: =SUM(D58) -> 2800000 | Q58: =SUM(D58:O58) -> 2800000
C59: 退货率 | D59: =1-D58/D57 -> 0.6 | E59: =1-E58/E57 -> #DIV/0! | F59: =1-F58/F57 -> #DIV/0! | G59: =1-G58/G57 -> #DIV/0! | H59: =1-H58/H57 -> #DIV/0! | I59: =1-I58/I57 -> #DIV/0! | J59: =1-J58/J57 -> #DIV/0! | K59: =1-K58/K57 -> #DIV/0! | ... Q59: =1-Q58/Q57 -> 0.6
C60: 投放费比 | D60: 0.05 | E60: 0 | F60: 0 | G60: 0 | H60: 0 | I60: 0 | J60: 0 | K60: 0 | L60: 0 | M60: 0 | N60: 0 | O60: 0 | P60: 0 | Q60: 0
B61: 目标达成率 | C61: GMV | D61: =D50/D57 -> 0.52304956 | E61: =E50/E57 -> #DIV/0! | F61: =F50/F57 -> #DIV/0! | G61: =G50/G57 -> #DIV/0! | H61: =H50/H57 -> #DIV/0! | I61: =I50/I57 -> #DIV/0! | J61: =J50/J57 -> #DIV/0! | K61: =K50/K57 -> #DIV/0! | ... Q61: =Q50/Q57 -> 0.52304956
C62: NET | D62: =D51/D58 -> 0.54036602 | E62: =E51/E58 -> #DIV/0! | F62: =F51/F58 -> #DIV/0! | G62: =G51/G58 -> #DIV/0! | H62: =H51/H58 -> #DIV/0! | I62: =I51/I58 -> #DIV/0! | J62: =J51/J58 -> #DIV/0! | K62: =K51/K58 -> #DIV/0! | ... Q62: =Q51/Q58 -> 0.54036602
C63: 退货率 | D63: =D52/D59 -> 0.97792885 | E63: =E52/E59 -> #DIV/0! | F63: =F52/F59 -> #DIV/0! | G63: =G52/G59 -> #DIV/0! | H63: =H52/H59 -> #DIV/0! | I63: =I52/I59 -> #DIV/0! | J63: =J52/J59 -> #DIV/0! | K63: =K52/K59 -> #DIV/0! | ... Q63: =Q52/Q59 -> 0.97792885
C64: 投放费比 | D64: =D56/D60 -> 1.161833 | E64: =E56/E60 -> #DIV/0! | F64: =F56/F60 -> #DIV/0! | G64: =G56/G60 -> #DIV/0! | H64: =H56/H60 -> #DIV/0! | I64: =I56/I60 -> #DIV/0! | J64: =J56/J60 -> #DIV/0! | K64: =K56/K60 -> #DIV/0! | ... Q64: =Q56/Q60 -> #DIV/0!
A65: TOTAL | B65: 实际 | C65: GMV | D65: =D2+D20+D38+D50 -> 46563135 | E65: =E2+E20+E38+E50 -> 31655340 | F65: =F2+F20 -> 6896097.6 | G65: =G2+G20 -> 0 | H65: =H2+H20 -> 0 | I65: =I2+I20 -> 0 | J65: =J2+J20 -> 0 | K65: =K2+K20 -> 0 | L65: =L2+L20 -> 0 | M65: =M2+M20 -> 0 | ... O65: =O2+O20 -> 0 | P65: =SUM(D65:E65) -> 78218474 | Q65: =Q2+Q20 -> 78504577
C66: NET | D66: =D3+D21+D39+D51 -> 13036622 | E66: =E3+E21+E39+E51 -> 8251832.2 | F66: =F3+F21 -> 1722419.6 | G66: =G3+G21 -> 0 | H66: =H3+H21 -> 0 | I66: =I3+I21 -> 0 | J66: =J3+J21 -> 0 | K66: =K3+K21 -> 0 | L66: =L3+L21 -> 0 | M66: =M3+M21 -> 0 | ... O66: =O3+O21 -> 0 | P66: =SUM(D66:E66) -> 21288454 | Q66: =Q3+Q21 -> 20940549
C67: 退货率 | D67: =1-D66/D65 -> 0.72002267 | E67: =1-E66/E65 -> 0.73932258 | F67: =1-F66/F65 -> 0.75023271 | G67: =1-G66/G65 -> #DIV/0! | H67: =1-H66/H65 -> #DIV/0! | I67: =1-I66/I65 -> #DIV/0! | J67: =1-J66/J65 -> #DIV/0! | K67: =1-K66/K65 -> #DIV/0! | ... Q67: =1-Q66/Q65 -> 0.73325697
C68: 商品卡GMV | D68: =D5+D23++D53 -> 10971386 | E68: =E5+E23++E53 -> 7842606 | F68: =F5+F23 -> 2086226.7 | G68: =G5+G23 -> 0 | H68: =H5+H23 -> 0 | I68: =I5+I23 -> 0 | J68: =J5+J23 -> 0 | K68: =K5+K23 -> 0 | L68: =L5+L23 -> 0 | M68: =M5+M23 -> 0 | ... O68: =O5+O23 -> 0 | P68: =SUM(D68:E68) -> 18813992 | Q68: =Q5+Q23 -> 19537337
C69: 商品卡占比 | D69: =D68/D65 -> 0.23562386 | E69: =E68/E65 -> 0.24774986 | F69: =F68/F65 -> 0.3025228 | G69: =G68/G65 -> #DIV/0! | H69: =H68/H65 -> #DIV/0! | I69: =I68/I65 -> #DIV/0! | J69: =J68/J65 -> #DIV/0! | K69: =K68/K65 -> #DIV/0! | ... Q69: =Q68/Q65 -> 0.24886876
C70: 投放消耗金额 | D70: =D7+D25+D55 -> 710161.6 | E70: =E7+E25+E55 -> 445794.03 | F70: =F7+F25 -> 76058.86 | G70: =G7+G25 -> 0 | H70: =H7+H25 -> 0 | I70: =I7+I25 -> 0 | J70: =J7+J25 -> 0 | K70: =K7+K25 -> 0 | L70: =L7+L25 -> 0 | M70: =M7+M25 -> 0 | ... O70: =O7+O25 -> 0 | P70: =SUM(D70:E70) -> 1155955.6 | Q70: =Q7+Q25 -> 1144120.4
C71: 投放费比 | D71: =D70/D66 -> 0.054474356 | E71: =E70/E66 -> 0.054023642 | F71: =F70/F66 -> 0.044158148 | G71: =G70/G66 -> #DIV/0! | H71: =H70/H66 -> #DIV/0! | I71: =I70/I66 -> #DIV/0! | J71: =J70/J66 -> #DIV/0! | K71: =K70/K66 -> #DIV/0! | ... Q71: =Q70/Q66 -> 0.054636599
B72: 目标 | C72: GMV | D72: =D9+D27+D41+D57 -> 43860000 | E72: =E9+E27+E41+E57 -> 23077500 | F72: =F9+F27+F41+F57 -> 25240000 | G72: =G9+G27+G41+G57 -> 22140882 | H72: =H9+H27+H41+H57 -> 26665000 | I72: =I9+I27+I41+I57 -> 28620333 | J72: =J9+J27+J41+J57 -> 24507500 | K72: =K9+K27+K41+K57 -> 22901667 | ... O72: =O9+O27+O41+O57 -> 37955677 | P72: =SUM(D72:E72) -> 66937500 | Q72: =Q9+Q27 -> 306226735
C73: NET | D73: =D10+D28+D42+D58 -> 13291200 | E73: =E10+E28+E42+E58 -> 6193800 | F73: =F10+F28+F42+F58 -> 5925600 | G73: =G10+G28+G42+G58 -> 5739000 | H73: =H10+H28+H42+H58 -> 6882600 | I73: =I10+I28+I42+I58 -> 6867800 | J73: =J10+J28+J42+J58 -> 6197400 | K73: =K10+K28+K42+K58 -> 6050600 | ... O73: =O10+O28+O42+O58 -> 9689940 | P73: =SUM(D73:E73) -> 19485000 | Q73: =Q10+Q28 -> 81031650
C74: 退货率 | D74: =1-D73/D72 -> 0.69696306 | E74: =1-E73/E72 -> 0.73160871 | F74: =1-F73/F72 -> 0.76522979 | G74: =1-G73/G72 -> 0.74079623 | H74: =1-H73/H72 -> 0.74188637 | I74: =1-I73/I72 -> 0.76003773 | J74: =1-J73/J72 -> 0.74712231 | K74: =1-K73/K72 -> 0.73580089 | ... Q74: =1-Q73/Q72 -> 0.73538676
C75: 投放费比 | D75: =(D10*D12+D28*D30+D58*D60)/D73 -> 0.047868966 | E75: =(E10*E12+E28*E30+E58*E60)/E73 -> 0.046080597 | F75: =(F10*F12+F28*F30+F58*F60)/F73 -> 0.037249899 | G75: =(G10*G12+G28*G30+G58*G60)/G73 -> 0.040914794 | H75: =(H10*H12+H28*H30+H58*H60)/H73 -> 0.040809868 | I75: =(I10*I12+I28*I30+I58*I60)/I73 -> 0.041269985 | J75: =(J10*J12+J28*J30+J58*J60)/J73 -> 0.042198664 | K75: =(K10*K12+K28*K30+K58*K60)/K73 -> 0.042147556 | ... Q75: =(Q10*Q12+Q28*Q30+Q58*Q60)/Q73 -> 0.04851869
B76: 目标达成率 | C76: GMV | D76: =D65/D72 -> 1.061631 | E76: =E65/E72 -> 1.3716971 | F76: =F65/F72 -> 0.27322098 | G76: =G65/G72 -> 0 | H76: =H65/H72 -> 0 | I76: =I65/I72 -> 0 | J76: =J65/J72 -> 0 | K76: =K65/K72 -> 0 | ... Q76: =Q65/Q72 -> 0.25636095
C77: NET | D77: =D66/D73 -> 0.98084614 | E77: =E66/E73 -> 1.3322729 | F77: =F66/F73 -> 0.29067429 | G77: =G66/G73 -> 0 | H77: =H66/H73 -> 0 | I77: =I66/I73 -> 0 | J77: =J66/J73 -> 0 | K77: =K66/K73 -> 0 | ... Q77: =Q66/Q73 -> 0.25842432
C78: 退货率 | D78: =D67/D74 -> 1.0330858 | E78: =E67/E74 -> 1.0105437 | F78: =F67/F74 -> 0.98040186 | G78: =G67/G74 -> #DIV/0! | H78: =H67/H74 -> #DIV/0! | I78: =I67/I74 -> #DIV/0! | J78: =J67/J74 -> #DIV/0! | K78: =K67/K74 -> #DIV/0! | ... Q78: =Q67/Q74 -> 0.99710385
C79: 投放费比 | D79: =D71/D75 -> 1.137989 | E79: =E71/E75 -> 1.1723729 | F79: =F71/F75 -> 1.1854569 | G79: =G71/G75 -> #DIV/0! | H79: =H71/H75 -> #DIV/0! | I79: =I71/I75 -> #DIV/0! | J79: =J71/J75 -> #DIV/0! | K79: =K71/K75 -> #DIV/0! | ... Q79: =Q71/Q75 -> 1.1260939
A80: GXG | B80: 2025年实际 | C80: GMV | D80: 15035838 | E80: 6108020.2 | F80: 6428975.5 | G80: 5542270.2 | H80: 4632434.3 | I80: 4093008.5 | J80: 5168530.9 | K80: 3702757.5 | L80: 6335151.3 | M80: 8528298.5 | N80: 15167700 | O80: 20116713 | P80: =SUM(D80:E80) -> 21143858 | Q80: =SUM(D80:O80) -> 1.008597e+08
C81: NET | D81: 7044181.2 | E81: 3157100.1 | F81: 3291187.9 | G81: 3539119.5 | H81: 2607807.7 | I81: 2615814.4 | J81: 3327958.4 | K81: 1899367.5 | L81: 3574405.4 | M81: 3736691.4 | N81: 5842898.2 | O81: 9689345.8 | P81: =SUM(D81:E81) -> 10201281 | Q81: =SUM(D81:O81) -> 50325878
C82: 退货率 | D82: =1-D81/D80 -> 0.53150725 | E82: =1-E81/E80 -> 0.4831222 | F82: =1-F81/F80 -> 0.48806961 | G82: =1-G81/G80 -> 0.36143145 | H82: =1-H81/H80 -> 0.43705456 | I82: =1-I81/I80 -> 0.36090667 | J82: =1-J81/J80 -> 0.35611135 | K82: =1-K81/K80 -> 0.48703971 | ... Q82: =1-Q81/Q80 -> 0.50103085
C83: 成交退款金额 | D83: =D80-D81 -> 7991657.1 | E83: =E80-E81 -> 2950920.1 | F83: =F80-F81 -> 3137787.6 | G83: =G80-G81 -> 2003150.8 | H83: =H80-H81 -> 2024626.5 | I83: =I80-I81 -> 1477194.1 | J83: =J80-J81 -> 1840572.5 | K83: =K80-K81 -> 1803389.9 | ... O83: =O80-O81 -> 10427367 | P83: =SUM(D83:E83) -> 10942577 | Q83: =SUM(D83:O83) -> 50533821
A84: DAZZLE抖音 | B84: 2025年实际 | C84: GMV | D84: 14085918 | E84: 11645113 | F84: 13535430 | G84: 11149820 | H84: 22002324 | I84: 17431026 | J84: 15838455 | K84: 10982584 | L84: 14318715 | M84: 23966280 | N84: 20098622 | O84: 25774381 | P84: =SUM(D84:E84) -> 25731031 | Q84: =SUM(D84:O84) -> 2.0082867e+08
C85: NET | D85: 2336167.7 | E85: 2131932.3 | F85: 1527858 | G85: 2272772.7 | H85: 3348178.9 | I85: 1932060.6 | J85: 1488176.7 | K85: 1810748.4 | L85: 2348319.8 | M85: 3647072.3 | N85: 1794528.4 | O85: 4202618.7 | P85: =SUM(D85:E85) -> 4468100 | Q85: =SUM(D85:O85) -> 28840434
C86: 退货率 | D86: =1-D85/D84 -> 0.83414871 | E86: =1-E85/E84 -> 0.81692472 | F86: =1-F85/F84 -> 0.88712157 | G86: =1-G85/G84 -> 0.79616059 | H86: =1-H85/H84 -> 0.84782612 | I86: =1-I85/I84 -> 0.88915968 | J86: =1-J85/J84 -> 0.90604028 | K86: =1-K85/K84 -> 0.83512547 | ... Q86: =1-Q85/Q84 -> 0.85639284
A87: DAZZLE视频号 | B87: 2025年实际 | C87: GMV | J87: 3191723 | K87: 2911151 | L87: 3144052 | M87: 2097594 | N87: 1589592 | O87: 2380304 | P87: =SUM(D87:E87) -> 0 | Q87: =SUM(D87:O87) -> 15314416
C88: NET | J88: 859217 | K88: 681876 | L88: 768234 | M88: 262306 | N88: 561845 | O88: 404458 | P88: =SUM(D88:E88) -> 0 | Q88: =SUM(D88:O88) -> 3537936
C89: 退货率 | J89: =1-J88/J87 -> 0.73079838 | K89: =1-K88/K87 -> 0.765771 | L89: =1-L88/L87 -> 0.7556548 | M89: =1-M88/M87 -> 0.87494911 | N89: =1-N88/N87 -> 0.64654767 | O89: =1-O88/O87 -> 0.83008137 | P89: =1-P88/P87 -> #DIV/0! | Q89: =1-Q88/Q87 -> 0.76898003

Sheet 2026年-周目标
A1: 品牌 | D1: 1.1-1.4 | E1: 1.5-1.11 | F1: 1.12-1.18 | G1: 1.19-1.25 | H1: 1.26-2.1 | I1: 2.2-2.8 | J1: 2.9-2.15 | K1: 2.16-2.22 | L1: 2.23-3.1 | M1: 3.2-3.8 | N1: 周环比 | O1: 达成/未达成原因 | P1: 后期措施 | Q1: W10重点工作&成果 | S1: W11重点工作安排
D2: W1 | E2: W2 | F2: W3 | G2: W4 | H2: W5 | I2: W6 | J2: W7 | K2: W8 | L2: W9 | M2: W10
A3: GXG | B3: 实际 | C3: GMV | D3: =SUMIF('GXG-日报'!$E:$E,D$2,'GXG-日报'!$F:$F) -> 2454809.4 | E3: =SUMIF('GXG-日报'!$E:$E,E$2,'GXG-日报'!$F:$F) -> 4472122.1 | F3: =SUMIF('GXG-日报'!$E:$E,F$2,'GXG-日报'!$F:$F) -> 2967577.7 | G3: =SUMIF('GXG-日报'!$E:$E,G$2,'GXG-日报'!$F:$F) -> 4606145.8 | H3: =SUMIF('GXG-日报'!$E:$E,H$2,'GXG-日报'!$F:$F) -> 4816637.9 | I3: =SUMIF('GXG-日报'!$E:$E,I$2,'GXG-日报'!$F:$F) -> 8272352 | J3: =SUMIF('GXG-日报'!$E:$E,J$2,'GXG-日报'!$F:$F) -> 4130552.9 | K3: =SUMIF('GXG-日报'!$E:$E,K$2,'GXG-日报'!$F:$F) -> 331005.2 | ... M3: =SUMIF('GXG-日报'!$E:$E,M$2,'GXG-日报'!$F:$F) -> 1914906.3 | N3: =M3/L3-1 -> 0.0023505354 | O3: 1、本周主播千喜临时调休4天，任真休假，主播以可可、周周、双胞胎为主，其中可可打款皮衣效能较好2W；周末任真、千喜回归，打款西装效能较好 | Q3: 1 | R3: 3.6平台&品牌会议报告完成 | S3: 1 | T3: 先锋大赛交稿
C4: NET | D4: =SUMIF('GXG-日报'!$E:$E,D$2,'GXG-日报'!$H:$H) -> 1136394.9 | E4: =SUMIF('GXG-日报'!$E:$E,E$2,'GXG-日报'!$H:$H) -> 1962965.2 | F4: =SUMIF('GXG-日报'!$E:$E,F$2,'GXG-日报'!$H:$H) -> 884420.8 | G4: =SUMIF('GXG-日报'!$E:$E,G$2,'GXG-日报'!$H:$H) -> 2449130.4 | H4: =SUMIF('GXG-日报'!$E:$E,H$2,'GXG-日报'!$H:$H) -> 2081978.3 | I4: =SUMIF('GXG-日报'!$E:$E,I$2,'GXG-日报'!$H:$H) -> 3898600.9 | J4: =SUMIF('GXG-日报'!$E:$E,J$2,'GXG-日报'!$H:$H) -> 961150.59 | K4: =SUMIF('GXG-日报'!$E:$E,K$2,'GXG-日报'!$H:$H) -> -157222.28 | ... M4: =SUMIF('GXG-日报'!$E:$E,M$2,'GXG-日报'!$H:$H) -> 904305.73 | N4: =M4/L4-1 -> 0.011633714 | Q4: 2 | S4: 2 | T4: 26年春季3-4月打款计划全盘
C5: 退货率 | D5: =1-D4/D3 -> 0.53707407 | E5: =1-E4/E3 -> 0.56106629 | F5: =1-F4/F3 -> 0.70197215 | G5: =1-G4/G3 -> 0.46829073 | H5: =1-H4/H3 -> 0.5677528 | I5: =1-I4/I3 -> 0.52871917 | J5: =1-J4/J3 -> 0.76730704 | K5: =1-K4/K3 -> 1.4749843 | ... M5: =1-M4/M3 -> 0.52775458 | N5: =M5/L5-1 -> -0.0081443723 | Q5: 3 | S5: 3 | T5: 商品卡全盘
C6: 商品卡GMV | D6: =SUMIF('GXG-日报'!$E:$E,D$2,'GXG-日报'!$I:$I) -> 249797.42 | E6: =SUMIF('GXG-日报'!$E:$E,E$2,'GXG-日报'!$I:$I) -> 419091.35 | F6: =SUMIF('GXG-日报'!$E:$E,F$2,'GXG-日报'!$I:$I) -> 475345.5 | G6: =SUMIF('GXG-日报'!$E:$E,G$2,'GXG-日报'!$I:$I) -> 766161.6 | H6: =SUMIF('GXG-日报'!$E:$E,H$2,'GXG-日报'!$I:$I) -> 984376.4 | I6: =SUMIF('GXG-日报'!$E:$E,I$2,'GXG-日报'!$I:$I) -> 1423772.5 | J6: =SUMIF('GXG-日报'!$E:$E,J$2,'GXG-日报'!$I:$I) -> 614786.3 | K6: =SUMIF('GXG-日报'!$E:$E,K$2,'GXG-日报'!$I:$I) -> 74016.2 | ... M6: =SUMIF('GXG-日报'!$E:$E,M$2,'GXG-日报'!$I:$I) -> 240644.6 | N6: =M6/L6-1 -> 0.27655875 | Q6: 4 | S6: 4 | T6: 26年秋季款下单计划盘点
C7: 商品卡占比 | D7: =D6/D3 -> 0.10175838 | E7: =E6/E3 -> 0.093711965 | F7: =F6/F3 -> 0.16017963 | G7: =G6/G3 -> 0.16633464 | H7: =H6/H3 -> 0.20437002 | I7: =I6/I3 -> 0.17211218 | J7: =J6/J3 -> 0.14883874 | K7: =K6/K3 -> 0.22361038 | ... M7: =M6/M3 -> 0.12566913 | N7: =M7/L7-1 -> 0.27356519 | Q7: 5 | S7: 5
C8: 投放消耗金额 | D8: =SUMIF('GXG-日报'!$E:$E,D$2,'GXG-日报'!$K:$K) -> 81402.31 | E8: =SUMIF('GXG-日报'!$E:$E,E$2,'GXG-日报'!$K:$K) -> 145657.56 | F8: =SUMIF('GXG-日报'!$E:$E,F$2,'GXG-日报'!$K:$K) -> 80162.01 | G8: =SUMIF('GXG-日报'!$E:$E,G$2,'GXG-日报'!$K:$K) -> 127649.27 | H8: =SUMIF('GXG-日报'!$E:$E,H$2,'GXG-日报'!$K:$K) -> 130671.33 | I8: =SUMIF('GXG-日报'!$E:$E,I$2,'GXG-日报'!$K:$K) -> 219375.53 | J8: =SUMIF('GXG-日报'!$E:$E,J$2,'GXG-日报'!$K:$K) -> 108471.95 | K8: =SUMIF('GXG-日报'!$E:$E,K$2,'GXG-日报'!$K:$K) -> 7787.9 | ... M8: =SUMIF('GXG-日报'!$E:$E,M$2,'GXG-日报'!$K:$K) -> 56373.81 | N8: =M8/L8-1 -> 0.0069698971 | Q8: 6 | S8: 6
C9: 投放费比 | D9: =D8/D4 -> 0.07163206 | E9: =E8/E4 -> 0.074202824 | F9: =F8/F4 -> 0.090637862 | G9: =G8/G4 -> 0.052120242 | H9: =H8/H4 -> 0.062763062 | I9: =I8/I4 -> 0.056270322 | J9: =J8/J4 -> 0.11285635 | K9: =K8/K4 -> -0.049534328 | ... M9: =M8/M4 -> 0.062339326 | N9: =M9/L9-1 -> -0.0046101834 | Q9: 7 | S9: 7
B10: 目标 | C10: GMV | D10: 2000000 | E10: 3500000 | F10: 3500000 | G10: 3500000 | H10: 3500000 | I10: 3500000 | J10: 3500000 | K10: 3500000 | L10: 3500000 | M10: 2000000 | N10: =M10/L10-1 -> -0.42857143 | Q10: 8 | S10: 8
C11: NET | D11: =D10*(1-55%) -> 900000 | E11: =E10*(1-55%) -> 1575000 | F11: =F10*(1-55%) -> 1575000 | G11: =G10*(1-55%) -> 1575000 | H11: =H10*(1-55%) -> 1575000 | I11: =I10*(1-55%) -> 1575000 | J11: =J10*(1-55%) -> 1575000 | K11: =K10*(1-55%) -> 1575000 | ... M11: =M10*(1-55%) -> 900000 | N11: =M11/L11-1 -> -0.42857143 | Q11: 9 | S11: 9
C12: 退货率 | D12: =1-D11/D10 -> 0.55 | E12: =1-E11/E10 -> 0.55 | F12: =1-F11/F10 -> 0.55 | G12: =1-G11/G10 -> 0.55 | H12: =1-H11/H10 -> 0.55 | I12: =1-I11/I10 -> 0.55 | J12: =1-J11/J10 -> 0.55 | K12: =1-K11/K10 -> 0.55 | ... M12: =1-M11/M10 -> 0.55 | N12: =M12/L12-1 -> 0 | Q12: 10 | S12: 10
C13: 投放费比 | D13: 0.05 | E13: 0.05 | F13: 0.05 | G13: 0.05 | H13: 0.05 | I13: 0.05 | J13: 0.05 | K13: 0.05 | L13: 0.05 | M13: 0.05 | N13: =M13/L13-1 -> 0 | Q13: 11 | S13: 11
B14: 目标达成率 | C14: GMV | D14: =D3/D10 -> 1.2274047 | E14: =E3/E10 -> 1.2777492 | F14: =F3/F10 -> 0.84787934 | G14: =G3/G10 -> 1.3160417 | H14: =H3/H10 -> 1.3761823 | I14: =I3/I10 -> 2.3635291 | J14: =J3/J10 -> 1.180158 | K14: =K3/K10 -> 0.094572914 | ... M14: =M3/M10 -> 0.95745315 | N14: =M14/L14-1 -> 0.75411344 | Q14: 12 | S14: 12
C15: NET | D15: =D4/D11 -> 1.262661 | E15: =E4/E11 -> 1.2463271 | F15: =F4/F11 -> 0.56153702 | G15: =G4/G11 -> 1.5550034 | H15: =H4/H11 -> 1.321891 | I15: =I4/I11 -> 2.4753022 | J15: =J4/J11 -> 0.61025434 | K15: =K4/K11 -> -0.09982367 | ... M15: =M4/M11 -> 1.0047841 | N15: =M15/L15-1 -> 0.770359 | Q15: 13 | S15: 13
C16: 退货率 | D16: =D5/D12 -> 0.9764983 | E16: =E5/E12 -> 1.0201205 | F16: =F5/F12 -> 1.276313 | G16: =G5/G12 -> 0.85143769 | H16: =H5/H12 -> 1.0322778 | I16: =I5/I12 -> 0.96130758 | J16: =J5/J12 -> 1.3951037 | K16: =K5/K12 -> 2.6817897 | ... M16: =M5/M12 -> 0.95955378 | N16: =M16/L16-1 -> -0.0081443723 | Q16: 14 | S16: 14
C17: 投放费比 | D17: =D9/D13 -> 1.4326412 | E17: =E9/E13 -> 1.4840565 | F17: =F9/F13 -> 1.8127572 | G17: =G9/G13 -> 1.0424048 | H17: =H9/H13 -> 1.2552612 | I17: =I9/I13 -> 1.1254064 | J17: =J9/J13 -> 2.2571271 | K17: =K9/K13 -> -0.99068656 | ... M17: =M9/M13 -> 1.2467865 | N17: =M17/L17-1 -> -0.0046101834 | Q17: 15 | S17: 15
A18: 品牌 | D18: W1 | E18: W2 | F18: W3 | G18: W4 | H18: W5 | I18: W6 | J18: W7 | K18: W8 | L18: W9 | M18: W10 | N18: 周环比 | O18: 达成/未达成原因 | P18: 后期措施 | Q18: W10重点工作&成果 | S18: W11重点工作安排
A19: DAZZLE 抖音 | B19: 实际 | C19: GMV | D19: =SUMIF('DAZZLE-日报'!$E:$E,D$18,'DAZZLE-日报'!$F:$F) -> 2304116 | E19: =SUMIF('DAZZLE-日报'!$E:$E,E$18,'DAZZLE-日报'!$F:$F) -> 4544258 | F19: =SUMIF('DAZZLE-日报'!$E:$E,F$18,'DAZZLE-日报'!$F:$F) -> 5227052 | G19: =SUMIF('DAZZLE-日报'!$E:$E,G$18,'DAZZLE-日报'!$F:$F) -> 5660742.6 | H19: =SUMIF('DAZZLE-日报'!$E:$E,H$18,'DAZZLE-日报'!$F:$F) -> 5716888.5 | I19: =SUMIF('DAZZLE-日报'!$E:$E,I$18,'DAZZLE-日报'!$F:$F) -> 5612308.4 | J19: =SUMIF('DAZZLE-日报'!$E:$E,J$18,'DAZZLE-日报'!$F:$F) -> 4373896.6 | K19: =SUMIF('DAZZLE-日报'!$E:$E,K$18,'DAZZLE-日报'!$F:$F) -> 1286931.7 | ... M19: =SUMIF('DAZZLE-日报'!$E:$E,M$18,'DAZZLE-日报'!$F:$F) -> 4198718.8 | N19: =M19/L19-1 -> 0.13382691 | Q19: 1 | R19: 4月内容场跟进 | S19: 1 | T19: 先锋大赛交稿
C20: NET | D20: =SUMIF('DAZZLE-日报'!$E:$E,D$18,'DAZZLE-日报'!$H:$H) -> -12713.3 | E20: =SUMIF('DAZZLE-日报'!$E:$E,E$18,'DAZZLE-日报'!$H:$H) -> 834747.6 | F20: =SUMIF('DAZZLE-日报'!$E:$E,F$18,'DAZZLE-日报'!$H:$H) -> 1003570.1 | G20: =SUMIF('DAZZLE-日报'!$E:$E,G$18,'DAZZLE-日报'!$H:$H) -> 462810.78 | H20: =SUMIF('DAZZLE-日报'!$E:$E,H$18,'DAZZLE-日报'!$H:$H) -> 889985.41 | I20: =SUMIF('DAZZLE-日报'!$E:$E,I$18,'DAZZLE-日报'!$H:$H) -> 770013.94 | J20: =SUMIF('DAZZLE-日报'!$E:$E,J$18,'DAZZLE-日报'!$H:$H) -> 616238.78 | K20: =SUMIF('DAZZLE-日报'!$E:$E,K$18,'DAZZLE-日报'!$H:$H) -> 705347.45 | ... M20: =SUMIF('DAZZLE-日报'!$E:$E,M$18,'DAZZLE-日报'!$H:$H) -> 538936.23 | N20: =M20/L20-1 -> 3.6467555 | Q20: 2 | R20: 主播灿灿沟通协商 | S20: 2 | T20: 秋冬订货资料梳理跟进
C21: 退货率 | D21: =1-D20/D19 -> 1.0055176 | E21: =1-E20/E19 -> 0.81630717 | F21: =1-F20/F19 -> 0.80800458 | G21: =1-G20/G19 -> 0.91824204 | H21: =1-H20/H19 -> 0.84432346 | I21: =1-I20/I19 -> 0.86279907 | J21: =1-J20/J19 -> 0.85910989 | K21: =1-K20/K19 -> 0.45191538 | ... M21: =1-M20/M19 -> 0.8716427 | N21: =M21/L21-1 -> -0.10017506 | Q21: 3 | S21: 3 | T21: 主播小鱼沟通协商
C22: 商品卡GMV | D22: =SUMIF('DAZZLE-日报'!$E:$E,D$18,'DAZZLE-日报'!$I:$I) -> 649679.93 | E22: =SUMIF('DAZZLE-日报'!$E:$E,E$18,'DAZZLE-日报'!$I:$I) -> 971970.08 | F22: =SUMIF('DAZZLE-日报'!$E:$E,F$18,'DAZZLE-日报'!$I:$I) -> 1371054.4 | G22: =SUMIF('DAZZLE-日报'!$E:$E,G$18,'DAZZLE-日报'!$I:$I) -> 2123815.6 | H22: =SUMIF('DAZZLE-日报'!$E:$E,H$18,'DAZZLE-日报'!$I:$I) -> 2063635 | I22: =SUMIF('DAZZLE-日报'!$E:$E,I$18,'DAZZLE-日报'!$I:$I) -> 2236801.1 | J22: =SUMIF('DAZZLE-日报'!$E:$E,J$18,'DAZZLE-日报'!$I:$I) -> 1415399.3 | K22: =SUMIF('DAZZLE-日报'!$E:$E,K$18,'DAZZLE-日报'!$I:$I) -> 595333.78 | ... M22: =SUMIF('DAZZLE-日报'!$E:$E,M$18,'DAZZLE-日报'!$I:$I) -> 1656604.6 | N22: =M22/L22-1 -> 0.62964889 | Q22: 4 | S22: 4
C23: 商品卡占比 | D23: =D22/D19 -> 0.28196494 | E23: =E22/E19 -> 0.21388972 | F23: =F22/F19 -> 0.26229974 | G23: =G22/G19 -> 0.37518322 | H23: =H22/H19 -> 0.3609717 | I23: =I22/I19 -> 0.39855279 | J23: =J22/J19 -> 0.32360146 | K23: =K22/K19 -> 0.46259937 | ... M23: =M22/M19 -> 0.39455001 | N23: =M23/L23-1 -> 0.43729954 | Q23: 5 | S23: 5
C24: 投放消耗金额 | D24: =SUMIF('DAZZLE-日报'!$E:$E,D$18,'DAZZLE-日报'!$K:$K) -> 8995.83 | E24: =SUMIF('DAZZLE-日报'!$E:$E,E$18,'DAZZLE-日报'!$K:$K) -> 16811.44 | F24: =SUMIF('DAZZLE-日报'!$E:$E,F$18,'DAZZLE-日报'!$K:$K) -> 16632.25 | G24: =SUMIF('DAZZLE-日报'!$E:$E,G$18,'DAZZLE-日报'!$K:$K) -> 14811.17 | H24: =SUMIF('DAZZLE-日报'!$E:$E,H$18,'DAZZLE-日报'!$K:$K) -> 17959.67 | I24: =SUMIF('DAZZLE-日报'!$E:$E,I$18,'DAZZLE-日报'!$K:$K) -> 15945.6 | J24: =SUMIF('DAZZLE-日报'!$E:$E,J$18,'DAZZLE-日报'!$K:$K) -> 13574.59 | K24: =SUMIF('DAZZLE-日报'!$E:$E,K$18,'DAZZLE-日报'!$K:$K) -> 3247.74 | ... M24: =SUMIF('DAZZLE-日报'!$E:$E,M$18,'DAZZLE-日报'!$K:$K) -> 10588.05 | N24: =M24/L24-1 -> -0.11903973 | Q24: 6 | S24: 6
C25: 投放费比 | D25: =D24/D20 -> -0.70759205 | E25: =E24/E20 -> 0.020139549 | F25: =F24/F20 -> 0.016573083 | G25: =G24/G20 -> 0.032002647 | H25: =H24/H20 -> 0.020179735 | I25: =I24/I20 -> 0.020708197 | J25: =J24/J20 -> 0.022028133 | K25: =K24/K20 -> 0.0046044542 | ... M25: =M24/M20 -> 0.019646202 | N25: =M25/L25-1 -> -0.8104139 | Q25: 7 | S25: 7
B26: 目标 | C26: GMV | D26: 2400000 | E26: 4200000 | F26: 4200000 | G26: 4200000 | H26: 4200000 | I26: 3000000 | J26: 3000000 | K26: 2000000 | L26: 3000000 | M26: 4000000 | N26: =M26/L26-1 -> 0.33333333 | Q26: 8 | S26: 8
C27: NET | D27: =D26*(1-84%) -> 384000 | E27: =E26*(1-84%) -> 672000 | F27: =F26*(1-84%) -> 672000 | G27: =G26*(1-84%) -> 672000 | H27: =H26*(1-84%) -> 672000 | I27: =I26*(1-85%) -> 450000 | J27: =J26*(1-85%) -> 450000 | K27: =K26*(1-85%) -> 300000 | L27: =L26*(1-85%) -> 450000 | M27: =M26*(1-85%) -> 600000 | N27: =M27/L27-1 -> 0.33333333 | Q27: 9 | S27: 9
C28: 退货率 | D28: =1-D27/D26 -> 0.84 | E28: =1-E27/E26 -> 0.84 | F28: =1-F27/F26 -> 0.84 | G28: =1-G27/G26 -> 0.84 | H28: =1-H27/H26 -> 0.84 | I28: =1-I27/I26 -> 0.85 | J28: =1-J27/J26 -> 0.85 | K28: =1-K27/K26 -> 0.85 | ... M28: =1-M27/M26 -> 0.85 | N28: =M28/L28-1 -> 0 | Q28: 10 | S28: 10
C29: 投放费比 | D29: 0.03 | E29: 0.03 | F29: 0.03 | G29: 0.03 | H29: 0.03 | I29: 0.03 | J29: 0.03 | K29: 0.03 | L29: 0.03 | M29: 0.03 | N29: =M29/L29-1 -> 0 | Q29: 11 | S29: 11
B30: 目标达成率 | C30: GMV | D30: =D19/D26 -> 0.96004833 | E30: =E19/E26 -> 1.0819662 | F30: =F19/F26 -> 1.2445362 | G30: =G19/G26 -> 1.3477959 | H30: =H19/H26 -> 1.3611639 | I30: =I19/I26 -> 1.8707695 | J30: =J19/J26 -> 1.4579655 | K30: =K19/K26 -> 0.64346583 | ... M30: =M19/M26 -> 1.0496797 | N30: =M30/L30-1 -> -0.14962982 | Q30: 12 | S30: 12
C31: NET | D31: =D20/D27 -> -0.033107552 | E31: =E20/E27 -> 1.2421839 | F31: =F20/F27 -> 1.4934078 | G31: =G20/G27 -> 0.68870652 | H31: =H20/H27 -> 1.3243831 | I31: =I20/I27 -> 1.7111421 | J31: =J20/J27 -> 1.3694195 | K31: =K20/K27 -> 2.3511582 | ... M31: =M20/M27 -> 0.89822705 | N31: =M31/L31-1 -> 2.4850666 | Q31: 13 | S31: 13
C32: 退货率 | D32: =D21/D28 -> 1.1970448 | E32: =E21/E28 -> 0.97179425 | F32: =F21/F28 -> 0.96191021 | G32: =G21/G28 -> 1.0931453 | H32: =H21/H28 -> 1.005147 | I32: =I21/I28 -> 1.0150577 | J32: =J21/J28 -> 1.0107175 | K32: =K21/K28 -> 0.53166516 | ... M32: =M21/M28 -> 1.025462 | N32: =M32/L32-1 -> -0.10017506 | Q32: 14 | S32: 14
C33: 投放费比 | D33: =D25/D29 -> -23.586402 | E33: =E25/E29 -> 0.67131829 | F33: =F25/F29 -> 0.5524361 | G33: =G25/G29 -> 1.0667549 | H33: =H25/H29 -> 0.67265784 | I33: =I25/I29 -> 0.69027322 | J33: =J25/J29 -> 0.73427111 | K33: =K25/K29 -> 0.15348181 | ... M33: =M25/M29 -> 0.6548734 | N33: =M33/L33-1 -> -0.8104139 | Q33: 15 | S33: 15
A34: 品牌 | D34: W1 | E34: W2 | F34: W3 | G34: W4 | H34: W5 | I34: W6 | J34: W7 | K34: W8 | L34: W9 | M34: W10 | N34: 周环比 | O34: 达成/未达成原因 | P34: 后期措施 | Q34: W10重点工作&成果 | S34: W11重点工作安排
A35: DAZZLE 视频号 | B35: 实际 | C35: GMV | D35: =SUMIF('DAZZLE（视频号）-日报'!$E:$E,D$34,'DAZZLE（视频号）-日报'!$F:$F) -> 168425 | E35: =SUMIF('DAZZLE（视频号）-日报'!$E:$E,E$34,'DAZZLE（视频号）-日报'!$F:$F) -> 451947 | F35: =SUMIF('DAZZLE（视频号）-日报'!$E:$E,F$34,'DAZZLE（视频号）-日报'!$F:$F) -> 451358 | G35: =SUMIF('DAZZLE（视频号）-日报'!$E:$E,G$34,'DAZZLE（视频号）-日报'!$F:$F) -> 362779 | H35: =SUMIF('DAZZLE（视频号）-日报'!$E:$E,H$34,'DAZZLE（视频号）-日报'!$F:$F) -> 328764 | I35: =SUMIF('DAZZLE（视频号）-日报'!$E:$E,I$34,'DAZZLE（视频号）-日报'!$F:$F) -> 297402 | J35: =SUMIF('DAZZLE（视频号）-日报'!$E:$E,J$34,'DAZZLE（视频号）-日报'!$F:$F) -> 378348 | K35: =SUMIF('DAZZLE（视频号）-日报'!$E:$E,K$34,'DAZZLE（视频号）-日报'!$F:$F) -> 195708 | ... M35: =SUMIF('DAZZLE（视频号）-日报'!$E:$E,M$34,'DAZZLE（视频号）-日报'!$F:$F) -> 430167 | N35: =M35/L35-1 -> 0.20333839 | Q35: 1 | S35: 1
C36: NET | D36: =SUMIF('DAZZLE（视频号）-日报'!$E:$E,D$34,'DAZZLE（视频号）-日报'!$G:$G) -> 7352.03 | E36: =SUMIF('DAZZLE（视频号）-日报'!$E:$E,E$34,'DAZZLE（视频号）-日报'!$G:$G) -> 125929 | F36: =SUMIF('DAZZLE（视频号）-日报'!$E:$E,F$34,'DAZZLE（视频号）-日报'!$G:$G) -> 53154 | G36: =SUMIF('DAZZLE（视频号）-日报'!$E:$E,G$34,'DAZZLE（视频号）-日报'!$G:$G) -> 21738.25 | H36: =SUMIF('DAZZLE（视频号）-日报'!$E:$E,H$34,'DAZZLE（视频号）-日报'!$G:$G) -> 58085.32 | I36: =SUMIF('DAZZLE（视频号）-日报'!$E:$E,I$34,'DAZZLE（视频号）-日报'!$G:$G) -> 37837.39 | J36: =SUMIF('DAZZLE（视频号）-日报'!$E:$E,J$34,'DAZZLE（视频号）-日报'!$G:$G) -> 107610.75 | K36: =SUMIF('DAZZLE（视频号）-日报'!$E:$E,K$34,'DAZZLE（视频号）-日报'!$G:$G) -> 130656 | ... M36: =SUMIF('DAZZLE（视频号）-日报'!$E:$E,M$34,'DAZZLE（视频号）-日报'!$G:$G) -> 118456 | N36: =M36/L36-1 -> 1.9790232 | Q36: 2 | S36: 2
C37: 退货率 | D37: =1-D36/D35 -> 0.95634834 | E37: =1-E36/E35 -> 0.72136335 | F37: =1-F36/F35 -> 0.88223539 | G37: =1-G36/G35 -> 0.94007853 | H37: =1-H36/H35 -> 0.82332214 | I37: =1-I36/I35 -> 0.87277359 | J37: =1-J36/J35 -> 0.71557733 | K37: =1-K36/K35 -> 0.33239316 | ... M37: =1-M36/M35 -> 0.72462788 | N37: =M37/L37-1 -> -0.18468179 | Q37: 3 | S37: 3
B38: 目标 | C38: GMV | D38: 800000 | E38: 1400000 | F38: 1400000 | G38: 1400000 | H38: 1400000 | I38: 650000 | J38: 650000 | K38: 650000 | L38: 650000 | M38: 650000 | N38: =M38/L38-1 -> 0 | Q38: 8 | S38: 8
C39: NET | D39: =D38*0.2 -> 160000 | E39: =E38*0.2 -> 280000 | F39: =F38*0.2 -> 280000 | G39: =G38*0.23 -> 322000 | H39: =H38*0.23 -> 322000 | I39: =I38*0.22 -> 143000 | J39: =J38*0.22 -> 143000 | K39: =K38*0.22 -> 143000 | L39: =L38*0.22 -> 143000 | M39: =M38*0.22 -> 143000 | N39: =M39/L39-1 -> 0 | Q39: 9 | S39: 9
C40: 退货率 | D40: =1-D39/D38 -> 0.8 | E40: =1-E39/E38 -> 0.8 | F40: =1-F39/F38 -> 0.8 | G40: =1-G39/G38 -> 0.77 | H40: =1-H39/H38 -> 0.77 | I40: =1-I39/I38 -> 0.78 | J40: =1-J39/J38 -> 0.78 | K40: =1-K39/K38 -> 0.78 | ... M40: =1-M39/M38 -> 0.78 | N40: =M40/L40-1 -> 0 | Q40: 10 | S40: 10
B41: 目标达成率 | C41: GMV | D41: =D35/D38 -> 0.21053125 | E41: =E35/E38 -> 0.32281929 | F41: =F35/F38 -> 0.32239857 | G41: =G35/G38 -> 0.25912786 | H41: =H35/H38 -> 0.23483143 | I41: =I35/I38 -> 0.45754154 | J41: =J35/J38 -> 0.58207385 | K41: =K35/K38 -> 0.30108923 | ... M41: =M35/M38 -> 0.66179538 | N41: =M41/L41-1 -> 0.20333839 | Q41: 12 | S41: 12
C42: NET | D42: =D36/D39 -> 0.045950188 | E42: =E36/E39 -> 0.44974643 | F42: =F36/F39 -> 0.18983571 | G42: =G36/G39 -> 0.067510093 | H42: =H36/H39 -> 0.18038919 | I42: =I36/I39 -> 0.26459713 | J42: =J36/J39 -> 0.75252273 | K42: =K36/K39 -> 0.91367832 | ... M42: =M36/M39 -> 0.82836364 | N42: =M42/L42-1 -> 1.9790232 | Q42: 13 | S42: 13
C43: 退货率 | D43: =D37/D40 -> 1.1954354 | E43: =E37/E40 -> 0.90170418 | F43: =F37/F40 -> 1.1027942 | G43: =G37/G40 -> 1.2208812 | H43: =H37/H40 -> 1.0692495 | I43: =I37/I40 -> 1.1189405 | J43: =J37/J40 -> 0.91740683 | K43: =K37/K40 -> 0.42614507 | ... M43: =M37/M40 -> 0.9290101 | N43: =M43/L43-1 -> -0.18468179 | Q43: 14 | S43: 14
A44: 品牌 | D44: W1 | E44: W2 | F44: W3 | G44: W4 | H44: W5 | N44: =L44/K44-1 -> #DIV/0! | O44: 达成/未达成原因 | P44: 后期措施 | Q44: W5重点工作&成果 | S44: W6重点工作&成果
A45: Champion 抖音 | B45: 实际 | C45: GMV | D45: =SUMIF('Champion-日报'!$E:$E,D$44,'Champion-日报'!$F:$F) -> 603443.24 | E45: =SUMIF('Champion-日报'!$E:$E,E$44,'Champion-日报'!$F:$F) -> 846358.68 | F45: =SUMIF('Champion-日报'!$E:$E,F$44,'Champion-日报'!$F:$F) -> 905616.29 | G45: =SUMIF('Champion-日报'!$E:$E,G$44,'Champion-日报'!$F:$F) -> 1305928.7 | H45: =SUMIF('Champion-日报'!$E:$E,H$44,'Champion-日报'!$F:$F) -> 0 | N45: =L45/K45-1 -> #DIV/0! | Q45: 1 | R45: 冠军人员沟通安排：已完成 | S45: 1 | T45: 冠军样品处理完成to品牌
C46: NET | D46: =SUMIF('Champion-日报'!$E:$E,D$44,'Champion-日报'!$G:$G) -> 136313.43 | E46: =SUMIF('Champion-日报'!$E:$E,E$44,'Champion-日报'!$G:$G) -> 280852.65 | F46: =SUMIF('Champion-日报'!$E:$E,F$44,'Champion-日报'!$G:$G) -> 357770.29 | G46: =SUMIF('Champion-日报'!$E:$E,G$44,'Champion-日报'!$G:$G) -> 738088.5 | H46: =SUMIF('Champion-日报'!$E:$E,H$44,'Champion-日报'!$G:$G) -> 0 | N46: =L46/K46-1 -> #DIV/0! | Q46: 2 | R46: 冠军闭店事宜处理：数据交接、系统流程、品牌知会函、财务通知已完成 | S46: 2
C47: 退货率 | D47: =1-D46/D45 -> 0.77410729 | E47: =1-E46/E45 -> 0.66816356 | F47: =1-F46/F45 -> 0.60494274 | G47: =1-G46/G45 -> 0.43481717 | H47: =1-H46/H45 -> #DIV/0! | N47: =L47/K47-1 -> #DIV/0! | Q47: 3 | R47: 冠军样品处理：有50件差异需重新核对 | S47: 3
C48: 商品卡GMV | D48: =SUMIF('Champion-日报'!$E:$E,D$44,'Champion-日报'!$H:$H) -> 153151.92 | E48: =SUMIF('Champion-日报'!$E:$E,E$44,'Champion-日报'!$H:$H) -> 249218.73 | F48: =SUMIF('Champion-日报'!$E:$E,F$44,'Champion-日报'!$H:$H) -> 355414.28 | G48: =SUMIF('Champion-日报'!$E:$E,G$44,'Champion-日报'!$H:$H) -> 605096.58 | H48: =SUMIF('Champion-日报'!$E:$E,H$44,'Champion-日报'!$H:$H) -> 0 | N48: =L48/K48-1 -> #DIV/0! | Q48: 4 | S48: 4
C49: 商品卡占比 | D49: =D48/D45 -> 0.25379673 | E49: =E48/E45 -> 0.29445994 | F49: =F48/F45 -> 0.39245571 | G49: =G48/G45 -> 0.46334579 | H49: =H48/H45 -> #DIV/0! | N49: =L49/K49-1 -> #DIV/0! | Q49: 5 | S49: 5
C50: 投放消耗金额 | D50: =SUMIF('Champion-日报'!$E:$E,D$44,'Champion-日报'!$J:$J) -> 17188.36 | E50: =SUMIF('Champion-日报'!$E:$E,E$44,'Champion-日报'!$J:$J) -> 20407.47 | F50: =SUMIF('Champion-日报'!$E:$E,F$44,'Champion-日报'!$J:$J) -> 18302.11 | G50: =SUMIF('Champion-日报'!$E:$E,G$44,'Champion-日报'!$J:$J) -> 31996.17 | H50: =SUMIF('Champion-日报'!$E:$E,H$44,'Champion-日报'!$J:$J) -> 0 | N50: =L50/K50-1 -> #DIV/0! | Q50: 6 | S50: 6
C51: 投放费比 | D51: =D50/D46 -> 0.1260944 | E51: =E50/E46 -> 0.072662551 | F51: =F50/F46 -> 0.051156036 | G51: =G50/G46 -> 0.043350045 | H51: =H50/H46 -> #DIV/0! | N51: =L51/K51-1 -> #DIV/0! | Q51: 7 | S51: 7
B52: 目标 | C52: GMV | D52: 500000 | E52: 2000000 | F52: 2400000 | G52: 2400000 | H52: 2400000 | N52: =L52/K52-1 -> #DIV/0! | Q52: 8 | S52: 8
C53: NET | D53: =D52*40% -> 200000 | E53: =E52*40% -> 800000 | F53: =F52*40% -> 960000 | G53: =G52*40% -> 960000 | H53: =H52*40% -> 960000 | N53: =L53/K53-1 -> #DIV/0! | Q53: 9 | S53: 9
C54: 退货率 | D54: =1-D53/D52 -> 0.6 | E54: =1-E53/E52 -> 0.6 | F54: =1-F53/F52 -> 0.6 | G54: =1-G53/G52 -> 0.6 | H54: =1-H53/H52 -> 0.6 | N54: =L54/K54-1 -> #DIV/0! | Q54: 10 | S54: 10
C55: 投放费比 | D55: 0.05 | E55: 0.05 | F55: 0.05 | G55: 0.05 | H55: 0.05 | N55: =L55/K55-1 -> #DIV/0! | Q55: 11 | S55: 11
B56: 目标达成率 | C56: GMV | D56: =D45/D52 -> 1.2068865 | E56: =E45/E52 -> 0.42317934 | F56: =F45/F52 -> 0.37734012 | G56: =G45/G52 -> 0.54413698 | H56: =H45/H52 -> 0 | N56: =L56/K56-1 -> #DIV/0! | Q56: 12 | S56: 12
C57: NET | D57: =D46/D53 -> 0.68156715 | E57: =E46/E53 -> 0.35106581 | F57: =F46/F53 -> 0.37267739 | G57: =G46/G53 -> 0.76884219 | H57: =H46/H53 -> 0 | N57: =L57/K57-1 -> #DIV/0! | Q57: 13 | S57: 13
C58: 退货率 | D58: =D47/D54 -> 1.2901788 | E58: =E47/E54 -> 1.1136059 | F58: =F47/F54 -> 1.0082379 | G58: =G47/G54 -> 0.72469528 | H58: =H47/H54 -> #DIV/0! | N58: =L58/K58-1 -> #DIV/0! | Q58: 14 | S58: 14
C59: 投放费比 | D59: =D51/D55 -> 2.521888 | E59: =E51/E55 -> 1.453251 | F59: =F51/F55 -> 1.0231207 | G59: =G51/G55 -> 0.86700091 | H59: =H51/H55 -> #DIV/0! | N59: =L59/K59-1 -> #DIV/0! | Q59: 15 | S59: 15

Sheet 2026年-行业竞品跟踪
A1: 行业 | B1: 子类 | C1: 1.1-1.4 | D1: 1.5-1.11 | E1: 1.12-1.18 | F1: 1.19-1.25 | G1: 1.26-2.1 | H1: 2.2-2.8 | I1: 2.9-2.15 | J1: 2.16-2.22 | K1: 2.23-3.1 | L1: 3.2-3.8 | M1: 周环比 | N1: 周关键变化
C2: W1 | D2: W2 | E2: W3 | F2: W4 | G2: W5 | H2: W6 | I2: W7 | J2: W8 | K2: W9 | L2: W10
A3: 女装 | B3: 总计 | C3: =SUMIF('女装-品类销售明细'!$C:$C,C$2,'女装-品类销售明细'!$I:$I) -> 1.5774031e+10 | D3: =SUMIF('女装-品类销售明细'!$C:$C,D$2,'女装-品类销售明细'!$I:$I) -> 2.9456159e+10 | E3: =SUMIF('女装-品类销售明细'!$C:$C,E$2,'女装-品类销售明细'!$I:$I) -> 2.8343911e+10 | F3: =SUMIF('女装-品类销售明细'!$C:$C,F$2,'女装-品类销售明细'!$I:$I) -> 2.6033953e+10 | G3: =SUMIF('女装-品类销售明细'!$C:$C,G$2,'女装-品类销售明细'!$I:$I) -> 2.3243439e+10 | H3: =SUMIF('女装-品类销售明细'!$C:$C,H$2,'女装-品类销售明细'!$I:$I) -> 2.0999516e+10 | I3: =SUMIF('女装-品类销售明细'!$C:$C,I$2,'女装-品类销售明细'!$I:$I) -> 1.0780144e+10 | J3: =SUMIF('女装-品类销售明细'!$C:$C,J$2,'女装-品类销售明细'!$I:$I) -> 7.1820793e+09 | ... L3: =SUMIF('女装-品类销售明细'!$C:$C,L$2,'女装-品类销售明细'!$I:$I) -> 1.1240004e+10 | M3: =L3/K3-1 -> -0.14291742 | N3: 女装3月裤子、短外套、制服为行业TOP品类，TOP商品为唐发发、lucas等达人品牌
B4: 羽绒服 | C4: =SUMIFS('女装-品类销售明细'!$I:$I,'女装-品类销售明细'!$C:$C,C$2,'女装-品类销售明细'!$G:$G,$B4) -> 3.6909943e+09 | D4: =SUMIFS('女装-品类销售明细'!$I:$I,'女装-品类销售明细'!$C:$C,D$2,'女装-品类销售明细'!$G:$G,$B4) -> 6.5543407e+09 | E4: =SUMIFS('女装-品类销售明细'!$I:$I,'女装-品类销售明细'!$C:$C,E$2,'女装-品类销售明细'!$G:$G,$B4) -> 5.7873272e+09 | F4: =SUMIFS('女装-品类销售明细'!$I:$I,'女装-品类销售明细'!$C:$C,F$2,'女装-品类销售明细'!$G:$G,$B4) -> 6.01545e+09 | G4: =SUMIFS('女装-品类销售明细'!$I:$I,'女装-品类销售明细'!$C:$C,G$2,'女装-品类销售明细'!$G:$G,$B4) -> 4.5474167e+09 | H4: =SUMIFS('女装-品类销售明细'!$I:$I,'女装-品类销售明细'!$C:$C,H$2,'女装-品类销售明细'!$G:$G,$B4) -> 3.5706335e+09 | I4: =SUMIFS('女装-品类销售明细'!$I:$I,'女装-品类销售明细'!$C:$C,I$2,'女装-品类销售明细'!$G:$G,$B4) -> 1.5042211e+09 | J4: =SUMIFS('女装-品类销售明细'!$I:$I,'女装-品类销售明细'!$C:$C,J$2,'女装-品类销售明细'!$G:$G,$B4) -> 3.6859033e+08 | ... L4: =SUMIFS('女装-品类销售明细'!$I:$I,'女装-品类销售明细'!$C:$C,L$2,'女装-品类销售明细'!$G:$G,$B4) -> 4.643779e+08 | M4: =L4/K4-1 -> -0.19205433
B5: 裤子 | C5: =SUMIFS('女装-品类销售明细'!$I:$I,'女装-品类销售明细'!$C:$C,C$2,'女装-品类销售明细'!$G:$G,$B5) -> 1.992412e+09 | D5: =SUMIFS('女装-品类销售明细'!$I:$I,'女装-品类销售明细'!$C:$C,D$2,'女装-品类销售明细'!$G:$G,$B5) -> 3.6534308e+09 | E5: =SUMIFS('女装-品类销售明细'!$I:$I,'女装-品类销售明细'!$C:$C,E$2,'女装-品类销售明细'!$G:$G,$B5) -> 3.3824702e+09 | F5: =SUMIFS('女装-品类销售明细'!$I:$I,'女装-品类销售明细'!$C:$C,F$2,'女装-品类销售明细'!$G:$G,$B5) -> 3.0231186e+09 | G5: =SUMIFS('女装-品类销售明细'!$I:$I,'女装-品类销售明细'!$C:$C,G$2,'女装-品类销售明细'!$G:$G,$B5) -> 2.7553911e+09 | H5: =SUMIFS('女装-品类销售明细'!$I:$I,'女装-品类销售明细'!$C:$C,H$2,'女装-品类销售明细'!$G:$G,$B5) -> 2.5004961e+09 | I5: =SUMIFS('女装-品类销售明细'!$I:$I,'女装-品类销售明细'!$C:$C,I$2,'女装-品类销售明细'!$G:$G,$B5) -> 1.1770306e+09 | J5: =SUMIFS('女装-品类销售明细'!$I:$I,'女装-品类销售明细'!$C:$C,J$2,'女装-品类销售明细'!$G:$G,$B5) -> 9.7269023e+08 | ... L5: =SUMIFS('女装-品类销售明细'!$I:$I,'女装-品类销售明细'!$C:$C,L$2,'女装-品类销售明细'!$G:$G,$B5) -> 1.8875436e+09 | M5: =L5/K5-1 -> -0.080373972
B6: 皮草 | C6: =SUMIFS('女装-品类销售明细'!$I:$I,'女装-品类销售明细'!$C:$C,C$2,'女装-品类销售明细'!$G:$G,$B6) -> 1.7638643e+09 | D6: =SUMIFS('女装-品类销售明细'!$I:$I,'女装-品类销售明细'!$C:$C,D$2,'女装-品类销售明细'!$G:$G,$B6) -> 3.494858e+09 | E6: =SUMIFS('女装-品类销售明细'!$I:$I,'女装-品类销售明细'!$C:$C,E$2,'女装-品类销售明细'!$G:$G,$B6) -> 3.3075553e+09 | F6: =SUMIFS('女装-品类销售明细'!$I:$I,'女装-品类销售明细'!$C:$C,F$2,'女装-品类销售明细'!$G:$G,$B6) -> 3.0968458e+09 | G6: =SUMIFS('女装-品类销售明细'!$I:$I,'女装-品类销售明细'!$C:$C,G$2,'女装-品类销售明细'!$G:$G,$B6) -> 2.5923623e+09 | H6: =SUMIFS('女装-品类销售明细'!$I:$I,'女装-品类销售明细'!$C:$C,H$2,'女装-品类销售明细'!$G:$G,$B6) -> 1.9682827e+09 | I6: =SUMIFS('女装-品类销售明细'!$I:$I,'女装-品类销售明细'!$C:$C,I$2,'女装-品类销售明细'!$G:$G,$B6) -> 1.04112e+09 | J6: =SUMIFS('女装-品类销售明细'!$I:$I,'女装-品类销售明细'!$C:$C,J$2,'女装-品类销售明细'!$G:$G,$B6) -> 3.7401703e+08 | ... L6: =SUMIFS('女装-品类销售明细'!$I:$I,'女装-品类销售明细'!$C:$C,L$2,'女装-品类销售明细'!$G:$G,$B6) -> 2.894328e+08 | M6: =L6/K6-1 -> -0.25324019
B7: 毛呢外套 | C7: =SUMIFS('女装-品类销售明细'!$I:$I,'女装-品类销售明细'!$C:$C,C$2,'女装-品类销售明细'!$G:$G,$B7) -> 1.1294749e+09 | D7: =SUMIFS('女装-品类销售明细'!$I:$I,'女装-品类销售明细'!$C:$C,D$2,'女装-品类销售明细'!$G:$G,$B7) -> 2.2988587e+09 | E7: =SUMIFS('女装-品类销售明细'!$I:$I,'女装-品类销售明细'!$C:$C,E$2,'女装-品类销售明细'!$G:$G,$B7) -> 2.3975557e+09 | F7: =SUMIFS('女装-品类销售明细'!$I:$I,'女装-品类销售明细'!$C:$C,F$2,'女装-品类销售明细'!$G:$G,$B7) -> 2.1733749e+09 | G7: =SUMIFS('女装-品类销售明细'!$I:$I,'女装-品类销售明细'!$C:$C,G$2,'女装-品类销售明细'!$G:$G,$B7) -> 2.1960572e+09 | H7: =SUMIFS('女装-品类销售明细'!$I:$I,'女装-品类销售明细'!$C:$C,H$2,'女装-品类销售明细'!$G:$G,$B7) -> 2.2605817e+09 | I7: =SUMIFS('女装-品类销售明细'!$I:$I,'女装-品类销售明细'!$C:$C,I$2,'女装-品类销售明细'!$G:$G,$B7) -> 1.2334271e+09 | J7: =SUMIFS('女装-品类销售明细'!$I:$I,'女装-品类销售明细'!$C:$C,J$2,'女装-品类销售明细'!$G:$G,$B7) -> 5.0428934e+08 | ... L7: =SUMIFS('女装-品类销售明细'!$I:$I,'女装-品类销售明细'!$C:$C,L$2,'女装-品类销售明细'!$G:$G,$B7) -> 3.832651e+08 | M7: =L7/K7-1 -> -0.34207614
B8: 短外套 | C8: =SUMIFS('女装-品类销售明细'!$I:$I,'女装-品类销售明细'!$C:$C,C$2,'女装-品类销售明细'!$G:$G,$B8) -> 1.2223895e+09 | D8: =SUMIFS('女装-品类销售明细'!$I:$I,'女装-品类销售明细'!$C:$C,D$2,'女装-品类销售明细'!$G:$G,$B8) -> 2.3389406e+09 | E8: =SUMIFS('女装-品类销售明细'!$I:$I,'女装-品类销售明细'!$C:$C,E$2,'女装-品类销售明细'!$G:$G,$B8) -> 2.2592979e+09 | F8: =SUMIFS('女装-品类销售明细'!$I:$I,'女装-品类销售明细'!$C:$C,F$2,'女装-品类销售明细'!$G:$G,$B8) -> 1.9907418e+09 | G8: =SUMIFS('女装-品类销售明细'!$I:$I,'女装-品类销售明细'!$C:$C,G$2,'女装-品类销售明细'!$G:$G,$B8) -> 1.8154165e+09 | H8: =SUMIFS('女装-品类销售明细'!$I:$I,'女装-品类销售明细'!$C:$C,H$2,'女装-品类销售明细'!$G:$G,$B8) -> 1.7019438e+09 | I8: =SUMIFS('女装-品类销售明细'!$I:$I,'女装-品类销售明细'!$C:$C,I$2,'女装-品类销售明细'!$G:$G,$B8) -> 8.5299712e+08 | J8: =SUMIFS('女装-品类销售明细'!$I:$I,'女装-品类销售明细'!$C:$C,J$2,'女装-品类销售明细'!$G:$G,$B8) -> 6.0443885e+08 | ... L8: =SUMIFS('女装-品类销售明细'!$I:$I,'女装-品类销售明细'!$C:$C,L$2,'女装-品类销售明细'!$G:$G,$B8) -> 8.7856331e+08 | M8: =L8/K8-1 -> -0.13604478
B9: 毛针织衫 | C9: =SUMIFS('女装-品类销售明细'!$I:$I,'女装-品类销售明细'!$C:$C,C$2,'女装-品类销售明细'!$G:$G,$B9) -> 8.3580089e+08 | D9: =SUMIFS('女装-品类销售明细'!$I:$I,'女装-品类销售明细'!$C:$C,D$2,'女装-品类销售明细'!$G:$G,$B9) -> 1.5271795e+09 | E9: =SUMIFS('女装-品类销售明细'!$I:$I,'女装-品类销售明细'!$C:$C,E$2,'女装-品类销售明细'!$G:$G,$B9) -> 1.4925484e+09 | F9: =SUMIFS('女装-品类销售明细'!$I:$I,'女装-品类销售明细'!$C:$C,F$2,'女装-品类销售明细'!$G:$G,$B9) -> 1.2552472e+09 | G9: =SUMIFS('女装-品类销售明细'!$I:$I,'女装-品类销售明细'!$C:$C,G$2,'女装-品类销售明细'!$G:$G,$B9) -> 1.2649956e+09 | H9: =SUMIFS('女装-品类销售明细'!$I:$I,'女装-品类销售明细'!$C:$C,H$2,'女装-品类销售明细'!$G:$G,$B9) -> 1.225105e+09 | I9: =SUMIFS('女装-品类销售明细'!$I:$I,'女装-品类销售明细'!$C:$C,I$2,'女装-品类销售明细'!$G:$G,$B9) -> 6.0583994e+08 | J9: =SUMIFS('女装-品类销售明细'!$I:$I,'女装-品类销售明细'!$C:$C,J$2,'女装-品类销售明细'!$G:$G,$B9) -> 3.9571464e+08 | ... L9: =SUMIFS('女装-品类销售明细'!$I:$I,'女装-品类销售明细'!$C:$C,L$2,'女装-品类销售明细'!$G:$G,$B9) -> 6.6613623e+08 | M9: =L9/K9-1 -> -0.095646499
B10: 套装/学生校服/工作制服 | C10: =SUMIFS('女装-品类销售明细'!$I:$I,'女装-品类销售明细'!$C:$C,C$2,'女装-品类销售明细'!$G:$G,$B10) -> 5.1385935e+08 | D10: =SUMIFS('女装-品类销售明细'!$I:$I,'女装-品类销售明细'!$C:$C,D$2,'女装-品类销售明细'!$G:$G,$B10) -> 1.0256684e+09 | E10: =SUMIFS('女装-品类销售明细'!$I:$I,'女装-品类销售明细'!$C:$C,E$2,'女装-品类销售明细'!$G:$G,$B10) -> 1.0583934e+09 | F10: =SUMIFS('女装-品类销售明细'!$I:$I,'女装-品类销售明细'!$C:$C,F$2,'女装-品类销售明细'!$G:$G,$B10) -> 8.7488052e+08 | G10: =SUMIFS('女装-品类销售明细'!$I:$I,'女装-品类销售明细'!$C:$C,G$2,'女装-品类销售明细'!$G:$G,$B10) -> 8.4553027e+08 | H10: =SUMIFS('女装-品类销售明细'!$I:$I,'女装-品类销售明细'!$C:$C,H$2,'女装-品类销售明细'!$G:$G,$B10) -> 8.4748374e+08 | I10: =SUMIFS('女装-品类销售明细'!$I:$I,'女装-品类销售明细'!$C:$C,I$2,'女装-品类销售明细'!$G:$G,$B10) -> 4.8431745e+08 | J10: =SUMIFS('女装-品类销售明细'!$I:$I,'女装-品类销售明细'!$C:$C,J$2,'女装-品类销售明细'!$G:$G,$B10) -> 5.4355274e+08 | ... L10: =SUMIFS('女装-品类销售明细'!$I:$I,'女装-品类销售明细'!$C:$C,L$2,'女装-品类销售明细'!$G:$G,$B10) -> 8.6200163e+08 | M10: =L10/K10-1 -> -0.11246082
B11: 棉衣/棉服 | C11: =SUMIFS('女装-品类销售明细'!$I:$I,'女装-品类销售明细'!$C:$C,C$2,'女装-品类销售明细'!$G:$G,$B11) -> 4.4754223e+08 | D11: =SUMIFS('女装-品类销售明细'!$I:$I,'女装-品类销售明细'!$C:$C,D$2,'女装-品类销售明细'!$G:$G,$B11) -> 8.2795625e+08 | E11: =SUMIFS('女装-品类销售明细'!$I:$I,'女装-品类销售明细'!$C:$C,E$2,'女装-品类销售明细'!$G:$G,$B11) -> 7.1441661e+08 | F11: =SUMIFS('女装-品类销售明细'!$I:$I,'女装-品类销售明细'!$C:$C,F$2,'女装-品类销售明细'!$G:$G,$B11) -> 6.5335219e+08 | G11: =SUMIFS('女装-品类销售明细'!$I:$I,'女装-品类销售明细'!$C:$C,G$2,'女装-品类销售明细'!$G:$G,$B11) -> 5.6781032e+08 | H11: =SUMIFS('女装-品类销售明细'!$I:$I,'女装-品类销售明细'!$C:$C,H$2,'女装-品类销售明细'!$G:$G,$B11) -> 4.7647234e+08 | I11: =SUMIFS('女装-品类销售明细'!$I:$I,'女装-品类销售明细'!$C:$C,I$2,'女装-品类销售明细'!$G:$G,$B11) -> 2.0971026e+08 | J11: =SUMIFS('女装-品类销售明细'!$I:$I,'女装-品类销售明细'!$C:$C,J$2,'女装-品类销售明细'!$G:$G,$B11) -> 76072748 | ... L11: =SUMIFS('女装-品类销售明细'!$I:$I,'女装-品类销售明细'!$C:$C,L$2,'女装-品类销售明细'!$G:$G,$B11) -> 1.0246709e+08 | M11: =L11/K11-1 -> -0.22971324
B12: 连衣裙 | C12: =SUMIFS('女装-品类销售明细'!$I:$I,'女装-品类销售明细'!$C:$C,C$2,'女装-品类销售明细'!$G:$G,$B12) -> 3.7536787e+08 | D12: =SUMIFS('女装-品类销售明细'!$I:$I,'女装-品类销售明细'!$C:$C,D$2,'女装-品类销售明细'!$G:$G,$B12) -> 7.6012306e+08 | E12: =SUMIFS('女装-品类销售明细'!$I:$I,'女装-品类销售明细'!$C:$C,E$2,'女装-品类销售明细'!$G:$G,$B12) -> 7.9439538e+08 | F12: =SUMIFS('女装-品类销售明细'!$I:$I,'女装-品类销售明细'!$C:$C,F$2,'女装-品类销售明细'!$G:$G,$B12) -> 6.7089778e+08 | G12: =SUMIFS('女装-品类销售明细'!$I:$I,'女装-品类销售明细'!$C:$C,G$2,'女装-品类销售明细'!$G:$G,$B12) -> 6.8750437e+08 | H12: =SUMIFS('女装-品类销售明细'!$I:$I,'女装-品类销售明细'!$C:$C,H$2,'女装-品类销售明细'!$G:$G,$B12) -> 7.2605512e+08 | I12: =SUMIFS('女装-品类销售明细'!$I:$I,'女装-品类销售明细'!$C:$C,I$2,'女装-品类销售明细'!$G:$G,$B12) -> 4.8429199e+08 | J12: =SUMIFS('女装-品类销售明细'!$I:$I,'女装-品类销售明细'!$C:$C,J$2,'女装-品类销售明细'!$G:$G,$B12) -> 4.8133275e+08 | ... L12: =SUMIFS('女装-品类销售明细'!$I:$I,'女装-品类销售明细'!$C:$C,L$2,'女装-品类销售明细'!$G:$G,$B12) -> 8.2742336e+08 | M12: =L12/K12-1 -> -0.094456673
B13: 汉服 | C13: =SUMIFS('女装-品类销售明细'!$I:$I,'女装-品类销售明细'!$C:$C,C$2,'女装-品类销售明细'!$G:$G,$B13) -> 3.4202961e+08 | D13: =SUMIFS('女装-品类销售明细'!$I:$I,'女装-品类销售明细'!$C:$C,D$2,'女装-品类销售明细'!$G:$G,$B13) -> 5.6991605e+08 | E13: =SUMIFS('女装-品类销售明细'!$I:$I,'女装-品类销售明细'!$C:$C,E$2,'女装-品类销售明细'!$G:$G,$B13) -> 6.3974023e+08 | F13: =SUMIFS('女装-品类销售明细'!$I:$I,'女装-品类销售明细'!$C:$C,F$2,'女装-品类销售明细'!$G:$G,$B13) -> 5.6224573e+08 | G13: =SUMIFS('女装-品类销售明细'!$I:$I,'女装-品类销售明细'!$C:$C,G$2,'女装-品类销售明细'!$G:$G,$B13) -> 4.133411e+08 | H13: =SUMIFS('女装-品类销售明细'!$I:$I,'女装-品类销售明细'!$C:$C,H$2,'女装-品类销售明细'!$G:$G,$B13) -> 3.4257381e+08 | I13: =SUMIFS('女装-品类销售明细'!$I:$I,'女装-品类销售明细'!$C:$C,I$2,'女装-品类销售明细'!$G:$G,$B13) -> 2.2392502e+08 | J13: =SUMIFS('女装-品类销售明细'!$I:$I,'女装-品类销售明细'!$C:$C,J$2,'女装-品类销售明细'!$G:$G,$B13) -> 2.616555e+08 | ... L13: =SUMIFS('女装-品类销售明细'!$I:$I,'女装-品类销售明细'!$C:$C,L$2,'女装-品类销售明细'!$G:$G,$B13) -> 3.1731798e+08 | M13: =L13/K13-1 -> -0.48244288
B14: T恤 | C14: =SUMIFS('女装-品类销售明细'!$I:$I,'女装-品类销售明细'!$C:$C,C$2,'女装-品类销售明细'!$G:$G,$B14) -> 3.466147e+08 | D14: =SUMIFS('女装-品类销售明细'!$I:$I,'女装-品类销售明细'!$C:$C,D$2,'女装-品类销售明细'!$G:$G,$B14) -> 6.4555713e+08 | E14: =SUMIFS('女装-品类销售明细'!$I:$I,'女装-品类销售明细'!$C:$C,E$2,'女装-品类销售明细'!$G:$G,$B14) -> 6.5485147e+08 | F14: =SUMIFS('女装-品类销售明细'!$I:$I,'女装-品类销售明细'!$C:$C,F$2,'女装-品类销售明细'!$G:$G,$B14) -> 5.428292e+08 | G14: =SUMIFS('女装-品类销售明细'!$I:$I,'女装-品类销售明细'!$C:$C,G$2,'女装-品类销售明细'!$G:$G,$B14) -> 5.5292836e+08 | H14: =SUMIFS('女装-品类销售明细'!$I:$I,'女装-品类销售明细'!$C:$C,H$2,'女装-品类销售明细'!$G:$G,$B14) -> 5.6920843e+08 | I14: =SUMIFS('女装-品类销售明细'!$I:$I,'女装-品类销售明细'!$C:$C,I$2,'女装-品类销售明细'!$G:$G,$B14) -> 3.6441938e+08 | J14: =SUMIFS('女装-品类销售明细'!$I:$I,'女装-品类销售明细'!$C:$C,J$2,'女装-品类销售明细'!$G:$G,$B14) -> 3.8979497e+08 | ... L14: =SUMIFS('女装-品类销售明细'!$I:$I,'女装-品类销售明细'!$C:$C,L$2,'女装-品类销售明细'!$G:$G,$B14) -> 7.8339826e+08 | M14: =L14/K14-1 -> -0.071574667
B15: 羊毛衫 | C15: =SUMIFS('女装-品类销售明细'!$I:$I,'女装-品类销售明细'!$C:$C,C$2,'女装-品类销售明细'!$G:$G,$B15) -> 3.2711365e+08 | D15: =SUMIFS('女装-品类销售明细'!$I:$I,'女装-品类销售明细'!$C:$C,D$2,'女装-品类销售明细'!$G:$G,$B15) -> 5.6454322e+08 | E15: =SUMIFS('女装-品类销售明细'!$I:$I,'女装-品类销售明细'!$C:$C,E$2,'女装-品类销售明细'!$G:$G,$B15) -> 5.4039244e+08 | F15: =SUMIFS('女装-品类销售明细'!$I:$I,'女装-品类销售明细'!$C:$C,F$2,'女装-品类销售明细'!$G:$G,$B15) -> 4.7150448e+08 | G15: =SUMIFS('女装-品类销售明细'!$I:$I,'女装-品类销售明细'!$C:$C,G$2,'女装-品类销售明细'!$G:$G,$B15) -> 4.3148872e+08 | H15: =SUMIFS('女装-品类销售明细'!$I:$I,'女装-品类销售明细'!$C:$C,H$2,'女装-品类销售明细'!$G:$G,$B15) -> 3.6759399e+08 | I15: =SUMIFS('女装-品类销售明细'!$I:$I,'女装-品类销售明细'!$C:$C,I$2,'女装-品类销售明细'!$G:$G,$B15) -> 1.7074431e+08 | J15: =SUMIFS('女装-品类销售明细'!$I:$I,'女装-品类销售明细'!$C:$C,J$2,'女装-品类销售明细'!$G:$G,$B15) -> 74077572 | ... L15: =SUMIFS('女装-品类销售明细'!$I:$I,'女装-品类销售明细'!$C:$C,L$2,'女装-品类销售明细'!$G:$G,$B15) -> 1.1969829e+08 | M15: =L15/K15-1 -> -0.19143362
... B23: 衬衫 | C23: =SUMIFS('女装-品类销售明细'!$I:$I,'女装-品类销售明细'!$C:$C,C$2,'女装-品类销售明细'!$G:$G,$B23) -> 1.7728861e+08 | D23: =SUMIFS('女装-品类销售明细'!$I:$I,'女装-品类销售明细'!$C:$C,D$2,'女装-品类销售明细'!$G:$G,$B23) -> 3.6254178e+08 | E23: =SUMIFS('女装-品类销售明细'!$I:$I,'女装-品类销售明细'!$C:$C,E$2,'女装-品类销售明细'!$G:$G,$B23) -> 4.1456181e+08 | F23: =SUMIFS('女装-品类销售明细'!$I:$I,'女装-品类销售明细'!$C:$C,F$2,'女装-品类销售明细'!$G:$G,$B23) -> 3.4254805e+08 | G23: =SUMIFS('女装-品类销售明细'!$I:$I,'女装-品类销售明细'!$C:$C,G$2,'女装-品类销售明细'!$G:$G,$B23) -> 3.5216652e+08 | H23: =SUMIFS('女装-品类销售明细'!$I:$I,'女装-品类销售明细'!$C:$C,H$2,'女装-品类销售明细'!$G:$G,$B23) -> 3.8471656e+08 | I23: =SUMIFS('女装-品类销售明细'!$I:$I,'女装-品类销售明细'!$C:$C,I$2,'女装-品类销售明细'!$G:$G,$B23) -> 2.5669686e+08 | J23: =SUMIFS('女装-品类销售明细'!$I:$I,'女装-品类销售明细'!$C:$C,J$2,'女装-品类销售明细'!$G:$G,$B23) -> 3.191767e+08 | ... L23: =SUMIFS('女装-品类销售明细'!$I:$I,'女装-品类销售明细'!$C:$C,L$2,'女装-品类销售明细'!$G:$G,$B23) -> 5.7799313e+08 | M23: =L23/K23-1 -> -0.12681129
A24: 男装 | B24: 总计 | C24: =SUMIF('男装-品类销售明细'!$C:$C,C$2,'男装-品类销售明细'!$I:$I) -> 3.6356234e+09 | D24: =SUMIF('男装-品类销售明细'!$C:$C,D$2,'男装-品类销售明细'!$I:$I) -> 6.4609903e+09 | E24: =SUMIF('男装-品类销售明细'!$C:$C,E$2,'男装-品类销售明细'!$I:$I) -> 5.8247083e+09 | F24: =SUMIF('男装-品类销售明细'!$C:$C,F$2,'男装-品类销售明细'!$I:$I) -> 6.2037542e+09 | G24: =SUMIF('男装-品类销售明细'!$C:$C,G$2,'男装-品类销售明细'!$I:$I) -> 5.715387e+09 | H24: =SUMIF('男装-品类销售明细'!$C:$C,H$2,'男装-品类销售明细'!$I:$I) -> 5.8179538e+09 | I24: =SUMIF('男装-品类销售明细'!$C:$C,I$2,'男装-品类销售明细'!$I:$I) -> 2.555649e+09 | J24: =SUMIF('男装-品类销售明细'!$C:$C,J$2,'男装-品类销售明细'!$I:$I) -> 1.0539623e+09 | ... L24: =SUMIF('男装-品类销售明细'!$C:$C,L$2,'男装-品类销售明细'!$I:$I) -> 1.8194574e+09 | M24: =L24/K24-1 -> -0.059232368 | N24: 3月截止7日夹克、T恤、休闲裤为行业TOP品类，其中夹克主要为德尔惠、西域骆驼品牌的冲锋衣、T恤为白小T、霞湖世家的T
B25: 羽绒服 | C25: =SUMIFS('男装-品类销售明细'!$I:$I,'男装-品类销售明细'!$C:$C,C$2,'男装-品类销售明细'!$G:$G,$B25) -> 1.010145e+09 | D25: =SUMIFS('男装-品类销售明细'!$I:$I,'男装-品类销售明细'!$C:$C,D$2,'男装-品类销售明细'!$G:$G,$B25) -> 1.8217393e+09 | E25: =SUMIFS('男装-品类销售明细'!$I:$I,'男装-品类销售明细'!$C:$C,E$2,'男装-品类销售明细'!$G:$G,$B25) -> 1.6525094e+09 | F25: =SUMIFS('男装-品类销售明细'!$I:$I,'男装-品类销售明细'!$C:$C,F$2,'男装-品类销售明细'!$G:$G,$B25) -> 1.8155163e+09 | G25: =SUMIFS('男装-品类销售明细'!$I:$I,'男装-品类销售明细'!$C:$C,G$2,'男装-品类销售明细'!$G:$G,$B25) -> 1.5261421e+09 | H25: =SUMIFS('男装-品类销售明细'!$I:$I,'男装-品类销售明细'!$C:$C,H$2,'男装-品类销售明细'!$G:$G,$B25) -> 1.3191202e+09 | I25: =SUMIFS('男装-品类销售明细'!$I:$I,'男装-品类销售明细'!$C:$C,I$2,'男装-品类销售明细'!$G:$G,$B25) -> 4.8248177e+08 | J25: =SUMIFS('男装-品类销售明细'!$I:$I,'男装-品类销售明细'!$C:$C,J$2,'男装-品类销售明细'!$G:$G,$B25) -> 48873978 | ... L25: =SUMIFS('男装-品类销售明细'!$I:$I,'男装-品类销售明细'!$C:$C,L$2,'男装-品类销售明细'!$G:$G,$B25) -> 69957568 | M25: =L25/K25-1 -> -0.1313529
B26: 休闲裤 | C26: =SUMIFS('男装-品类销售明细'!$I:$I,'男装-品类销售明细'!$C:$C,C$2,'男装-品类销售明细'!$G:$G,$B26) -> 4.4415925e+08 | D26: =SUMIFS('男装-品类销售明细'!$I:$I,'男装-品类销售明细'!$C:$C,D$2,'男装-品类销售明细'!$G:$G,$B26) -> 7.5578979e+08 | E26: =SUMIFS('男装-品类销售明细'!$I:$I,'男装-品类销售明细'!$C:$C,E$2,'男装-品类销售明细'!$G:$G,$B26) -> 6.4752562e+08 | F26: =SUMIFS('男装-品类销售明细'!$I:$I,'男装-品类销售明细'!$C:$C,F$2,'男装-品类销售明细'!$G:$G,$B26) -> 7.2102652e+08 | G26: =SUMIFS('男装-品类销售明细'!$I:$I,'男装-品类销售明细'!$C:$C,G$2,'男装-品类销售明细'!$G:$G,$B26) -> 6.5124034e+08 | H26: =SUMIFS('男装-品类销售明细'!$I:$I,'男装-品类销售明细'!$C:$C,H$2,'男装-品类销售明细'!$G:$G,$B26) -> 6.719057e+08 | I26: =SUMIFS('男装-品类销售明细'!$I:$I,'男装-品类销售明细'!$C:$C,I$2,'男装-品类销售明细'!$G:$G,$B26) -> 2.7137358e+08 | J26: =SUMIFS('男装-品类销售明细'!$I:$I,'男装-品类销售明细'!$C:$C,J$2,'男装-品类销售明细'!$G:$G,$B26) -> 1.1341844e+08 | ... L26: =SUMIFS('男装-品类销售明细'!$I:$I,'男装-品类销售明细'!$C:$C,L$2,'男装-品类销售明细'!$G:$G,$B26) -> 2.2907644e+08 | M26: =L26/K26-1 -> -0.013908611
B27: 夹克 | C27: =SUMIFS('男装-品类销售明细'!$I:$I,'男装-品类销售明细'!$C:$C,C$2,'男装-品类销售明细'!$G:$G,$B27) -> 3.122099e+08 | D27: =SUMIFS('男装-品类销售明细'!$I:$I,'男装-品类销售明细'!$C:$C,D$2,'男装-品类销售明细'!$G:$G,$B27) -> 5.8952566e+08 | E27: =SUMIFS('男装-品类销售明细'!$I:$I,'男装-品类销售明细'!$C:$C,E$2,'男装-品类销售明细'!$G:$G,$B27) -> 5.5882267e+08 | F27: =SUMIFS('男装-品类销售明细'!$I:$I,'男装-品类销售明细'!$C:$C,F$2,'男装-品类销售明细'!$G:$G,$B27) -> 5.6333746e+08 | G27: =SUMIFS('男装-品类销售明细'!$I:$I,'男装-品类销售明细'!$C:$C,G$2,'男装-品类销售明细'!$G:$G,$B27) -> 5.7156317e+08 | H27: =SUMIFS('男装-品类销售明细'!$I:$I,'男装-品类销售明细'!$C:$C,H$2,'男装-品类销售明细'!$G:$G,$B27) -> 6.7160558e+08 | I27: =SUMIFS('男装-品类销售明细'!$I:$I,'男装-品类销售明细'!$C:$C,I$2,'男装-品类销售明细'!$G:$G,$B27) -> 3.6628613e+08 | J27: =SUMIFS('男装-品类销售明细'!$I:$I,'男装-品类销售明细'!$C:$C,J$2,'男装-品类销售明细'!$G:$G,$B27) -> 2.0758133e+08 | ... L27: =SUMIFS('男装-品类销售明细'!$I:$I,'男装-品类销售明细'!$C:$C,L$2,'男装-品类销售明细'!$G:$G,$B27) -> 4.0193211e+08 | M27: =L27/K27-1 -> -0.0083852805
B28: 牛仔裤 | C28: =SUMIFS('男装-品类销售明细'!$I:$I,'男装-品类销售明细'!$C:$C,C$2,'男装-品类销售明细'!$G:$G,$B28) -> 2.7165865e+08 | D28: =SUMIFS('男装-品类销售明细'!$I:$I,'男装-品类销售明细'!$C:$C,D$2,'男装-品类销售明细'!$G:$G,$B28) -> 4.7784218e+08 | E28: =SUMIFS('男装-品类销售明细'!$I:$I,'男装-品类销售明细'!$C:$C,E$2,'男装-品类销售明细'!$G:$G,$B28) -> 4.5338723e+08 | F28: =SUMIFS('男装-品类销售明细'!$I:$I,'男装-品类销售明细'!$C:$C,F$2,'男装-品类销售明细'!$G:$G,$B28) -> 4.7765462e+08 | G28: =SUMIFS('男装-品类销售明细'!$I:$I,'男装-品类销售明细'!$C:$C,G$2,'男装-品类销售明细'!$G:$G,$B28) -> 5.0487838e+08 | H28: =SUMIFS('男装-品类销售明细'!$I:$I,'男装-品类销售明细'!$C:$C,H$2,'男装-品类销售明细'!$G:$G,$B28) -> 5.5438552e+08 | I28: =SUMIFS('男装-品类销售明细'!$I:$I,'男装-品类销售明细'!$C:$C,I$2,'男装-品类销售明细'!$G:$G,$B28) -> 2.3710386e+08 | J28: =SUMIFS('男装-品类销售明细'!$I:$I,'男装-品类销售明细'!$C:$C,J$2,'男装-品类销售明细'!$G:$G,$B28) -> 1.0658688e+08 | ... L28: =SUMIFS('男装-品类销售明细'!$I:$I,'男装-品类销售明细'!$C:$C,L$2,'男装-品类销售明细'!$G:$G,$B28) -> 1.7649356e+08 | M28: =L28/K28-1 -> -0.060261027
B29: 棉衣 | C29: =SUMIFS('男装-品类销售明细'!$I:$I,'男装-品类销售明细'!$C:$C,C$2,'男装-品类销售明细'!$G:$G,$B29) -> 2.4380564e+08 | D29: =SUMIFS('男装-品类销售明细'!$I:$I,'男装-品类销售明细'!$C:$C,D$2,'男装-品类销售明细'!$G:$G,$B29) -> 4.447307e+08 | E29: =SUMIFS('男装-品类销售明细'!$I:$I,'男装-品类销售明细'!$C:$C,E$2,'男装-品类销售明细'!$G:$G,$B29) -> 3.4372697e+08 | F29: =SUMIFS('男装-品类销售明细'!$I:$I,'男装-品类销售明细'!$C:$C,F$2,'男装-品类销售明细'!$G:$G,$B29) -> 3.8419563e+08 | G29: =SUMIFS('男装-品类销售明细'!$I:$I,'男装-品类销售明细'!$C:$C,G$2,'男装-品类销售明细'!$G:$G,$B29) -> 3.3544012e+08 | H29: =SUMIFS('男装-品类销售明细'!$I:$I,'男装-品类销售明细'!$C:$C,H$2,'男装-品类销售明细'!$G:$G,$B29) -> 3.2143638e+08 | I29: =SUMIFS('男装-品类销售明细'!$I:$I,'男装-品类销售明细'!$C:$C,I$2,'男装-品类销售明细'!$G:$G,$B29) -> 1.2432645e+08 | J29: =SUMIFS('男装-品类销售明细'!$I:$I,'男装-品类销售明细'!$C:$C,J$2,'男装-品类销售明细'!$G:$G,$B29) -> 18969406 | ... L29: =SUMIFS('男装-品类销售明细'!$I:$I,'男装-品类销售明细'!$C:$C,L$2,'男装-品类销售明细'!$G:$G,$B29) -> 25145072 | M29: =L29/K29-1 -> -0.12354381
B30: 卫衣 | C30: =SUMIFS('男装-品类销售明细'!$I:$I,'男装-品类销售明细'!$C:$C,C$2,'男装-品类销售明细'!$G:$G,$B30) -> 2.168273e+08 | D30: =SUMIFS('男装-品类销售明细'!$I:$I,'男装-品类销售明细'!$C:$C,D$2,'男装-品类销售明细'!$G:$G,$B30) -> 3.8311135e+08 | E30: =SUMIFS('男装-品类销售明细'!$I:$I,'男装-品类销售明细'!$C:$C,E$2,'男装-品类销售明细'!$G:$G,$B30) -> 3.5311167e+08 | F30: =SUMIFS('男装-品类销售明细'!$I:$I,'男装-品类销售明细'!$C:$C,F$2,'男装-品类销售明细'!$G:$G,$B30) -> 3.6011416e+08 | G30: =SUMIFS('男装-品类销售明细'!$I:$I,'男装-品类销售明细'!$C:$C,G$2,'男装-品类销售明细'!$G:$G,$B30) -> 3.3685093e+08 | H30: =SUMIFS('男装-品类销售明细'!$I:$I,'男装-品类销售明细'!$C:$C,H$2,'男装-品类销售明细'!$G:$G,$B30) -> 3.6427562e+08 | I30: =SUMIFS('男装-品类销售明细'!$I:$I,'男装-品类销售明细'!$C:$C,I$2,'男装-品类销售明细'!$G:$G,$B30) -> 1.6497371e+08 | J30: =SUMIFS('男装-品类销售明细'!$I:$I,'男装-品类销售明细'!$C:$C,J$2,'男装-品类销售明细'!$G:$G,$B30) -> 75036934 | ... L30: =SUMIFS('男装-品类销售明细'!$I:$I,'男装-品类销售明细'!$C:$C,L$2,'男装-品类销售明细'!$G:$G,$B30) -> 1.0357297e+08 | M30: =L30/K30-1 -> -0.19158568
B31: 针织衫/毛衣 | C31: =SUMIFS('男装-品类销售明细'!$I:$I,'男装-品类销售明细'!$C:$C,C$2,'男装-品类销售明细'!$G:$G,$B31) -> 2.0159527e+08 | D31: =SUMIFS('男装-品类销售明细'!$I:$I,'男装-品类销售明细'!$C:$C,D$2,'男装-品类销售明细'!$G:$G,$B31) -> 3.4218691e+08 | E31: =SUMIFS('男装-品类销售明细'!$I:$I,'男装-品类销售明细'!$C:$C,E$2,'男装-品类销售明细'!$G:$G,$B31) -> 3.1221953e+08 | F31: =SUMIFS('男装-品类销售明细'!$I:$I,'男装-品类销售明细'!$C:$C,F$2,'男装-品类销售明细'!$G:$G,$B31) -> 3.2206166e+08 | G31: =SUMIFS('男装-品类销售明细'!$I:$I,'男装-品类销售明细'!$C:$C,G$2,'男装-品类销售明细'!$G:$G,$B31) -> 3.2353145e+08 | H31: =SUMIFS('男装-品类销售明细'!$I:$I,'男装-品类销售明细'!$C:$C,H$2,'男装-品类销售明细'!$G:$G,$B31) -> 3.4100804e+08 | I31: =SUMIFS('男装-品类销售明细'!$I:$I,'男装-品类销售明细'!$C:$C,I$2,'男装-品类销售明细'!$G:$G,$B31) -> 1.3926765e+08 | J31: =SUMIFS('男装-品类销售明细'!$I:$I,'男装-品类销售明细'!$C:$C,J$2,'男装-品类销售明细'!$G:$G,$B31) -> 50699283 | ... L31: =SUMIFS('男装-品类销售明细'!$I:$I,'男装-品类销售明细'!$C:$C,L$2,'男装-品类销售明细'!$G:$G,$B31) -> 60287113 | M31: =L31/K31-1 -> -0.054444969
B32: T恤 | C32: =SUMIFS('男装-品类销售明细'!$I:$I,'男装-品类销售明细'!$C:$C,C$2,'男装-品类销售明细'!$G:$G,$B32) -> 1.1907908e+08 | D32: =SUMIFS('男装-品类销售明细'!$I:$I,'男装-品类销售明细'!$C:$C,D$2,'男装-品类销售明细'!$G:$G,$B32) -> 2.2029537e+08 | E32: =SUMIFS('男装-品类销售明细'!$I:$I,'男装-品类销售明细'!$C:$C,E$2,'男装-品类销售明细'!$G:$G,$B32) -> 2.0724218e+08 | F32: =SUMIFS('男装-品类销售明细'!$I:$I,'男装-品类销售明细'!$C:$C,F$2,'男装-品类销售明细'!$G:$G,$B32) -> 1.9407977e+08 | G32: =SUMIFS('男装-品类销售明细'!$I:$I,'男装-品类销售明细'!$C:$C,G$2,'男装-品类销售明细'!$G:$G,$B32) -> 2.0479988e+08 | H32: =SUMIFS('男装-品类销售明细'!$I:$I,'男装-品类销售明细'!$C:$C,H$2,'男装-品类销售明细'!$G:$G,$B32) -> 2.6087323e+08 | I32: =SUMIFS('男装-品类销售明细'!$I:$I,'男装-品类销售明细'!$C:$C,I$2,'男装-品类销售明细'!$G:$G,$B32) -> 1.7004468e+08 | J32: =SUMIFS('男装-品类销售明细'!$I:$I,'男装-品类销售明细'!$C:$C,J$2,'男装-品类销售明细'!$G:$G,$B32) -> 1.6089187e+08 | ... L32: =SUMIFS('男装-品类销售明细'!$I:$I,'男装-品类销售明细'!$C:$C,L$2,'男装-品类销售明细'!$G:$G,$B32) -> 2.6278301e+08 | M32: =L32/K32-1 -> -0.098318623
B33: 皮衣 | C33: =SUMIFS('男装-品类销售明细'!$I:$I,'男装-品类销售明细'!$C:$C,C$2,'男装-品类销售明细'!$G:$G,$B33) -> 1.033758e+08 | D33: =SUMIFS('男装-品类销售明细'!$I:$I,'男装-品类销售明细'!$C:$C,D$2,'男装-品类销售明细'!$G:$G,$B33) -> 1.9609293e+08 | E33: =SUMIFS('男装-品类销售明细'!$I:$I,'男装-品类销售明细'!$C:$C,E$2,'男装-品类销售明细'!$G:$G,$B33) -> 1.784253e+08 | F33: =SUMIFS('男装-品类销售明细'!$I:$I,'男装-品类销售明细'!$C:$C,F$2,'男装-品类销售明细'!$G:$G,$B33) -> 1.8319699e+08 | G33: =SUMIFS('男装-品类销售明细'!$I:$I,'男装-品类销售明细'!$C:$C,G$2,'男装-品类销售明细'!$G:$G,$B33) -> 1.8147596e+08 | H33: =SUMIFS('男装-品类销售明细'!$I:$I,'男装-品类销售明细'!$C:$C,H$2,'男装-品类销售明细'!$G:$G,$B33) -> 1.9470404e+08 | I33: =SUMIFS('男装-品类销售明细'!$I:$I,'男装-品类销售明细'!$C:$C,I$2,'男装-品类销售明细'!$G:$G,$B33) -> 1.1312237e+08 | J33: =SUMIFS('男装-品类销售明细'!$I:$I,'男装-品类销售明细'!$C:$C,J$2,'男装-品类销售明细'!$G:$G,$B33) -> 37343894 | ... L33: =SUMIFS('男装-品类销售明细'!$I:$I,'男装-品类销售明细'!$C:$C,L$2,'男装-品类销售明细'!$G:$G,$B33) -> 65191075 | M33: =L33/K33-1 -> -0.11727719
B34: 毛呢大衣 | C34: =SUMIFS('男装-品类销售明细'!$I:$I,'男装-品类销售明细'!$C:$C,C$2,'男装-品类销售明细'!$G:$G,$B34) -> 75244752 | D34: =SUMIFS('男装-品类销售明细'!$I:$I,'男装-品类销售明细'!$C:$C,D$2,'男装-品类销售明细'!$G:$G,$B34) -> 1.4167981e+08 | E34: =SUMIFS('男装-品类销售明细'!$I:$I,'男装-品类销售明细'!$C:$C,E$2,'男装-品类销售明细'!$G:$G,$B34) -> 1.4984514e+08 | F34: =SUMIFS('男装-品类销售明细'!$I:$I,'男装-品类销售明细'!$C:$C,F$2,'男装-品类销售明细'!$G:$G,$B34) -> 1.4834381e+08 | G34: =SUMIFS('男装-品类销售明细'!$I:$I,'男装-品类销售明细'!$C:$C,G$2,'男装-品类销售明细'!$G:$G,$B34) -> 1.5986455e+08 | H34: =SUMIFS('男装-品类销售明细'!$I:$I,'男装-品类销售明细'!$C:$C,H$2,'男装-品类销售明细'!$G:$G,$B34) -> 1.6141824e+08 | I34: =SUMIFS('男装-品类销售明细'!$I:$I,'男装-品类销售明细'!$C:$C,I$2,'男装-品类销售明细'!$G:$G,$B34) -> 69395326 | J34: =SUMIFS('男装-品类销售明细'!$I:$I,'男装-品类销售明细'!$C:$C,J$2,'男装-品类销售明细'!$G:$G,$B34) -> 11567252 | ... L34: =SUMIFS('男装-品类销售明细'!$I:$I,'男装-品类销售明细'!$C:$C,L$2,'男装-品类销售明细'!$G:$G,$B34) -> 10253206 | M34: =L34/K34-1 -> -0.36301971
B35: 卫裤 | C35: =SUMIFS('男装-品类销售明细'!$I:$I,'男装-品类销售明细'!$C:$C,C$2,'男装-品类销售明细'!$G:$G,$B35) -> 93877704 | D35: =SUMIFS('男装-品类销售明细'!$I:$I,'男装-品类销售明细'!$C:$C,D$2,'男装-品类销售明细'!$G:$G,$B35) -> 1.4847938e+08 | E35: =SUMIFS('男装-品类销售明细'!$I:$I,'男装-品类销售明细'!$C:$C,E$2,'男装-品类销售明细'!$G:$G,$B35) -> 1.2299832e+08 | F35: =SUMIFS('男装-品类销售明细'!$I:$I,'男装-品类销售明细'!$C:$C,F$2,'男装-品类销售明细'!$G:$G,$B35) -> 1.4663449e+08 | G35: =SUMIFS('男装-品类销售明细'!$I:$I,'男装-品类销售明细'!$C:$C,G$2,'男装-品类销售明细'!$G:$G,$B35) -> 1.2755082e+08 | H35: =SUMIFS('男装-品类销售明细'!$I:$I,'男装-品类销售明细'!$C:$C,H$2,'男装-品类销售明细'!$G:$G,$B35) -> 1.2986481e+08 | I35: =SUMIFS('男装-品类销售明细'!$I:$I,'男装-品类销售明细'!$C:$C,I$2,'男装-品类销售明细'!$G:$G,$B35) -> 52329910 | J35: =SUMIFS('男装-品类销售明细'!$I:$I,'男装-品类销售明细'!$C:$C,J$2,'男装-品类销售明细'!$G:$G,$B35) -> 19329588 | ... L35: =SUMIFS('男装-品类销售明细'!$I:$I,'男装-品类销售明细'!$C:$C,L$2,'男装-品类销售明细'!$G:$G,$B35) -> 27203970 | M35: =L35/K35-1 -> -0.10131579
B36: 羊毛衫 | C36: =SUMIFS('男装-品类销售明细'!$I:$I,'男装-品类销售明细'!$C:$C,C$2,'男装-品类销售明细'!$G:$G,$B36) -> 81631018 | D36: =SUMIFS('男装-品类销售明细'!$I:$I,'男装-品类销售明细'!$C:$C,D$2,'男装-品类销售明细'!$G:$G,$B36) -> 1.47308e+08 | E36: =SUMIFS('男装-品类销售明细'!$I:$I,'男装-品类销售明细'!$C:$C,E$2,'男装-品类销售明细'!$G:$G,$B36) -> 1.270362e+08 | F36: =SUMIFS('男装-品类销售明细'!$I:$I,'男装-品类销售明细'!$C:$C,F$2,'男装-品类销售明细'!$G:$G,$B36) -> 1.2021275e+08 | G36: =SUMIFS('男装-品类销售明细'!$I:$I,'男装-品类销售明细'!$C:$C,G$2,'男装-品类销售明细'!$G:$G,$B36) -> 1.120333e+08 | H36: =SUMIFS('男装-品类销售明细'!$I:$I,'男装-品类销售明细'!$C:$C,H$2,'男装-品类销售明细'!$G:$G,$B36) -> 1.058964e+08 | I36: =SUMIFS('男装-品类销售明细'!$I:$I,'男装-品类销售明细'!$C:$C,I$2,'男装-品类销售明细'!$G:$G,$B36) -> 42411542 | J36: =SUMIFS('男装-品类销售明细'!$I:$I,'男装-品类销售明细'!$C:$C,J$2,'男装-品类销售明细'!$G:$G,$B36) -> 8019847.2 | ... L36: =SUMIFS('男装-品类销售明细'!$I:$I,'男装-品类销售明细'!$C:$C,L$2,'男装-品类销售明细'!$G:$G,$B36) -> 15038741 | M36: =L36/K36-1 -> -0.11242228
... B44: POLO衫 | C44: =SUMIFS('男装-品类销售明细'!$I:$I,'男装-品类销售明细'!$C:$C,C$2,'男装-品类销售明细'!$G:$G,$B44) -> 18168048 | D44: =SUMIFS('男装-品类销售明细'!$I:$I,'男装-品类销售明细'!$C:$C,D$2,'男装-品类销售明细'!$G:$G,$B44) -> 29700593 | E44: =SUMIFS('男装-品类销售明细'!$I:$I,'男装-品类销售明细'!$C:$C,E$2,'男装-品类销售明细'!$G:$G,$B44) -> 29706556 | F44: =SUMIFS('男装-品类销售明细'!$I:$I,'男装-品类销售明细'!$C:$C,F$2,'男装-品类销售明细'!$G:$G,$B44) -> 29044564 | G44: =SUMIFS('男装-品类销售明细'!$I:$I,'男装-品类销售明细'!$C:$C,G$2,'男装-品类销售明细'!$G:$G,$B44) -> 30909404 | H44: =SUMIFS('男装-品类销售明细'!$I:$I,'男装-品类销售明细'!$C:$C,H$2,'男装-品类销售明细'!$G:$G,$B44) -> 36815274 | I44: =SUMIFS('男装-品类销售明细'!$I:$I,'男装-品类销售明细'!$C:$C,I$2,'男装-品类销售明细'!$G:$G,$B44) -> 17453939 | J44: =SUMIFS('男装-品类销售明细'!$I:$I,'男装-品类销售明细'!$C:$C,J$2,'男装-品类销售明细'!$G:$G,$B44) -> 30660409 | ... L44: =SUMIFS('男装-品类销售明细'!$I:$I,'男装-品类销售明细'!$C:$C,L$2,'男装-品类销售明细'!$G:$G,$B44) -> 49004631 | M44: =L44/K44-1 -> -0.067177388
A45: 竞品 | C45: W1 | D45: W2 | E45: W3 | F45: W4 | G45: W5 | H45: W6 | I45: W7 | J45: W8 | K45: W9 | L45: W10 | N45: 周关键变化
A46: GXG官方旗舰店 | B46: GMV | G46: 500-750W | H46: 750-1000W | I46: 250-500W | J46: 10-25W | K46: 250-500W | L46: 250-500W | N46: 1、上周主打裤装、夹克、卫衣，其中牛仔裤G26D052031、G25D052118、G26D021062表现好，男装店基本没库存；
A47: 太平鸟男装官方旗舰店 | B47: GMV | G47: 500-750W | H47: 500-750W | I47: 100-250W | J47: 7.5-10W | K47: 75-100W | L47: 100-250W | N47: 1、上一周TOP单品均为满印/满提花元素外套；

Sheet GXG-日报
A1: 品牌 | B1: 日期 | C1: 年份 | D1: 月份 | E1: 周数 | F1: GMV | G1: 成交退款金额(退款时间) | H1: NET | I1: 商品卡GMV | J1: 直播GMV | K1: 投放消耗金额 | L1: ROI
A2: GXG | B2: 46023 | C2: =TEXT(YEAR(B2),"0")&"年" -> 2026年 | D2: =TEXT(MONTH(B2),"0")&"月" -> 1月 | E2: ="W"&TEXT(WEEKNUM(B2,2),"0") -> W1 | F2: 473933 | G2: 329167.89 | H2: =F2-G2 -> 144765.11 | I2: 53339 | J2: 413939 | K2: 15020.82 | L2: =J2/K2 -> 27.557683
A3: GXG | B3: 46024 | C3: =TEXT(YEAR(B3),"0")&"年" -> 2026年 | D3: =TEXT(MONTH(B3),"0")&"月" -> 1月 | E3: ="W"&TEXT(WEEKNUM(B3,2),"0") -> W1 | F3: 444251 | G3: 279102.56 | H3: =F3-G3 -> 165148.44 | I3: 50496 | J3: 385950 | K3: 14622.86 | L3: =J3/K3 -> 26.393606
A4: GXG | B4: 46025 | C4: =TEXT(YEAR(B4),"0")&"年" -> 2026年 | D4: =TEXT(MONTH(B4),"0")&"月" -> 1月 | E4: ="W"&TEXT(WEEKNUM(B4,2),"0") -> W1 | F4: 674234.99 | G4: 346786.75 | H4: =F4-G4 -> 327448.24 | I4: 72964 | J4: 591359.99 | K4: 22240.9 | L4: =J4/K4 -> 26.588852
A5: GXG | B5: 46026 | C5: =TEXT(YEAR(B5),"0")&"年" -> 2026年 | D5: =TEXT(MONTH(B5),"0")&"月" -> 1月 | E5: ="W"&TEXT(WEEKNUM(B5,2),"0") -> W1 | F5: 862390.42 | G5: 363357.27 | H5: =F5-G5 -> 499033.15 | I5: 72998.42 | J5: 772244 | K5: 29517.73 | L5: =J5/K5 -> 26.162039
A6: GXG | B6: 46027 | C6: =TEXT(YEAR(B6),"0")&"年" -> 2026年 | D6: =TEXT(MONTH(B6),"0")&"月" -> 1月 | E6: ="W"&TEXT(WEEKNUM(B6,2),"0") -> W2 | F6: 396291.82 | G6: 300916.79 | H6: =F6-G6 -> 95375.03 | I6: 63297.64 | J6: 322043.24 | K6: 11563.43 | L6: =J6/K6 -> 27.850148
A7: GXG | B7: 46028 | C7: =TEXT(YEAR(B7),"0")&"年" -> 2026年 | D7: =TEXT(MONTH(B7),"0")&"月" -> 1月 | E7: ="W"&TEXT(WEEKNUM(B7,2),"0") -> W2 | F7: 491573.49 | G7: 330114.1 | H7: =F7-G7 -> 161459.39 | I7: 56931.28 | J7: 421440.27 | K7: 15404.97 | L7: =J7/K7 -> 27.357422
A8: GXG | B8: 46029 | C8: =TEXT(YEAR(B8),"0")&"年" -> 2026年 | D8: =TEXT(MONTH(B8),"0")&"月" -> 1月 | E8: ="W"&TEXT(WEEKNUM(B8,2),"0") -> W2 | F8: 1055153.4 | G8: 435055.56 | H8: =F8-G8 -> 620097.79 | I8: 74211.01 | J8: 969128.7 | K8: 37826.72 | L8: =J8/K8 -> 25.620215
A9: GXG | B9: 46030 | C9: =TEXT(YEAR(B9),"0")&"年" -> 2026年 | D9: =TEXT(MONTH(B9),"0")&"月" -> 1月 | E9: ="W"&TEXT(WEEKNUM(B9,2),"0") -> W2 | F9: 690608.71 | G9: 343465.27 | H9: =F9-G9 -> 347143.44 | I9: 57300.58 | J9: 623972 | K9: 22188.28 | L9: =J9/K9 -> 28.121693
A10: GXG | B10: 46031 | C10: =TEXT(YEAR(B10),"0")&"年" -> 2026年 | D10: =TEXT(MONTH(B10),"0")&"月" -> 1月 | E10: ="W"&TEXT(WEEKNUM(B10,2),"0") -> W2 | F10: 647734.73 | G10: 350854.74 | H10: =F10-G10 -> 296879.99 | I10: 58141.46 | J10: 579154.99 | K10: 20245.73 | L10: =J10/K10 -> 28.606278
A11: GXG | B11: 46032 | C11: =TEXT(YEAR(B11),"0")&"年" -> 2026年 | D11: =TEXT(MONTH(B11),"0")&"月" -> 1月 | E11: ="W"&TEXT(WEEKNUM(B11,2),"0") -> W2 | F11: 640428.84 | G11: 400050.86 | H11: =F11-G11 -> 240377.98 | I11: 49943.2 | J11: 581678.64 | K11: 20841.12 | L11: =J11/K11 -> 27.910143
A12: GXG | B12: 46033 | C12: =TEXT(YEAR(B12),"0")&"年" -> 2026年 | D12: =TEXT(MONTH(B12),"0")&"月" -> 1月 | E12: ="W"&TEXT(WEEKNUM(B12,2),"0") -> W2 | F12: 550331.18 | G12: 348699.63 | H12: =F12-G12 -> 201631.55 | I12: 59266.18 | J12: 483041 | K12: 17587.31 | L12: =J12/K12 -> 27.465314
A13: GXG | B13: 46034 | C13: =TEXT(YEAR(B13),"0")&"年" -> 2026年 | D13: =TEXT(MONTH(B13),"0")&"月" -> 1月 | E13: ="W"&TEXT(WEEKNUM(B13,2),"0") -> W3 | F13: 449261 | G13: 344754.84 | H13: =F13-G13 -> 104506.16 | I13: 51530 | J13: 389110 | K13: 14151.91 | L13: =J13/K13 -> 27.495229
... A20: GXG | B20: 46041 | C20: =TEXT(YEAR(B20),"0")&"年" -> 2026年 | D20: =TEXT(MONTH(B20),"0")&"月" -> 1月 | E20: ="W"&TEXT(WEEKNUM(B20,2),"0") -> W4 | F20: 388005 | G20: 249460.1 | H20: =F20-G20 -> 138544.9 | I20: 85461 | J20: 295683 | K20: 9163.25 | L20: =J20/K20 -> 32.268355
A21: GXG | B21: 46042 | C21: =TEXT(YEAR(B21),"0")&"年" -> 2026年 | D21: =TEXT(MONTH(B21),"0")&"月" -> 1月 | E21: ="W"&TEXT(WEEKNUM(B21,2),"0") -> W4 | F21: 522199 | G21: 273259.92 | H21: =F21-G21 -> 248939.08 | I21: 83871 | J21: 436314 | K21: 14265.92 | L21: =J21/K21 -> 30.584358 | N21: 17949662 | O21: 118203.42 | P21: 583306.75
A22: GXG | B22: 46043 | C22: =TEXT(YEAR(B22),"0")&"年" -> 2026年 | D22: =TEXT(MONTH(B22),"0")&"月" -> 1月 | E22: ="W"&TEXT(WEEKNUM(B22,2),"0") -> W4 | F22: 613775.7 | G22: 293953.68 | H22: =F22-G22 -> 319822.02 | I22: 101984.5 | J22: 506573 | K22: 17244.66 | L22: =J22/K22 -> 29.375644 | N22: 10095223 | O22: 66131.45 | P22: 355400.89
A23: GXG | B23: 46044 | C23: =TEXT(YEAR(B23),"0")&"年" -> 2026年 | D23: =TEXT(MONTH(B23),"0")&"月" -> 1月 | E23: ="W"&TEXT(WEEKNUM(B23,2),"0") -> W4 | F23: 607412.9 | G23: 314737.8 | H23: =F23-G23 -> 292675.1 | I23: 102105.9 | J23: 502171 | K23: 16312.17 | L23: =J23/K23 -> 30.785052 | N23: =N21-N22 -> 7854439.5 | O23: =O21-O22 -> 52071.97 | P23: =P21-P22 -> 227905.86
A24: GXG | B24: 46045 | C24: =TEXT(YEAR(B24),"0")&"年" -> 2026年 | D24: =TEXT(MONTH(B24),"0")&"月" -> 1月 | E24: ="W"&TEXT(WEEKNUM(B24,2),"0") -> W4 | F24: 864204.99 | G24: 349889.84 | H24: =F24-G24 -> 514315.15 | I24: 140424 | J24: 716530.99 | K24: 25100.97 | L24: =J24/K24 -> 28.545948 | N24: =N23+O23+P23 -> 8134417.4
A25: GXG | B25: 46046 | C25: =TEXT(YEAR(B25),"0")&"年" -> 2026年 | D25: =TEXT(MONTH(B25),"0")&"月" -> 1月 | E25: ="W"&TEXT(WEEKNUM(B25,2),"0") -> W4 | F25: 801577 | G25: 339401.73 | H25: =F25-G25 -> 462175.27 | I25: 125083 | J25: 669818 | K25: 22459.24 | L25: =J25/K25 -> 29.823716
A26: GXG | B26: 46047 | C26: =TEXT(YEAR(B26),"0")&"年" -> 2026年 | D26: =TEXT(MONTH(B26),"0")&"月" -> 1月 | E26: ="W"&TEXT(WEEKNUM(B26,2),"0") -> W4 | F26: 808971.2 | G26: 336312.3 | H26: =F26-G26 -> 472658.9 | I26: 127232.2 | J26: 670202 | K26: 23103.06 | L26: =J26/K26 -> 29.009231
A27: GXG | B27: 46048 | C27: =TEXT(YEAR(B27),"0")&"年" -> 2026年 | D27: =TEXT(MONTH(B27),"0")&"月" -> 1月 | E27: ="W"&TEXT(WEEKNUM(B27,2),"0") -> W5 | F27: 674719.5 | G27: 352180.02 | H27: =F27-G27 -> 322539.48 | I27: 113110.5 | J27: 551231 | K27: 18427.46 | L27: =J27/K27 -> 29.913564
A28: GXG | B28: 46049 | C28: =TEXT(YEAR(B28),"0")&"年" -> 2026年 | D28: =TEXT(MONTH(B28),"0")&"月" -> 1月 | E28: ="W"&TEXT(WEEKNUM(B28,2),"0") -> W5 | F28: 521175.2 | G28: 375825.18 | H28: =F28-G28 -> 145350.02 | I28: 109705.2 | J28: 396472 | K28: 13582.51 | L28: =J28/K28 -> 29.189892
A29: GXG | B29: 46050 | C29: =TEXT(YEAR(B29),"0")&"年" -> 2026年 | D29: =TEXT(MONTH(B29),"0")&"月" -> 1月 | E29: ="W"&TEXT(WEEKNUM(B29,2),"0") -> W5 | F29: 535475.5 | G29: 342941 | H29: =F29-G29 -> 192534.5 | I29: 113159.5 | J29: 411551 | K29: 14263.25 | L29: =J29/K29 -> 28.853943
A30: GXG | B30: 46051 | C30: =TEXT(YEAR(B30),"0")&"年" -> 2026年 | D30: =TEXT(MONTH(B30),"0")&"月" -> 1月 | E30: ="W"&TEXT(WEEKNUM(B30,2),"0") -> W5 | F30: 916667.5 | G30: 456802.43 | H30: =F30-G30 -> 459865.07 | I30: 167016 | J30: 732694 | K30: 26275.65 | L30: =J30/K30 -> 27.884905
A31: GXG | B31: 46052 | C31: =TEXT(YEAR(B31),"0")&"年" -> 2026年 | D31: =TEXT(MONTH(B31),"0")&"月" -> 1月 | E31: ="W"&TEXT(WEEKNUM(B31,2),"0") -> W5 | F31: 599854 | G31: 356815.92 | H31: =F31-G31 -> 243038.08 | I31: 146623 | J31: 441134 | K31: 16911.94 | L31: =J31/K31 -> 26.084175
A32: GXG | B32: 46053 | C32: =TEXT(YEAR(B32),"0")&"年" -> 2026年 | D32: =TEXT(MONTH(B32),"0")&"月" -> 1月 | E32: ="W"&TEXT(WEEKNUM(B32,2),"0") -> W5 | F32: 902625.8 | G32: 412848.81 | H32: =F32-G32 -> 489776.99 | I32: 163059.8 | J32: 719319 | K32: 25311.98 | L32: =J32/K32 -> 28.418125
A33: GXG | B33: 46054 | C33: =TEXT(YEAR(B33),"0")&"年" -> 2026年 | D33: =TEXT(MONTH(B33),"0")&"月" -> 2月 | E33: ="W"&TEXT(WEEKNUM(B33,2),"0") -> W5 | F33: 666120.4 | G33: 437246.28 | H33: =F33-G33 -> 228874.12 | I33: 171702.4 | J33: 470865 | K33: 15898.54 | L33: =J33/K33 -> 29.61687
A34: GXG | B34: 46055 | C34: =TEXT(YEAR(B34),"0")&"年" -> 2026年 | D34: =TEXT(MONTH(B34),"0")&"月" -> 2月 | E34: ="W"&TEXT(WEEKNUM(B34,2),"0") -> W6 | F34: 1496727.9 | G34: 613931.51 | H34: =F34-G34 -> 882796.39 | I34: 224377.6 | J34: 1258502 | K34: 41250.82 | L34: =J34/K34 -> 30.508533
A35: GXG | B35: 46056 | C35: =TEXT(YEAR(B35),"0")&"年" -> 2026年 | D35: =TEXT(MONTH(B35),"0")&"月" -> 2月 | E35: ="W"&TEXT(WEEKNUM(B35,2),"0") -> W6 | F35: 1570124.3 | G35: 648252.62 | H35: =F35-G35 -> 921871.71 | I35: 229940.33 | J35: 1327530.1 | K35: 44600.68 | L35: =J35/K35 -> 29.764795
A36: GXG | B36: 46057 | C36: =TEXT(YEAR(B36),"0")&"年" -> 2026年 | D36: =TEXT(MONTH(B36),"0")&"月" -> 2月 | E36: ="W"&TEXT(WEEKNUM(B36,2),"0") -> W6 | F36: 914322.48 | G36: 567195.86 | H36: =F36-G36 -> 347126.62 | I36: 202259.38 | J36: 697666.3 | K36: 23364.95 | L36: =J36/K36 -> 29.859525
... A68: GXG | B68: 46089 | C68: =TEXT(YEAR(B68),"0")&"年" -> 2026年 | D68: =TEXT(MONTH(B68),"0")&"月" -> 3月 | E68: ="W"&TEXT(WEEKNUM(B68,2),"0") -> W10 | F68: 592386.9 | G68: 229605.25 | H68: =F68-G68 -> 362781.65 | I68: 59605.3 | J68: 520537.6 | K68: 16867.03 | L68: =J68/K68 -> 30.861248

Sheet Champion-日报
A1: 品牌 | B1: 日期 | C1: 年份 | D1: 月份 | E1: 周数 | F1: GMV | G1: NET | H1: 商品卡GMV | I1: 直播GMV | J1: 投放消耗金额 | K1: ROI
A2: Champion | B2: 46023 | C2: =TEXT(YEAR(B2),"0")&"年" -> 2026年 | D2: =TEXT(MONTH(B2),"0")&"月" -> 1月 | E2: ="W"&TEXT(WEEKNUM(B2,2),"0") -> W1 | F2: 120915.37 | G2: 25383.25 | H2: 39045.27 | I2: 79062.42 | J2: 2888.73 | K2: =I2/J2 -> 27.369266
A3: Champion | B3: 46024 | C3: =TEXT(YEAR(B3),"0")&"年" -> 2026年 | D3: =TEXT(MONTH(B3),"0")&"月" -> 1月 | E3: ="W"&TEXT(WEEKNUM(B3,2),"0") -> W1 | F3: 128733.26 | G3: 29809.7 | H3: 31165.7 | I3: 96205.56 | J3: 3941.43 | K3: =I3/J3 -> 24.408796
A4: Champion | B4: 46025 | C4: =TEXT(YEAR(B4),"0")&"年" -> 2026年 | D4: =TEXT(MONTH(B4),"0")&"月" -> 1月 | E4: ="W"&TEXT(WEEKNUM(B4,2),"0") -> W1 | F4: 154039.77 | G4: 30056.77 | H4: 35211.77 | I4: 117580.2 | J4: 4361.18 | K4: =I4/J4 -> 26.960639
A5: Champion | B5: 46026 | C5: =TEXT(YEAR(B5),"0")&"年" -> 2026年 | D5: =TEXT(MONTH(B5),"0")&"月" -> 1月 | E5: ="W"&TEXT(WEEKNUM(B5,2),"0") -> W1 | F5: 199754.84 | G5: 51063.71 | H5: 47729.18 | I5: 148851.56 | J5: 5997.02 | K5: =I5/J5 -> 24.820921
A6: Champion | B6: 46027 | C6: =TEXT(YEAR(B6),"0")&"年" -> 2026年 | D6: =TEXT(MONTH(B6),"0")&"月" -> 1月 | E6: ="W"&TEXT(WEEKNUM(B6,2),"0") -> W2 | F6: 166851.16 | G6: 37389.96 | H6: 39437.2 | I6: 124405.96 | J6: 4923.66 | K6: =I6/J6 -> 25.266968
A7: Champion | B7: 46028 | C7: =TEXT(YEAR(B7),"0")&"年" -> 2026年 | D7: =TEXT(MONTH(B7),"0")&"月" -> 1月 | E7: ="W"&TEXT(WEEKNUM(B7,2),"0") -> W2 | F7: 161793.63 | G7: 39194.05 | H7: 36461 | I7: 124689.63 | J7: 4450.24 | K7: =I7/J7 -> 28.01863
A8: Champion | B8: 46029 | C8: =TEXT(YEAR(B8),"0")&"年" -> 2026年 | D8: =TEXT(MONTH(B8),"0")&"月" -> 1月 | E8: ="W"&TEXT(WEEKNUM(B8,2),"0") -> W2 | F8: 85659.2 | G8: 27026.19 | H8: 32491.29 | I8: 51023.4 | J8: 1851.23 | K8: =I8/J8 -> 27.561891
A9: Champion | B9: 46030 | C9: =TEXT(YEAR(B9),"0")&"年" -> 2026年 | D9: =TEXT(MONTH(B9),"0")&"月" -> 1月 | E9: ="W"&TEXT(WEEKNUM(B9,2),"0") -> W2 | F9: 76453.65 | G9: 30551.85 | H9: 36126.6 | I9: 38260.05 | J9: 1249.52 | K9: =I9/J9 -> 30.619798
A10: Champion | B10: 46031 | C10: =TEXT(YEAR(B10),"0")&"年" -> 2026年 | D10: =TEXT(MONTH(B10),"0")&"月" -> 1月 | E10: ="W"&TEXT(WEEKNUM(B10,2),"0") -> W2 | F10: 86045.2 | G10: 34732.37 | H10: 29344.9 | I10: 53400.25 | J10: 1736.63 | K10: =I10/J10 -> 30.749354
A11: Champion | B11: 46032 | C11: =TEXT(YEAR(B11),"0")&"年" -> 2026年 | D11: =TEXT(MONTH(B11),"0")&"月" -> 1月 | E11: ="W"&TEXT(WEEKNUM(B11,2),"0") -> W2 | F11: 124404.38 | G11: 47597.81 | H11: 35876.6 | I11: 85364.78 | J11: 2859.81 | K11: =I11/J11 -> 29.849808
A12: Champion | B12: 46033 | C12: =TEXT(YEAR(B12),"0")&"年" -> 2026年 | D12: =TEXT(MONTH(B12),"0")&"月" -> 1月 | E12: ="W"&TEXT(WEEKNUM(B12,2),"0") -> W2 | F12: 145151.46 | G12: 64360.42 | H12: 39481.14 | I12: 102292.32 | J12: 3336.38 | K12: =I12/J12 -> 30.659673
A13: Champion | B13: 46034 | C13: =TEXT(YEAR(B13),"0")&"年" -> 2026年 | D13: =TEXT(MONTH(B13),"0")&"月" -> 1月 | E13: ="W"&TEXT(WEEKNUM(B13,2),"0") -> W3 | F13: 112458.13 | G13: 42052.5 | H13: 32784.5 | I13: 78079.63 | J13: 2608.37 | K13: =I13/J13 -> 29.934262
... A26: Champion | B26: 46047 | C26: =TEXT(YEAR(B26),"0")&"年" -> 2026年 | D26: =TEXT(MONTH(B26),"0")&"月" -> 1月 | E26: ="W"&TEXT(WEEKNUM(B26,2),"0") -> W4 | F26: 279682.58 | G26: 197341.93 | H26: 112236.67 | I26: 162955.14 | J26: 5534.58 | K26: =I26/J26 -> 29.443091

Sheet GXG-直播明细
A1: 品牌 | B1: 直播日期 | C1: 年份 | D1: 月份 | E1: 周数 | F1: 直播开始时间 | G1: 直播结束时间 | H1: 直播时长(分钟) | I1: 直播间曝光人数 | J1: 直播间曝光次数 | K1: 直播间观看人数 | L1: 单小时观看人数 | M1: 直播间观看次数 | N1: 最高在线人数 | O1: 平均在线人数 | P1: 人均观看时长(分钟) | Q1: 评论次数 | R1: 新加直播团人数 | S1: 新增粉丝数 | T1: 取关粉丝数 | U1: 观看老粉占比 | V1: 带货商品数 | W1: 直播间商品曝光人数 | X1: 直播间商品点击人数 | Y1: 直播间商品曝光次数 | Z1: 直播间商品点击次数 | AA1: 直播间成交订单数 | AB1: 直播间成交金额 | AC1: 直播间用户支付金额 | AD1: 单小时用户支付金额 | AE1: 直播间成交件数 | AF1: 直播间成交人数 | AG1: 直播间退款订单数 | AH1: 直播间退款金额 | AI1: 直播间退款人数 | AJ1: 预估佣金支出 | AK1: 商品曝光-点击率(次数) | AL1: 商品曝光-点击率(人数) | AM1: 商品点击-成交率(次数) | AN1: 商品点击-成交率(人数) | AO1: 观看-成交率(次数) | AP1: 观看-成交率(人数) | AQ1: 预售订单数 | AR1: 预售全款金额 | AS1: 新加购物团人数 | AT1: 直播间投放消耗 | AU1: 净成交金额 | AV1: 净成交订单数 | AW1: 1小时退款金额 | AX1: 1小时退款订单数 | AY1: 1小时退款率 | AZ1: 消费券引导支付金额 | BA1: 消费券引导支付占比 | BB1: 消费券补贴金额 | BC1: 消费券使用量
A2: GXG | B2: =DATE(YEAR(F2),MONTH(F2),DAY(F2)) -> 46028 | C2: =TEXT(YEAR(B2),"0")&"年" -> 2026年 | D2: =TEXT(MONTH(B2),"0")&"月" -> 1月 | E2: ="W"&TEXT(WEEKNUM(B2,2),"0") -> W2 | F2: 2026/01/06 20:10:13 | G2: 2026/01/07 02:21:24 | H2: 371 | I2: 982895 | J2: 1755677 | K2: 78132 | L2: 12629.662 | M2: 101147 | N2: 602 | O2: 392 | P2: 0.87 | Q2: 3984 | R2: 3 | S2: 437 | T2: 39 | U2: 0.2576 | V2: 74 | W2: 75686 | X2: 24887 | Y2: 602586 | Z2: 62858 | AA2: 1048 | AB2: 470829 | AC2: 467933.92 | AD2: 75639.267 | AE2: 1048 | AF2: 913 | AG2: 592 | AH2: 268010.7 | AI2: 529 | AJ2: 0 | AK2: 0.1043 | AL2: 0.3288 | AM2: 0.0167 | AN2: 0.0367 | AO2: 0.0104 | AP2: 0.0117 | AQ2: 0 | AR2: 0 | AS2: 160 | AT2: 16119.99 | AU2: 409096 | AV2: 913 | AW2: 61733 | AX2: 135 | AY2: 0.1311 | AZ2: - | BA2: - | BB2: - | BC2: -
A3: GXG | B3: =DATE(YEAR(F3),MONTH(F3),DAY(F3)) -> 46029 | C3: =TEXT(YEAR(B3),"0")&"年" -> 2026年 | D3: =TEXT(MONTH(B3),"0")&"月" -> 1月 | E3: ="W"&TEXT(WEEKNUM(B3,2),"0") -> W2 | F3: 2026/01/07 19:59:23 | G3: 2026/01/08 01:38:34 | H3: 339 | I3: 898752 | J3: 1556099 | K3: 65281 | L3: 11547.914 | M3: 84452 | N3: 802 | O3: 368 | P3: 0.83 | Q3: 3824 | R3: 1 | S3: 372 | T3: 49 | U3: 0.2542 | V3: 74 | W3: 62687 | X3: 19503 | Y3: 474591 | Z3: 49377 | AA3: 840 | AB3: 375509.7 | AC3: 372226.17 | AD3: 65845.129 | AE3: 840 | AF3: 755 | AG3: 445 | AH3: 200152.71 | AI3: 403 | AJ3: 0 | AK3: 0.104 | AL3: 0.3111 | AM3: 0.017 | AN3: 0.0387 | AO3: 0.0099 | AP3: 0.0116 | AQ3: 0 | AR3: 0 | AS3: 131 | AT3: 16150.03 | AU3: 324205.7 | AV3: 728 | AW3: 51304 | AX3: 112 | AY3: 0.1366 | AZ3: - | BA3: - | BB3: - | BC3: -
A4: GXG | B4: =DATE(YEAR(F4),MONTH(F4),DAY(F4)) -> 46026 | C4: =TEXT(YEAR(B4),"0")&"年" -> 2026年 | D4: =TEXT(MONTH(B4),"0")&"月" -> 1月 | E4: ="W"&TEXT(WEEKNUM(B4,2),"0") -> W1 | F4: 2026/01/04 08:00:21 | G4: 2026/01/04 13:25:43 | H4: 325 | I4: 1163065 | J4: 1863643 | K4: 72986 | L4: 13459.154 | M4: 92498 | N4: 969 | O4: 399 | P4: 0.9 | Q4: 4303 | R4: 1 | S4: 711 | T4: 42 | U4: 0.1877 | V4: 154 | W4: 70412 | X4: 18120 | Y4: 475460 | Z4: 44140 | AA4: 973 | AB4: 367425 | AC4: 365531.91 | AD4: 67406.765 | AE4: 973 | AF4: 853 | AG4: 502 | AH4: 190854.41 | AI4: 437 | AJ4: 0 | AK4: 0.0928 | AL4: 0.2573 | AM4: 0.022 | AN4: 0.0471 | AO4: 0.0105 | AP4: 0.0117 | AQ4: 0 | AR4: 0 | AS4: 211 | AT4: 14024.06 | AU4: 316794.1 | AV4: 840 | AW4: 50630.9 | AX4: 133 | AY4: 0.1378 | AZ4: - | BA4: - | BB4: - | BC4: -
A5: GXG | B5: =DATE(YEAR(F5),MONTH(F5),DAY(F5)) -> 46029 | C5: =TEXT(YEAR(B5),"0")&"年" -> 2026年 | D5: =TEXT(MONTH(B5),"0")&"月" -> 1月 | E5: ="W"&TEXT(WEEKNUM(B5,2),"0") -> W2 | F5: 2026/01/07 08:00:16 | G5: 2026/01/07 13:00:22 | H5: 300 | I5: 901375 | J5: 1524187 | K5: 65119 | L5: 13019.46 | M5: 84167 | N5: 860 | O5: 442 | P5: 0.96 | Q5: 4243 | R5: 6 | S5: 537 | T5: 30 | U5: 0.2444 | V5: 74 | W5: 63021 | X5: 17520 | Y5: 466930 | Z5: 39873 | AA5: 758 | AB5: 343189 | AC5: 341308.91 | AD5: 68239.036 | AE5: 758 | AF5: 670 | AG5: 377 | AH5: 172156.03 | AI5: 344 | AJ5: 0 | AK5: 0.0854 | AL5: 0.278 | AM5: 0.019 | AN5: 0.0382 | AO5: 0.009 | AP5: 0.0103 | AQ5: 0 | AR5: 0 | AS5: 223 | AT5: 12735.69 | AU5: 303549 | AV5: 674 | AW5: 39640 | AX5: 84 | AY5: 0.1155 | AZ5: - | BA5: - | BB5: - | BC5: -
A6: GXG | B6: =DATE(YEAR(F6),MONTH(F6),DAY(F6)) -> 46025 | C6: =TEXT(YEAR(B6),"0")&"年" -> 2026年 | D6: =TEXT(MONTH(B6),"0")&"月" -> 1月 | E6: ="W"&TEXT(WEEKNUM(B6,2),"0") -> W1 | F6: 2026/01/03 08:00:51 | G6: 2026/01/03 13:03:13 | H6: 302 | I6: 1038565 | J6: 1655513 | K6: 70127 | L6: 13915.621 | M6: 88786 | N6: 1090 | O6: 437 | P6: 0.86 | Q6: 3802 | R6: 4 | S6: 644 | T6: 45 | U6: 0.1915 | V6: 154 | W6: 67615 | X6: 17666 | Y6: 466477 | Z6: 42412 | AA6: 809 | AB6: 307922.99 | AC6: 306252.78 | AD6: 60771.139 | AE6: 809 | AF6: 736 | AG6: 445 | AH6: 164197.11 | AI6: 405 | AJ6: 0 | AK6: 0.0909 | AL6: 0.2613 | AM6: 0.0191 | AN6: 0.0417 | AO6: 0.0091 | AP6: 0.0105 | AQ6: 0 | AR6: 0 | AS6: 246 | AT6: 11040.16 | AU6: 268937.99 | AV6: 708 | AW6: 38985 | AX6: 101 | AY6: 0.1266 | AZ6: - | BA6: - | BB6: - | BC6: -
A7: GXG | B7: =DATE(YEAR(F7),MONTH(F7),DAY(F7)) -> 46032 | C7: =TEXT(YEAR(B7),"0")&"年" -> 2026年 | D7: =TEXT(MONTH(B7),"0")&"月" -> 1月 | E7: ="W"&TEXT(WEEKNUM(B7,2),"0") -> W2 | F7: 2026/01/10 08:00:13 | G7: 2026/01/10 13:25:32 | H7: 325 | I7: 940903 | J7: 1548192 | K7: 68242 | L7: 12586.26 | M7: 87383 | N7: 978 | O7: 411 | P7: 1 | Q7: 5112 | R7: 5 | S7: 591 | T7: 51 | U7: 0.1946 | V7: 76 | W7: 66040 | X7: 16574 | Y7: 419957 | Z7: 39953 | AA7: 786 | AB7: 295108 | AC7: 293339.69 | AD7: 54102.305 | AE7: 786 | AF7: 698 | AG7: 422 | AH7: 157511.24 | AI7: 384 | AJ7: 0 | AK7: 0.0951 | AL7: 0.251 | AM7: 0.0197 | AN7: 0.0421 | AO7: 0.009 | AP7: 0.0102 | AQ7: 0 | AR7: 0 | AS7: 188 | AT7: 10329.13 | AU7: 252393 | AV7: 675 | AW7: 42715 | AX7: 111 | AY7: 0.1447 | AZ7: - | BA7: - | BB7: - | BC7: -
A8: GXG | B8: =DATE(YEAR(F8),MONTH(F8),DAY(F8)) -> 46030 | C8: =TEXT(YEAR(B8),"0")&"年" -> 2026年 | D8: =TEXT(MONTH(B8),"0")&"月" -> 1月 | E8: ="W"&TEXT(WEEKNUM(B8,2),"0") -> W2 | F8: 2026/01/08 20:00:56 | G8: 2026/01/09 01:55:01 | H8: 354 | I8: 577758 | J8: 1049310 | K8: 48017 | L8: 8136.5592 | M8: 63335 | N8: 476 | O8: 166 | P8: 0.84 | Q8: 3007 | R8: 0 | S8: 220 | T8: 38 | U8: 0.2872 | V8: 76 | W8: 45970 | X8: 13312 | Y8: 347810 | Z8: 34232 | AA8: 589 | AB8: 255842 | AC8: 253944.26 | AD8: 43031.27 | AE8: 589 | AF8: 543 | AG8: 307 | AH8: 132954.16 | AI8: 285 | AJ8: 0 | AK8: 0.0984 | AL8: 0.2896 | AM8: 0.0172 | AN8: 0.0408 | AO8: 0.0093 | AP8: 0.0113 | AQ8: 0 | AR8: 0 | AS8: 95 | AT8: 8625.92 | AU8: 225332 | AV8: 519 | AW8: 30510 | AX8: 70 | AY8: 0.1193 | AZ8: - | BA8: - | BB8: - | BC8: -
A9: GXG | B9: =DATE(YEAR(F9),MONTH(F9),DAY(F9)) -> 46033 | C9: =TEXT(YEAR(B9),"0")&"年" -> 2026年 | D9: =TEXT(MONTH(B9),"0")&"月" -> 1月 | E9: ="W"&TEXT(WEEKNUM(B9,2),"0") -> W2 | F9: 2026/01/11 08:03:22 | G9: 2026/01/11 13:17:47 | H9: 314 | I9: 598689 | J9: 1000261 | K9: 46366 | L9: 8848.0042 | M9: 59677 | N9: 880 | O9: 236 | P9: 0.91 | Q9: 3104 | R9: 2 | S9: 403 | T9: 40 | U9: 0.2287 | V9: 74 | W9: 44232 | X9: 11539 | Y9: 296678 | Z9: 29218 | AA9: 655 | AB9: 245474 | AC9: 243563.86 | AD9: 46479.189 | AE9: 655 | AF9: 536 | AG9: 340 | AH9: 129027.29 | AI9: 279 | AJ9: 0 | AK9: 0.0985 | AL9: 0.2609 | AM9: 0.0224 | AN9: 0.0465 | AO9: 0.011 | AP9: 0.0116 | AQ9: 0 | AR9: 0 | AS9: 168 | AT9: 7824.68 | AU9: 208701 | AV9: 561 | AW9: 36773 | AX9: 94 | AY9: 0.1498 | AZ9: - | BA9: - | BB9: - | BC9: -
A10: GXG | B10: =DATE(YEAR(F10),MONTH(F10),DAY(F10)) -> 46024 | C10: =TEXT(YEAR(B10),"0")&"年" -> 2026年 | D10: =TEXT(MONTH(B10),"0")&"月" -> 1月 | E10: ="W"&TEXT(WEEKNUM(B10,2),"0") -> W1 | F10: 2026/01/02 07:59:38 | G10: 2026/01/02 13:01:47 | H10: 302 | I10: 814223 | J10: 1410676 | K10: 69481 | L10: 13797.319 | M10: 89820 | N10: 1003 | O10: 437 | P10: 0.9 | Q10: 3956 | R10: 1 | S10: 427 | T10: 35 | U10: 0.249 | V10: 154 | W10: 67610 | X10: 16971 | Y10: 455877 | Z10: 40629 | AA10: 787 | AB10: 243057 | AC10: 240211.48 | AD10: 47700.443 | AE10: 796 | AF10: 640 | AG10: 356 | AH10: 127480.2 | AI10: 305 | AJ10: 0 | AK10: 0.0891 | AL10: 0.251 | AM10: 0.0194 | AN10: 0.0377 | AO10: 0.0088 | AP10: 0.0092 | AQ10: 0 | AR10: 0 | AS10: 174 | AT10: 9554.13 | AU10: 208240 | AV10: 705 | AW10: 34817 | AX10: 82 | AY10: 0.1432 | AZ10: - | BA10: - | BB10: - | BC10: -
A11: GXG | B11: =DATE(YEAR(F11),MONTH(F11),DAY(F11)) -> 46026 | C11: =TEXT(YEAR(B11),"0")&"年" -> 2026年 | D11: =TEXT(MONTH(B11),"0")&"月" -> 1月 | E11: ="W"&TEXT(WEEKNUM(B11,2),"0") -> W1 | F11: 2026/01/04 19:57:04 | G11: 2026/01/05 01:44:06 | H11: 347 | I11: 633373 | J11: 1150337 | K11: 56431 | L11: 9756.5844 | M11: 74852 | N11: 838 | O11: 198 | P11: 0.76 | Q11: 3039 | R11: 1 | S11: 257 | T11: 33 | U11: 0.2508 | V11: 154 | W11: 53308 | X11: 13897 | Y11: 403125 | Z11: 36476 | AA11: 602 | AB11: 227092 | AC11: 224834.33 | AD11: 38872.519 | AE11: 603 | AF11: 526 | AG11: 323 | AH11: 121874.55 | AI11: 285 | AJ11: 0 | AK11: 0.0905 | AL11: 0.2607 | AM11: 0.0165 | AN11: 0.0378 | AO11: 0.008 | AP11: 0.0093 | AQ11: 0 | AR11: 0 | AS11: 90 | AT11: 8720.02 | AU11: 193997 | AV11: 516 | AW11: 33095 | AX11: 86 | AY11: 0.1457 | AZ11: - | BA11: - | BB11: - | BC11: -
A12: GXG | B12: =DATE(YEAR(F12),MONTH(F12),DAY(F12)) -> 46031 | C12: =TEXT(YEAR(B12),"0")&"年" -> 2026年 | D12: =TEXT(MONTH(B12),"0")&"月" -> 1月 | E12: ="W"&TEXT(WEEKNUM(B12,2),"0") -> W2 | F12: 2026/01/09 08:01:13 | G12: 2026/01/09 13:25:39 | H12: 324 | I12: 616826 | J12: 1040705 | K12: 46689 | L12: 8634.5628 | M12: 60089 | N12: 844 | O12: 215 | P12: 0.96 | Q12: 3267 | R12: 2 | S12: 338 | T12: 24 | U12: 0.2412 | V12: 76 | W12: 44772 | X12: 10727 | Y12: 271514 | Z12: 25222 | AA12: 582 | AB12: 219431.99 | AC12: 217959.17 | AD12: 40308.898 | AE12: 582 | AF12: 511 | AG12: 280 | AH12: 106065.11 | AI12: 252 | AJ12: 0 | AK12: 0.0929 | AL12: 0.2396 | AM12: 0.0231 | AN12: 0.0476 | AO12: 0.0097 | AP12: 0.0109 | AQ12: 0 | AR12: 0 | AS12: 134 | AT12: 7264.25 | AU12: 187815.99 | AV12: 498 | AW12: 31616 | AX12: 84 | AY12: 0.1441 | AZ12: - | BA12: - | BB12: - | BC12: -
A13: GXG | B13: =DATE(YEAR(F13),MONTH(F13),DAY(F13)) -> 46031 | C13: =TEXT(YEAR(B13),"0")&"年" -> 2026年 | D13: =TEXT(MONTH(B13),"0")&"月" -> 1月 | E13: ="W"&TEXT(WEEKNUM(B13,2),"0") -> W2 | F13: 2026/01/09 19:57:22 | G13: 2026/01/10 01:32:31 | H13: 335 | I13: 524034 | J13: 957389 | K13: 45273 | L13: 8104.9679 | M13: 59263 | N13: 473 | O13: 149 | P13: 0.75 | Q13: 2714 | R13: 0 | S13: 229 | T13: 45 | U13: 0.2683 | V13: 75 | W13: 42889 | X13: 13177 | Y13: 325688 | Z13: 34488 | AA13: 548 | AB13: 216564 | AC13: 214844.01 | AD13: 38462.302 | AE13: 548 | AF13: 486 | AG13: 271 | AH13: 108030.03 | AI13: 243 | AJ13: 0 | AK13: 0.1059 | AL13: 0.3072 | AM13: 0.0159 | AN13: 0.0369 | AO13: 0.0092 | AP13: 0.0107 | AQ13: 0 | AR13: 0 | AS13: 72 | AT13: 7438.88 | AU13: 189583 | AV13: 484 | AW13: 26981 | AX13: 64 | AY13: 0.1246 | AZ13: - | BA13: - | BB13: - | BC13: -
A14: GXG | B14: =DATE(YEAR(F14),MONTH(F14),DAY(F14)) -> 46040 | C14: =TEXT(YEAR(B14),"0")&"年" -> 2026年 | D14: =TEXT(MONTH(B14),"0")&"月" -> 1月 | E14: ="W"&TEXT(WEEKNUM(B14,2),"0") -> W3 | F14: 2026/01/18 07:59:37 | G14: 2026/01/18 13:03:54 | H14: 304 | I14: 530540 | J14: 857317 | K14: 44109 | L14: 8697.6174 | M14: 55585 | N14: 719 | O14: 154 | P14: 0.64 | Q14: 2220 | R14: 0 | S14: 448 | T14: 30 | U14: 0.1932 | V14: 79 | W14: 40636 | X14: 11037 | Y14: 260942 | Z14: 26099 | AA14: 508 | AB14: 201785 | AC14: 192399.81 | AD14: 37938.288 | AE14: 513 | AF14: 458 | AG14: 218 | AH14: 85459.58 | AI14: 196 | AJ14: 0 | AK14: 0.1 | AL14: 0.2716 | AM14: 0.0195 | AN14: 0.0415 | AO14: 0.0091 | AP14: 0.0104 | AQ14: 0 | AR14: 0 | AS14: 82 | AT14: 5866.5 | AU14: 136648.04 | AV14: 354 | AW14: 65136.96 | AX14: 154 | AY14: 0.3228 | AZ14: 130057.51 | BA14: 0.67597525 | BB14: 8521.31 | BC14: 322
A15: GXG | B15: =DATE(YEAR(F15),MONTH(F15),DAY(F15)) -> 46034 | C15: =TEXT(YEAR(B15),"0")&"年" -> 2026年 | D15: =TEXT(MONTH(B15),"0")&"月" -> 1月 | E15: ="W"&TEXT(WEEKNUM(B15,2),"0") -> W3 | F15: 2026/01/12 08:02:45 | G15: 2026/01/12 13:19:48 | H15: 317 | I15: 482448 | J15: 836106 | K15: 36802 | L15: 6964.5797 | M15: 47420 | N15: 595 | O15: 162 | P15: 0.89 | Q15: 2477 | R15: 2 | S15: 281 | T15: 15 | U15: 0.2465 | V15: 76 | W15: 34991 | X15: 8845 | Y15: 227771 | Z15: 21754 | AA15: 514 | AB15: 191196 | AC15: 189405.16 | AD15: 35843.903 | AE15: 515 | AF15: 461 | AG15: 241 | AH15: 90493.18 | AI15: 223 | AJ15: 0 | AK15: 0.0955 | AL15: 0.2528 | AM15: 0.0236 | AN15: 0.0521 | AO15: 0.0108 | AP15: 0.0125 | AQ15: 0 | AR15: 0 | AS15: 103 | AT15: 6485.42 | AU15: 168256 | AV15: 454 | AW15: 22940 | AX15: 60 | AY15: 0.12 | AZ15: - | BA15: - | BB15: - | BC15: -
A16: GXG | B16: =DATE(YEAR(F16),MONTH(F16),DAY(F16)) -> 46039 | C16: =TEXT(YEAR(B16),"0")&"年" -> 2026年 | D16: =TEXT(MONTH(B16),"0")&"月" -> 1月 | E16: ="W"&TEXT(WEEKNUM(B16,2),"0") -> W3 | F16: 2026/01/17 08:08:35 | G16: 2026/01/17 13:29:41 | H16: 321 | I16: 506574 | J16: 851596 | K16: 44083 | L16: 8237.247 | M16: 56499 | N16: 667 | O16: 147 | P16: 0.66 | Q16: 2481 | R16: 0 | S16: 320 | T16: 26 | U16: 0.2057 | V16: 79 | W16: 40762 | X16: 11116 | Y16: 254560 | Z16: 25916 | AA16: 510 | AB16: 198152 | AC16: 188518.32 | AD16: 35226.095 | AE16: 511 | AF16: 448 | AG16: 221 | AH16: 80999.64 | AI16: 197 | AJ16: 0 | AK16: 0.1018 | AL16: 0.2727 | AM16: 0.0197 | AN16: 0.0403 | AO16: 0.009 | AP16: 0.0102 | AQ16: 0 | AR16: 0 | AS16: 63 | AT16: 6259 | AU16: 150430.4 | AV16: 391 | AW16: 47721.6 | AX16: 119 | AY16: 0.2408 | AZ16: 127699.35 | BA16: 0.6773843 | BB16: 8367.36 | BC16: 322
A17: GXG | B17: =DATE(YEAR(F17),MONTH(F17),DAY(F17)) -> 46026 | C17: =TEXT(YEAR(B17),"0")&"年" -> 2026年 | D17: =TEXT(MONTH(B17),"0")&"月" -> 1月 | E17: ="W"&TEXT(WEEKNUM(B17,2),"0") -> W1 | F17: 2026/01/04 14:01:29 | G17: 2026/01/04 19:15:47 | H17: 314 | I17: 433081 | J17: 718482 | K17: 28065 | L17: 5357.6201 | M17: 35802 | N17: 121 | O17: 80 | P17: 0.59 | Q17: 1383 | R17: 1 | S17: 222 | T17: 27 | U17: 0.2 | V17: 154 | W17: 25912 | X17: 7732 | Y17: 219384 | Z17: 18716 | AA17: 498 | AB17: 190218 | AC17: 188326.75 | AD17: 35951.654 | AE17: 498 | AF17: 453 | AG17: 254 | AH17: 97780.11 | AI17: 235 | AJ17: 0 | AK17: 0.0853 | AL17: 0.2984 | AM17: 0.0266 | AN17: 0.0586 | AO17: 0.0139 | AP17: 0.0161 | AQ17: 0 | AR17: 0 | AS17: 73 | AT17: 8081.39 | AU17: 168262 | AV17: 442 | AW17: 21956 | AX17: 56 | AY17: 0.1154 | AZ17: - | BA17: - | BB17: - | BC17: -
A18: GXG | B18: =DATE(YEAR(F18),MONTH(F18),DAY(F18)) -> 46034 | C18: =TEXT(YEAR(B18),"0")&"年" -> 2026年 | D18: =TEXT(MONTH(B18),"0")&"月" -> 1月 | E18: ="W"&TEXT(WEEKNUM(B18,2),"0") -> W3 | F18: 2026/01/12 19:55:13 | G18: 2026/01/13 01:48:18 | H18: 353 | I18: 437663 | J18: 863860 | K18: 42338 | L18: 7194.5622 | M18: 55539 | N18: 208 | O18: 129 | P18: 0.76 | Q18: 2300 | R18: 1 | S18: 157 | T18: 46 | U18: 0.3353 | V18: 76 | W18: 39537 | X18: 11408 | Y18: 378002 | Z18: 28406 | AA18: 300 | AB18: 189243 | AC18: 187109.87 | AD18: 31795.871 | AE18: 301 | AF18: 257 | AG18: 164 | AH18: 107210.18 | AI18: 146 | AJ18: 0 | AK18: 0.0751 | AL18: 0.2885 | AM18: 0.0106 | AN18: 0.0225 | AO18: 0.0054 | AP18: 0.0061 | AQ18: 0 | AR18: 0 | AS18: 66 | AT18: 5936.88 | AU18: 161009 | AV18: 256 | AW18: 28234 | AX18: 44 | AY18: 0.1492 | AZ18: - | BA18: - | BB18: - | BC18: -
A19: GXG | B19: =DATE(YEAR(F19),MONTH(F19),DAY(F19)) -> 46037 | C19: =TEXT(YEAR(B19),"0")&"年" -> 2026年 | D19: =TEXT(MONTH(B19),"0")&"月" -> 1月 | E19: ="W"&TEXT(WEEKNUM(B19,2),"0") -> W3 | F19: 2026/01/15 08:15:29 | G19: 2026/01/15 13:17:38 | H19: 302 | I19: 467439 | J19: 834307 | K19: 40430 | L19: 8028.4627 | M19: 52623 | N19: 697 | O19: 193 | P19: 0.88 | Q19: 2394 | R19: 3 | S19: 228 | T19: 24 | U19: 0.3005 | V19: 76 | W19: 38588 | X19: 8443 | Y19: 259558 | Z19: 18956 | AA19: 284 | AB19: 185497 | AC19: 183572.15 | AD19: 36453.182 | AE19: 284 | AF19: 237 | AG19: 157 | AH19: 106821.05 | AI19: 129 | AJ19: 0 | AK19: 0.073 | AL19: 0.2188 | AM19: 0.015 | AN19: 0.0281 | AO19: 0.0054 | AP19: 0.0059 | AQ19: 0 | AR19: 0 | AS19: 86 | AT19: 6080.46 | AU19: 151368 | AV19: 236 | AW19: 34129 | AX19: 48 | AY19: 0.184 | AZ19: - | BA19: - | BB19: - | BC19: -
A20: GXG | B20: =DATE(YEAR(F20),MONTH(F20),DAY(F20)) -> 46023 | C20: =TEXT(YEAR(B20),"0")&"年" -> 2026年 | D20: =TEXT(MONTH(B20),"0")&"月" -> 1月 | E20: ="W"&TEXT(WEEKNUM(B20,2),"0") -> W1 | F20: 2026/01/01 10:01:43 | G20: 2026/01/01 13:30:03 | H20: 208 | I20: 726000 | J20: 1162958 | K20: 55207 | L20: 15899.616 | M20: 69024 | N20: 1152 | O20: 418 | P20: 0.74 | Q20: 2634 | R20: 1 | S20: 376 | T20: 21 | U20: 0.2361 | V20: 154 | W20: 52328 | X20: 13717 | Y20: 404630 | Z20: 32096 | AA20: 539 | AB20: 173989 | AC20: 171096.59 | AD20: 49275.818 | AE20: 539 | AF20: 470 | AG20: 228 | AH20: 88747.59 | AI20: 203 | AJ20: 0 | AK20: 0.0793 | AL20: 0.2621 | AM20: 0.0168 | AN20: 0.0343 | AO20: 0.0078 | AP20: 0.0085 | AQ20: 0 | AR20: 0 | AS20: 89 | AT20: 6619.82 | AU20: 152400 | AV20: 491 | AW20: 21589 | AX20: 48 | AY20: 0.1241 | AZ20: - | BA20: - | BB20: - | BC20: -
A21: GXG | B21: =DATE(YEAR(F21),MONTH(F21),DAY(F21)) -> 46042 | C21: =TEXT(YEAR(B21),"0")&"年" -> 2026年 | D21: =TEXT(MONTH(B21),"0")&"月" -> 1月 | E21: ="W"&TEXT(WEEKNUM(B21,2),"0") -> W4 | F21: 2026/01/20 07:54:13 | G21: 2026/01/20 13:30:19 | H21: 336 | I21: 487664 | J21: 816159 | K21: 37727 | L21: 6734.9598 | M21: 48427 | N21: 224 | O21: 108 | P21: 0.65 | Q21: 2418 | R21: 2 | S21: 320 | T21: 26 | U21: 0.2124 | V21: 76 | W21: 34822 | X21: 8757 | Y21: 215719 | Z21: 20180 | AA21: 458 | AB21: 175722 | AC21: 169573.12 | AD21: 30271.905 | AE21: 458 | AF21: 411 | AG21: 87 | AH21: 32687.68 | AI21: 79 | AJ21: 0 | AK21: 0.0935 | AL21: 0.2515 | AM21: 0.0227 | AN21: 0.0469 | AO21: 0.0095 | AP21: 0.0109 | AQ21: 0 | AR21: 0 | AS21: 65 | AT21: 5995.8 | AU21: 147597.55 | AV21: 387 | AW21: 28124.45 | AX21: 71 | AY21: 0.1601 | AZ21: 81703.28 | BA21: 0.4818174 | BB21: 5200.58 | BC21: 212
A22: GXG | B22: =DATE(YEAR(F22),MONTH(F22),DAY(F22)) -> 46038 | C22: =TEXT(YEAR(B22),"0")&"年" -> 2026年 | D22: =TEXT(MONTH(B22),"0")&"月" -> 1月 | E22: ="W"&TEXT(WEEKNUM(B22,2),"0") -> W3 | F22: 2026/01/16 08:00:11 | G22: 2026/01/16 12:02:31 | H22: 242 | I22: 535300 | J22: 853830 | K22: 38164 | L22: 9449.1334 | M22: 48386 | N22: 732 | O22: 228 | P22: 0.83 | Q22: 2257 | R22: 1 | S22: 285 | T22: 34 | U22: 0.2487 | V22: 79 | W22: 36555 | X22: 9686 | Y22: 250258 | Z22: 22170 | AA22: 256 | AB22: 182257 | AC22: 168206.85 | AD22: 41646.813 | AE22: 256 | AF22: 218 | AG22: 117 | AH22: 80643.79 | AI22: 102 | AJ22: 0 | AK22: 0.0886 | AL22: 0.265 | AM22: 0.0115 | AN22: 0.0225 | AO22: 0.0053 | AP22: 0.0057 | AQ22: 0 | AR22: 0 | AS22: 80 | AT22: 5538.11 | AU22: 139237.28 | AV22: 201 | AW22: 43019.72 | AX22: 55 | AY22: 0.236 | AZ22: 128337.88 | BA22: 0.76297654 | BB22: 12944.12 | BC22: 169
A23: GXG | B23: =DATE(YEAR(F23),MONTH(F23),DAY(F23)) -> 46024 | C23: =TEXT(YEAR(B23),"0")&"年" -> 2026年 | D23: =TEXT(MONTH(B23),"0")&"月" -> 1月 | E23: ="W"&TEXT(WEEKNUM(B23,2),"0") -> W1 | F23: 2026/01/02 19:59:48 | G23: 2026/01/03 01:25:12 | H23: 325 | I23: 407957 | J23: 712946 | K23: 35258 | L23: 6501.1678 | M23: 44997 | N23: 151 | O23: 90 | P23: 0.55 | Q23: 1616 | R23: 3 | S23: 286 | T23: 46 | U23: 0.2288 | V23: 154 | W23: 33007 | X23: 9840 | Y23: 266526 | Z23: 25101 | AA23: 438 | AB23: 166235 | AC23: 165252.19 | AD23: 30470.594 | AE23: 438 | AF23: 387 | AG23: 237 | AH23: 90126.39 | AI23: 218 | AJ23: 0 | AK23: 0.0942 | AL23: 0.2981 | AM23: 0.0174 | AN23: 0.0393 | AO23: 0.0097 | AP23: 0.011 | AQ23: 0 | AR23: 0 | AS23: 139 | AT23: 6484.51 | AU23: 141614 | AV23: 373 | AW23: 24621 | AX23: 65 | AY23: 0.1481 | AZ23: - | BA23: - | BB23: - | BC23: -
A24: GXG | B24: =DATE(YEAR(F24),MONTH(F24),DAY(F24)) -> 46039 | C24: =TEXT(YEAR(B24),"0")&"年" -> 2026年 | D24: =TEXT(MONTH(B24),"0")&"月" -> 1月 | E24: ="W"&TEXT(WEEKNUM(B24,2),"0") -> W3 | F24: 2026/01/17 19:59:56 | G24: 2026/01/18 01:33:08 | H24: 333 | I24: 373307 | J24: 691150 | K24: 35535 | L24: 6398.8595 | M24: 45588 | N24: 189 | O24: 102 | P24: 0.68 | Q24: 1744 | R24: 1 | S24: 318 | T24: 42 | U24: 0.2118 | V24: 79 | W24: 32185 | X24: 11721 | Y24: 305531 | Z24: 29940 | AA24: 350 | AB24: 180282 | AC24: 156287.42 | AD24: 28142.993 | AE24: 350 | AF24: 328 | AG24: 105 | AH24: 47567.18 | AI24: 99 | AJ24: 0 | AK24: 0.098 | AL24: 0.3642 | AM24: 0.0117 | AN24: 0.028 | AO24: 0.0077 | AP24: 0.0092 | AQ24: 0 | AR24: 0 | AS24: 162 | AT24: 5639.58 | AU24: 157506.18 | AV24: 307 | AW24: 22775.82 | AX24: 43 | AY24: 0.1263 | AZ24: 114231.43 | BA24: 0.73090611 | BB24: 7461.35 | BC24: 242
A25: GXG | B25: =DATE(YEAR(F25),MONTH(F25),DAY(F25)) -> 46030 | C25: =TEXT(YEAR(B25),"0")&"年" -> 2026年 | D25: =TEXT(MONTH(B25),"0")&"月" -> 1月 | E25: ="W"&TEXT(WEEKNUM(B25,2),"0") -> W2 | F25: 2026/01/08 07:59:55 | G25: 2026/01/08 11:15:27 | H25: 195 | I25: 578253 | J25: 880837 | K25: 38582 | L25: 11839.004 | M25: 48020 | N25: 718 | O25: 342 | P25: 0.91 | Q25: 2387 | R25: 2 | S25: 320 | T25: 24 | U25: 0.2491 | V25: 74 | W25: 37544 | X25: 8362 | Y25: 203030 | Z25: 18544 | AA25: 344 | AB25: 156138 | AC25: 155117.74 | AD25: 47598.352 | AE25: 344 | AF25: 309 | AG25: 187 | AH25: 84035.21 | AI25: 167 | AJ25: 0 | AK25: 0.0913 | AL25: 0.2227 | AM25: 0.0186 | AN25: 0.037 | AO25: 0.0072 | AP25: 0.008 | AQ25: 0 | AR25: 0 | AS25: 133 | AT25: 5887.41 | AU25: 138584 | AV25: 306 | AW25: 17554 | AX25: 38 | AY25: 0.1124 | AZ25: - | BA25: - | BB25: - | BC25: -
A26: GXG | B26: =DATE(YEAR(F26),MONTH(F26),DAY(F26)) -> 46038 | C26: =TEXT(YEAR(B26),"0")&"年" -> 2026年 | D26: =TEXT(MONTH(B26),"0")&"月" -> 1月 | E26: ="W"&TEXT(WEEKNUM(B26,2),"0") -> W3 | F26: 2026/01/16 20:05:49 | G26: 2026/01/17 01:46:54 | H26: 341 | I26: 335005 | J26: 653646 | K26: 35031 | L26: 6162.3064 | M26: 45070 | N26: 171 | O26: 95 | P26: 0.62 | Q26: 1573 | R26: 2 | S26: 296 | T26: 44 | U26: 0.2511 | V26: 79 | W26: 32098 | X26: 11371 | Y26: 316408 | Z26: 29980 | AA26: 350 | AB26: 177106 | AC26: 154067.56 | AD26: 27102.038 | AE26: 350 | AF26: 321 | AG26: 161 | AH26: 72173.85 | AI26: 145 | AJ26: 0 | AK26: 0.0948 | AL26: 0.3543 | AM26: 0.0117 | AN26: 0.0282 | AO26: 0.0078 | AP26: 0.0092 | AQ26: 0 | AR26: 0 | AS26: 177 | AT26: 5108.6 | AU26: 148313.26 | AV26: 296 | AW26: 28792.74 | AX26: 54 | AY26: 0.1626 | AZ26: 96072.77 | BA26: 0.62357559 | BB26: 5875.52 | BC26: 203
A27: GXG | B27: =DATE(YEAR(F27),MONTH(F27),DAY(F27)) -> 46041 | C27: =TEXT(YEAR(B27),"0")&"年" -> 2026年 | D27: =TEXT(MONTH(B27),"0")&"月" -> 1月 | E27: ="W"&TEXT(WEEKNUM(B27,2),"0") -> W4 | F27: 2026/01/19 20:01:08 | G27: 2026/01/20 01:05:14 | H27: 304 | I27: 343808 | J27: 622764 | K27: 33655 | L27: 6640.2499 | M27: 42618 | N27: 144 | O27: 99 | P27: 0.59 | Q27: 1575 | R27: 2 | S27: 228 | T27: 39 | U27: 0.2119 | V27: 78 | W27: 29721 | X27: 8674 | Y27: 265921 | Z27: 21207 | AA27: 417 | AB27: 157296 | AC27: 151816.06 | AD27: 29953.843 | AE27: 417 | AF27: 380 | AG27: 73 | AH27: 26724.46 | AI27: 67 | AJ27: 0 | AK27: 0.0797 | AL27: 0.2918 | AM27: 0.0197 | AN27: 0.0438 | AO27: 0.0098 | AP27: 0.0113 | AQ27: 0 | AR27: 0 | AS27: 137 | AT27: 5025.11 | AU27: 135992.12 | AV27: 362 | AW27: 21303.88 | AX27: 55 | AY27: 0.1354 | AZ27: 70797.66 | BA27: 0.46633841 | BB27: 4622.04 | BC27: 189
A28: GXG | B28: =DATE(YEAR(F28),MONTH(F28),DAY(F28)) -> 46029 | C28: =TEXT(YEAR(B28),"0")&"年" -> 2026年 | D28: =TEXT(MONTH(B28),"0")&"月" -> 1月 | E28: ="W"&TEXT(WEEKNUM(B28,2),"0") -> W2 | F28: 2026/01/07 14:00:40 | G28: 2026/01/07 19:24:45 | H28: 324 | I28: 363984 | J28: 671753 | K28: 27481 | L28: 5087.7655 | M28: 37325 | N28: 207 | O28: 99 | P28: 0.8 | Q28: 2071 | R28: 1 | S28: 187 | T28: 28 | U28: 0.3226 | V28: 74 | W28: 26008 | X28: 6749 | Y28: 182147 | Z28: 15882 | AA28: 328 | AB28: 148013 | AC28: 146450.9 | AD28: 27113.563 | AE28: 328 | AF28: 299 | AG28: 174 | AH28: 79349.04 | AI28: 160 | AJ28: 0 | AK28: 0.0872 | AL28: 0.2595 | AM28: 0.0207 | AN28: 0.0443 | AO28: 0.0088 | AP28: 0.0109 | AQ28: 0 | AR28: 0 | AS28: 79 | AT28: 5483.89 | AU28: 126293 | AV28: 282 | AW28: 21720 | AX28: 46 | AY28: 0.1467 | AZ28: - | BA28: - | BB28: - | BC28: -
A29: GXG | B29: =DATE(YEAR(F29),MONTH(F29),DAY(F29)) -> 46025 | C29: =TEXT(YEAR(B29),"0")&"年" -> 2026年 | D29: =TEXT(MONTH(B29),"0")&"月" -> 1月 | E29: ="W"&TEXT(WEEKNUM(B29,2),"0") -> W1 | F29: 2026/01/03 20:00:45 | G29: 2026/01/04 01:32:52 | H29: 332 | I29: 350129 | J29: 637174 | K29: 32646 | L29: 5897.807 | M29: 42124 | N29: 139 | O29: 88 | P29: 0.6 | Q29: 1486 | R29: 1 | S29: 227 | T29: 36 | U29: 0.2483 | V29: 154 | W29: 29628 | X29: 8440 | Y29: 256746 | Z29: 22621 | AA29: 386 | AB29: 147263 | AC29: 146152.97 | AD29: 26403.909 | AE29: 386 | AF29: 359 | AG29: 195 | AH29: 74499.42 | AI29: 188 | AJ29: 0 | AK29: 0.0881 | AL29: 0.2849 | AM29: 0.0171 | AN29: 0.0425 | AO29: 0.0092 | AP29: 0.011 | AQ29: 0 | AR29: 0 | AS29: 87 | AT29: 5582.35 | AU29: 131610 | AV29: 346 | AW29: 15653 | AX29: 40 | AY29: 0.1063 | AZ29: - | BA29: - | BB29: - | BC29: -
A30: GXG | B30: =DATE(YEAR(F30),MONTH(F30),DAY(F30)) -> 46032 | C30: =TEXT(YEAR(B30),"0")&"年" -> 2026年 | D30: =TEXT(MONTH(B30),"0")&"月" -> 1月 | E30: ="W"&TEXT(WEEKNUM(B30,2),"0") -> W2 | F30: 2026/01/10 19:48:06 | G30: 2026/01/11 01:05:13 | H30: 317 | I30: 348166 | J30: 691311 | K30: 37878 | L30: 7166.7 | M30: 50601 | N30: 596 | O30: 134 | P30: 0.76 | Q30: 2163 | R30: 1 | S30: 181 | T30: 27 | U30: 0.2898 | V30: 74 | W30: 35361 | X30: 9299 | Y30: 291493 | Z30: 25070 | AA30: 390 | AB30: 146812 | AC30: 145527.38 | AD30: 27534.481 | AE30: 391 | AF30: 345 | AG30: 189 | AH30: 71941.29 | AI30: 178 | AJ30: 0 | AK30: 0.086 | AL30: 0.263 | AM30: 0.0156 | AN30: 0.0371 | AO30: 0.0077 | AP30: 0.0091 | AQ30: 0 | AR30: 0 | AS30: 68 | AT30: 5252.32 | AU30: 129265.99 | AV30: 345 | AW30: 17546.01 | AX30: 45 | AY30: 0.1195 | AZ30: - | BA30: - | BB30: - | BC30: -
A31: GXG | B31: =DATE(YEAR(F31),MONTH(F31),DAY(F31)) -> 46035 | C31: =TEXT(YEAR(B31),"0")&"年" -> 2026年 | D31: =TEXT(MONTH(B31),"0")&"月" -> 1月 | E31: ="W"&TEXT(WEEKNUM(B31,2),"0") -> W3 | F31: 2026/01/13 07:39:32 | G31: 2026/01/13 12:30:42 | H31: 291 | I31: 372602 | J31: 622930 | K31: 29026 | L31: 5981.3165 | M31: 37344 | N31: 626 | O31: 118 | P31: 0.73 | Q31: 1962 | R31: 1 | S31: 184 | T31: 18 | U31: 0.2654 | V31: 76 | W31: 27873 | X31: 7174 | Y31: 185244 | Z31: 16476 | AA31: 352 | AB31: 138948.99 | AC31: 137525.79 | AD31: 28339.602 | AE31: 352 | AF31: 310 | AG31: 187 | AH31: 72072.59 | AI31: 168 | AJ31: 0 | AK31: 0.0889 | AL31: 0.2574 | AM31: 0.0214 | AN31: 0.0432 | AO31: 0.0094 | AP31: 0.0107 | AQ31: 0 | AR31: 0 | AS31: 66 | AT31: 4900.72 | AU31: 114173.09 | AV31: 292 | AW31: 24775.9 | AX31: 60 | AY31: 0.1783 | AZ31: - | BA31: - | BB31: - | BC31: -
A32: GXG | B32: =DATE(YEAR(F32),MONTH(F32),DAY(F32)) -> 46025 | C32: =TEXT(YEAR(B32),"0")&"年" -> 2026年 | D32: =TEXT(MONTH(B32),"0")&"月" -> 1月 | E32: ="W"&TEXT(WEEKNUM(B32,2),"0") -> W1 | F32: 2026/01/03 14:00:49 | G32: 2026/01/03 19:10:08 | H32: 309 | I32: 345103 | J32: 634805 | K32: 28707 | L32: 5568.4681 | M32: 38711 | N32: 173 | O32: 93 | P32: 0.71 | Q32: 1734 | R32: 0 | S32: 192 | T32: 33 | U32: 0.2699 | V32: 154 | W32: 26747 | X32: 6455 | Y32: 198323 | Z32: 16641 | AA32: 334 | AB32: 126583 | AC32: 125895.78 | AD32: 24420.756 | AE32: 334 | AF32: 291 | AG32: 186 | AH32: 69577.09 | AI32: 163 | AJ32: 0 | AK32: 0.0839 | AL32: 0.2413 | AM32: 0.0201 | AN32: 0.0451 | AO32: 0.0086 | AP32: 0.0101 | AQ32: 0 | AR32: 0 | AS32: 66 | AT32: 4262 | AU32: 106374 | AV32: 281 | AW32: 20209 | AX32: 53 | AY32: 0.1597 | AZ32: - | BA32: - | BB32: - | BC32: -
A33: GXG | B33: =DATE(YEAR(F33),MONTH(F33),DAY(F33)) -> 46040 | C33: =TEXT(YEAR(B33),"0")&"年" -> 2026年 | D33: =TEXT(MONTH(B33),"0")&"月" -> 1月 | E33: ="W"&TEXT(WEEKNUM(B33,2),"0") -> W3 | F33: 2026/01/18 20:48:04 | G33: 2026/01/19 01:37:11 | H33: 289 | I33: 257266 | J33: 478371 | K33: 28145 | L33: 5840.8947 | M33: 35576 | N33: 146 | O33: 84 | P33: 0.6 | Q33: 1172 | R33: 1 | S33: 187 | T33: 25 | U33: 0.2294 | V33: 78 | W33: 24944 | X33: 7491 | Y33: 220469 | Z33: 18838 | AA33: 282 | AB33: 125554 | AC33: 115500.74 | AD33: 23969.716 | AE33: 284 | AF33: 255 | AG33: 58 | AH33: 24287.41 | AI33: 55 | AJ33: 0 | AK33: 0.0854 | AL33: 0.3003 | AM33: 0.015 | AN33: 0.034 | AO33: 0.0079 | AP33: 0.0091 | AQ33: 0 | AR33: 0 | AS33: 91 | AT33: 3617.21 | AU33: 108602.86 | AV33: 243 | AW33: 16951.14 | AX33: 39 | AY33: 0.135 | AZ33: 63366.64 | BA33: 0.5486254 | BB33: 4124.44 | BC33: 145
A34: GXG | B34: =DATE(YEAR(F34),MONTH(F34),DAY(F34)) -> 46042 | C34: =TEXT(YEAR(B34),"0")&"年" -> 2026年 | D34: =TEXT(MONTH(B34),"0")&"月" -> 1月 | E34: ="W"&TEXT(WEEKNUM(B34,2),"0") -> W4 | F34: 2026/01/20 20:00:54 | G34: 2026/01/21 00:36:04 | H34: 275 | I34: 243391 | J34: 453980 | K34: 24135 | L34: 5262.6287 | M34: 30966 | N34: 137 | O34: 75 | P34: 0.61 | Q34: 1089 | R34: 1 | S34: 134 | T34: 0 | U34: 0.2486 | V34: 106 | W34: 21403 | X34: 5907 | Y34: 183140 | Z34: 14859 | AA34: 314 | AB34: 118550 | AC34: 114083.07 | AD34: 24875.775 | AE34: 314 | AF34: 280 | AG34: 55 | AH34: 20361.14 | AI34: 52 | AJ34: 0 | AK34: 0.0811 | AL34: 0.276 | AM34: 0.0211 | AN34: 0.0474 | AO34: 0.0101 | AP34: 0.0116 | AQ34: 0 | AR34: 0 | AS34: 67 | AT34: 3782.18 | AU34: 100950.99 | AV34: 269 | AW34: 17599.01 | AX34: 45 | AY34: 0.1485 | AZ34: 55894.88 | BA34: 0.48994895 | BB34: 3927.65 | BC34: 149
A35: GXG | B35: =DATE(YEAR(F35),MONTH(F35),DAY(F35)) -> 46031 | C35: =TEXT(YEAR(B35),"0")&"年" -> 2026年 | D35: =TEXT(MONTH(B35),"0")&"月" -> 1月 | E35: ="W"&TEXT(WEEKNUM(B35,2),"0") -> W2 | F35: 2026/01/09 14:01:23 | G35: 2026/01/09 19:13:37 | H35: 312 | I35: 261578 | J35: 462722 | K35: 19527 | L35: 3752.386 | M35: 25181 | N35: 108 | O35: 62 | P35: 0.61 | Q35: 1149 | R35: 1 | S35: 155 | T35: 14 | U35: 0.2468 | V35: 76 | W35: 17951 | X35: 5328 | Y35: 144860 | Z35: 12878 | AA35: 297 | AB35: 115157 | AC35: 114060.53 | AD35: 21918.325 | AE35: 297 | AF35: 271 | AG35: 169 | AH35: 63329.04 | AI35: 158 | AJ35: 0 | AK35: 0.0889 | AL35: 0.2968 | AM35: 0.0231 | AN35: 0.0509 | AO35: 0.0118 | AP35: 0.0139 | AQ35: 0 | AR35: 0 | AS35: 60 | AT35: 4487.4 | AU35: 100794 | AV35: 260 | AW35: 14363 | AX35: 37 | AY35: 0.1247 | AZ35: - | BA35: - | BB35: - | BC35: -
A36: GXG | B36: =DATE(YEAR(F36),MONTH(F36),DAY(F36)) -> 46041 | C36: =TEXT(YEAR(B36),"0")&"年" -> 2026年 | D36: =TEXT(MONTH(B36),"0")&"月" -> 1月 | E36: ="W"&TEXT(WEEKNUM(B36,2),"0") -> W4 | F36: 2026/01/19 14:08:21 | G36: 2026/01/19 19:08:39 | H36: 300 | I36: 312214 | J36: 552792 | K36: 27519 | L36: 5498.3017 | M36: 34856 | N36: 114 | O36: 75 | P36: 0.51 | Q36: 1131 | R36: 0 | S36: 183 | T36: 21 | U36: 0.2049 | V36: 78 | W36: 25127 | X36: 7289 | Y36: 163594 | Z36: 16394 | AA36: 307 | AB36: 116648 | AC36: 112484.34 | AD36: 22474.394 | AE36: 307 | AF36: 276 | AG36: 73 | AH36: 27726.82 | AI36: 68 | AJ36: 0 | AK36: 0.1002 | AL36: 0.2901 | AM36: 0.0187 | AN36: 0.0379 | AO36: 0.0088 | AP36: 0.01 | AQ36: 0 | AR36: 0 | AS36: 34 | AT36: 3737.92 | AU36: 97205.05 | AV36: 259 | AW36: 19442.95 | AX36: 48 | AY36: 0.1667 | AZ36: 48630.44 | BA36: 0.43233076 | BB36: 3587.58 | BC36: 123
A37: GXG | B37: =DATE(YEAR(F37),MONTH(F37),DAY(F37)) -> 46042 | C37: =TEXT(YEAR(B37),"0")&"年" -> 2026年 | D37: =TEXT(MONTH(B37),"0")&"月" -> 1月 | E37: ="W"&TEXT(WEEKNUM(B37,2),"0") -> W4 | F37: 2026/01/20 14:00:24 | G37: 2026/01/20 19:20:25 | H37: 320 | I37: 292476 | J37: 524472 | K37: 24044 | L37: 4508.0152 | M37: 30569 | N37: 107 | O37: 68 | P37: 0.55 | Q37: 1258 | R37: 1 | S37: 179 | T37: 15 | U37: 0.2101 | V37: 120 | W37: 21364 | X37: 5911 | Y37: 172493 | Z37: 14352 | AA37: 305 | AB37: 116492 | AC37: 112194.57 | AD37: 21035.386 | AE37: 305 | AF37: 279 | AG37: 61 | AH37: 22006.88 | AI37: 56 | AJ37: 0 | AK37: 0.0832 | AL37: 0.2767 | AM37: 0.0213 | AN37: 0.0472 | AO37: 0.01 | AP37: 0.0116 | AQ37: 0 | AR37: 0 | AS37: 80 | AT37: 4028.13 | AU37: 98655.78 | AV37: 257 | AW37: 17836.22 | AX37: 48 | AY37: 0.1531 | AZ37: 45011.58 | BA37: 0.40119214 | BB37: 3403.64 | BC37: 121
A38: GXG | B38: =DATE(YEAR(F38),MONTH(F38),DAY(F38)) -> 46033 | C38: =TEXT(YEAR(B38),"0")&"年" -> 2026年 | D38: =TEXT(MONTH(B38),"0")&"月" -> 1月 | E38: ="W"&TEXT(WEEKNUM(B38,2),"0") -> W2 | F38: 2026/01/11 14:00:13 | G38: 2026/01/11 19:14:23 | H38: 314 | I38: 309164 | J38: 592263 | K38: 27135 | L38: 5182.2812 | M38: 36833 | N38: 168 | O38: 100 | P38: 0.82 | Q38: 2293 | R38: 0 | S38: 143 | T38: 18 | U38: 0.2811 | V38: 75 | W38: 25643 | X38: 6198 | Y38: 168048 | Z38: 15047 | AA38: 292 | AB38: 112644 | AC38: 111245.45 | AD38: 21245.815 | AE38: 292 | AF38: 261 | AG38: 154 | AH38: 58352.6 | AI38: 136 | AJ38: 0 | AK38: 0.0895 | AL38: 0.2417 | AM38: 0.0194 | AN38: 0.0421 | AO38: 0.0079 | AP38: 0.0096 | AQ38: 0 | AR38: 0 | AS38: 57 | AT38: 4919.83 | AU38: 96491.1 | AV38: 249 | AW38: 16152.9 | AX38: 43 | AY38: 0.1434 | AZ38: - | BA38: - | BB38: - | BC38: -
A39: GXG | B39: =DATE(YEAR(F39),MONTH(F39),DAY(F39)) -> 46037 | C39: =TEXT(YEAR(B39),"0")&"年" -> 2026年 | D39: =TEXT(MONTH(B39),"0")&"月" -> 1月 | E39: ="W"&TEXT(WEEKNUM(B39,2),"0") -> W3 | F39: 2026/01/15 19:54:11 | G39: 2026/01/16 00:58:15 | H39: 304 | I39: 235356 | J39: 458368 | K39: 23389 | L39: 4615.2379 | M39: 30074 | N39: 101 | O39: 68 | P39: 0.61 | Q39: 1268 | R39: 0 | S39: 120 | T39: 31 | U39: 0.268 | V39: 77 | W39: 21524 | X39: 5820 | Y39: 157070 | Z39: 14747 | AA39: 278 | AB39: 108601.99 | AC39: 107689.6 | AD39: 21249.866 | AE39: 278 | AF39: 259 | AG39: 112 | AH39: 41269.3 | AI39: 109 | AJ39: 0 | AK39: 0.0939 | AL39: 0.2704 | AM39: 0.0189 | AN39: 0.0445 | AO39: 0.0092 | AP39: 0.0111 | AQ39: 0 | AR39: 0 | AS39: 49 | AT39: 3468.61 | AU39: 98487.99 | AV39: 252 | AW39: 10114 | AX39: 26 | AY39: 0.0931 | AZ39: - | BA39: - | BB39: - | BC39: -
A40: GXG | B40: =DATE(YEAR(F40),MONTH(F40),DAY(F40)) -> 46032 | C40: =TEXT(YEAR(B40),"0")&"年" -> 2026年 | D40: =TEXT(MONTH(B40),"0")&"月" -> 1月 | E40: ="W"&TEXT(WEEKNUM(B40,2),"0") -> W2 | F40: 2026/01/10 13:59:45 | G40: 2026/01/10 19:04:49 | H40: 305 | I40: 230266 | J40: 435408 | K40: 19293 | L40: 3794.5149 | M40: 25103 | N40: 112 | O40: 58 | P40: 0.58 | Q40: 1036 | R40: 2 | S40: 132 | T40: 32 | U40: 0.2564 | V40: 75 | W40: 18029 | X40: 4973 | Y40: 121032 | Z40: 12062 | AA40: 281 | AB40: 106666.64 | AC40: 105616.29 | AD40: 20772.435 | AE40: 281 | AF40: 255 | AG40: 152 | AH40: 57136.05 | AI40: 141 | AJ40: 0 | AK40: 0.0997 | AL40: 0.2758 | AM40: 0.0233 | AN40: 0.0513 | AO40: 0.0112 | AP40: 0.0132 | AQ40: 0 | AR40: 0 | AS40: 65 | AT40: 4222.47 | AU40: 94318.64 | AV40: 249 | AW40: 12348 | AX40: 32 | AY40: 0.1158 | AZ40: - | BA40: - | BB40: - | BC40: -
A41: GXG | B41: =DATE(YEAR(F41),MONTH(F41),DAY(F41)) -> 46036 | C41: =TEXT(YEAR(B41),"0")&"年" -> 2026年 | D41: =TEXT(MONTH(B41),"0")&"月" -> 1月 | E41: ="W"&TEXT(WEEKNUM(B41,2),"0") -> W3 | F41: 2026/01/14 14:04:28 | G41: 2026/01/14 19:12:37 | H41: 308 | I41: 352069 | J41: 632969 | K41: 29325 | L41: 5709.8816 | M41: 38564 | N41: 636 | O41: 107 | P41: 0.7 | Q41: 1895 | R41: 1 | S41: 183 | T41: 14 | U41: 0.2647 | V41: 76 | W41: 27245 | X41: 7136 | Y41: 177948 | Z41: 15989 | AA41: 260 | AB41: 105851 | AC41: 104844.78 | AD41: 20414.366 | AE41: 261 | AF41: 232 | AG41: 126 | AH41: 48447.74 | AI41: 107 | AJ41: 0 | AK41: 0.0899 | AL41: 0.2619 | AM41: 0.0163 | AN41: 0.0325 | AO41: 0.0067 | AP41: 0.0079 | AQ41: 0 | AR41: 0 | AS41: 60 | AT41: 3677 | AU41: 90799 | AV41: 223 | AW41: 15052 | AX41: 37 | AY41: 0.1422 | AZ41: - | BA41: - | BB41: - | BC41: -
A42: GXG | B42: =DATE(YEAR(F42),MONTH(F42),DAY(F42)) -> 46028 | C42: =TEXT(YEAR(B42),"0")&"年" -> 2026年 | D42: =TEXT(MONTH(B42),"0")&"月" -> 1月 | E42: ="W"&TEXT(WEEKNUM(B42,2),"0") -> W2 | F42: 2026/01/06 08:19:09 | G42: 2026/01/06 13:19:11 | H42: 300 | I42: 279809 | J42: 483141 | K42: 21593 | L42: 4318.1202 | M42: 28301 | N42: 151 | O42: 78 | P42: 0.71 | Q42: 1776 | R42: 0 | S42: 115 | T42: 16 | U42: 0.2964 | V42: 70 | W42: 20152 | X42: 4341 | Y42: 117097 | Z42: 10533 | AA42: 259 | AB42: 104061.39 | AC42: 103207.49 | AD42: 20639.205 | AE42: 259 | AF42: 243 | AG42: 129 | AH42: 50386.28 | AI42: 121 | AJ42: 0 | AK42: 0.09 | AL42: 0.2154 | AM42: 0.0246 | AN42: 0.056 | AO42: 0.0092 | AP42: 0.0113 | AQ42: 0 | AR42: 0 | AS42: 55 | AT42: 4296.23 | AU42: 93102.39 | AV42: 231 | AW42: 10959 | AX42: 28 | AY42: 0.1053 | AZ42: - | BA42: - | BB42: - | BC42: -
A43: GXG | B43: =DATE(YEAR(F43),MONTH(F43),DAY(F43)) -> 46030 | C43: =TEXT(YEAR(B43),"0")&"年" -> 2026年 | D43: =TEXT(MONTH(B43),"0")&"月" -> 1月 | E43: ="W"&TEXT(WEEKNUM(B43,2),"0") -> W2 | F43: 2026/01/08 14:07:38 | G43: 2026/01/08 19:27:54 | H43: 320 | I43: 206648 | J43: 418084 | K43: 19721 | L43: 3694.6087 | M43: 27211 | N43: 125 | O43: 73 | P43: 0.79 | Q43: 1884 | R43: 2 | S43: 113 | T43: 17 | U43: 0.3245 | V43: 77 | W43: 18015 | X43: 4635 | Y43: 148702 | Z43: 11308 | AA43: 269 | AB43: 103542 | AC43: 102607.08 | AD43: 19222.808 | AE43: 269 | AF43: 241 | AG43: 141 | AH43: 55126.98 | AI43: 128 | AJ43: 0 | AK43: 0.076 | AL43: 0.2573 | AM43: 0.0238 | AN43: 0.052 | AO43: 0.0099 | AP43: 0.0122 | AQ43: 0 | AR43: 0 | AS43: 57 | AT43: 4180.17 | AU43: 90623 | AV43: 236 | AW43: 12919 | AX43: 33 | AY43: 0.1248 | AZ43: - | BA43: - | BB43: - | BC43: -
A44: GXG | B44: =DATE(YEAR(F44),MONTH(F44),DAY(F44)) -> 46030 | C44: =TEXT(YEAR(B44),"0")&"年" -> 2026年 | D44: =TEXT(MONTH(B44),"0")&"月" -> 1月 | E44: ="W"&TEXT(WEEKNUM(B44,2),"0") -> W2 | F44: 2026/01/08 11:39:36 | G44: 2026/01/08 13:38:40 | H44: 119 | I44: 291554 | J44: 440692 | K44: 21261 | L44: 10713.83 | M44: 26245 | N44: 609 | O44: 279 | P44: 0.87 | Q44: 1579 | R44: 0 | S44: 124 | T44: 10 | U44: 0.2746 | V44: 75 | W44: 20378 | X44: 5127 | Y44: 124295 | Z44: 11439 | AA44: 251 | AB44: 101460 | AC44: 100627.03 | AD44: 50707.91 | AE44: 251 | AF44: 229 | AG44: 128 | AH44: 53946.85 | AI44: 120 | AJ44: 0 | AK44: 0.092 | AL44: 0.2516 | AM44: 0.0219 | AN44: 0.0447 | AO44: 0.0096 | AP44: 0.0108 | AQ44: 0 | AR44: 0 | AS44: 44 | AT44: 3438.69 | AU44: 89318 | AV44: 222 | AW44: 12142 | AX44: 29 | AY44: 0.1197 | AZ44: - | BA44: - | BB44: - | BC44: -
A45: GXG | B45: =DATE(YEAR(F45),MONTH(F45),DAY(F45)) -> 46039 | C45: =TEXT(YEAR(B45),"0")&"年" -> 2026年 | D45: =TEXT(MONTH(B45),"0")&"月" -> 1月 | E45: ="W"&TEXT(WEEKNUM(B45,2),"0") -> W3 | F45: 2026/01/17 14:00:24 | G45: 2026/01/17 19:00:23 | H45: 299 | I45: 264433 | J45: 482895 | K45: 24626 | L45: 4925.4736 | M45: 30951 | N45: 119 | O45: 66 | P45: 0.48 | Q45: 969 | R45: 0 | S45: 202 | T45: 18 | U45: 0.2098 | V45: 79 | W45: 22111 | X45: 6324 | Y45: 145413 | Z45: 14330 | AA45: 269 | AB45: 104614 | AC45: 99134.7 | AD45: 19828.042 | AE45: 269 | AF45: 244 | AG45: 106 | AH45: 38807.83 | AI45: 98 | AJ45: 0 | AK45: 0.0985 | AL45: 0.286 | AM45: 0.0188 | AN45: 0.0386 | AO45: 0.0087 | AP45: 0.0099 | AQ45: 0 | AR45: 0 | AS45: 54 | AT45: 4098.4 | AU45: 88207 | AV45: 227 | AW45: 16407 | AX45: 42 | AY45: 0.1568 | AZ45: 70435.13 | BA45: 0.71049925 | BB45: 4623.15 | BC45: 183
A46: GXG | B46: =DATE(YEAR(F46),MONTH(F46),DAY(F46)) -> 46037 | C46: =TEXT(YEAR(B46),"0")&"年" -> 2026年 | D46: =TEXT(MONTH(B46),"0")&"月" -> 1月 | E46: ="W"&TEXT(WEEKNUM(B46,2),"0") -> W3 | F46: 2026/01/15 14:00:35 | G46: 2026/01/15 19:04:46 | H46: 304 | I46: 286025 | J46: 524713 | K46: 23201 | L46: 4576.3849 | M46: 30666 | N46: 137 | O46: 81 | P46: 0.72 | Q46: 1584 | R46: 0 | S46: 134 | T46: 17 | U46: 0.279 | V46: 76 | W46: 21406 | X46: 5759 | Y46: 168627 | Z46: 13235 | AA46: 235 | AB46: 95277 | AC46: 94690.85 | AD46: 18677.72 | AE46: 235 | AF46: 219 | AG46: 113 | AH46: 44242.05 | AI46: 105 | AJ46: 0 | AK46: 0.0785 | AL46: 0.269 | AM46: 0.0178 | AN46: 0.038 | AO46: 0.0077 | AP46: 0.0094 | AQ46: 0 | AR46: 0 | AS46: 42 | AT46: 3457 | AU46: 83489 | AV46: 207 | AW46: 11788 | AX46: 28 | AY46: 0.1237 | AZ46: - | BA46: - | BB46: - | BC46: -
A47: GXG | B47: =DATE(YEAR(F47),MONTH(F47),DAY(F47)) -> 46033 | C47: =TEXT(YEAR(B47),"0")&"年" -> 2026年 | D47: =TEXT(MONTH(B47),"0")&"月" -> 1月 | E47: ="W"&TEXT(WEEKNUM(B47,2),"0") -> W2 | F47: 2026/01/11 19:55:14 | G47: 2026/01/12 00:05:23 | H47: 250 | I47: 235018 | J47: 477900 | K47: 28442 | L47: 6821.9868 | M47: 38039 | N47: 234 | O47: 125 | P47: 0.78 | Q47: 1721 | R47: 0 | S47: 109 | T47: 35 | U47: 0.3224 | V47: 75 | W47: 26664 | X47: 6244 | Y47: 218683 | Z47: 16494 | AA47: 228 | AB47: 87659 | AC47: 86043.36 | AD47: 20638.024 | AE47: 228 | AF47: 205 | AG47: 107 | AH47: 40264.17 | AI47: 99 | AJ47: 0 | AK47: 0.0754 | AL47: 0.2342 | AM47: 0.0138 | AN47: 0.0328 | AO47: 0.006 | AP47: 0.0072 | AQ47: 0 | AR47: 0 | AS47: 44 | AT47: 3672.28 | AU47: 78422 | AV47: 205 | AW47: 9237 | AX47: 23 | AY47: 0.1054 | AZ47: - | BA47: - | BB47: - | BC47: -
A48: GXG | B48: =DATE(YEAR(F48),MONTH(F48),DAY(F48)) -> 46027 | C48: =TEXT(YEAR(B48),"0")&"年" -> 2026年 | D48: =TEXT(MONTH(B48),"0")&"月" -> 1月 | E48: ="W"&TEXT(WEEKNUM(B48,2),"0") -> W2 | F48: 2026/01/05 19:52:26 | G48: 2026/01/05 23:36:35 | H48: 224 | I48: 312184 | J48: 542605 | K48: 27259 | L48: 7296.6317 | M48: 35539 | N48: 683 | O48: 132 | P48: 0.66 | Q48: 1542 | R48: 0 | S48: 113 | T48: 27 | U48: 0.3013 | V48: 155 | W48: 25644 | X48: 6372 | Y48: 180372 | Z48: 16059 | AA48: 231 | AB48: 84955 | AC48: 84413.69 | AD48: 22595.679 | AE48: 231 | AF48: 206 | AG48: 133 | AH48: 48513.99 | AI48: 120 | AJ48: 0 | AK48: 0.089 | AL48: 0.2485 | AM48: 0.0144 | AN48: 0.0323 | AO48: 0.0065 | AP48: 0.0076 | AQ48: 0 | AR48: 0 | AS48: 38 | AT48: 3070.63 | AU48: 70804 | AV48: 194 | AW48: 14151 | AX48: 37 | AY48: 0.1666 | AZ48: - | BA48: - | BB48: - | BC48: -
A49: GXG | B49: =DATE(YEAR(F49),MONTH(F49),DAY(F49)) -> 46023 | C49: =TEXT(YEAR(B49),"0")&"年" -> 2026年 | D49: =TEXT(MONTH(B49),"0")&"月" -> 1月 | E49: ="W"&TEXT(WEEKNUM(B49,2),"0") -> W1 | F49: 2026/01/01 14:01:17 | G49: 2026/01/01 19:01:24 | H49: 300 | I49: 266282 | J49: 520529 | K49: 26015 | L49: 5200.9774 | M49: 35580 | N49: 637 | O49: 98 | P49: 0.7 | Q49: 1393 | R49: 1 | S49: 145 | T49: 27 | U49: 0.3264 | V49: 154 | W49: 23466 | X49: 5643 | Y49: 183562 | Z49: 13549 | AA49: 153 | AB49: 84839 | AC49: 83992.99 | AD49: 16792.068 | AE49: 154 | AF49: 134 | AG49: 97 | AH49: 55323.99 | AI49: 85 | AJ49: 0 | AK49: 0.0738 | AL49: 0.2405 | AM49: 0.0113 | AN49: 0.0237 | AO49: 0.0043 | AP49: 0.0052 | AQ49: 0 | AR49: 0 | AS49: 46 | AT49: 2913.14 | AU49: 69196 | AV49: 127 | AW49: 15643 | AX49: 26 | AY49: 0.1844 | AZ49: - | BA49: - | BB49: - | BC49: -
A50: GXG | B50: =DATE(YEAR(F50),MONTH(F50),DAY(F50)) -> 46023 | C50: =TEXT(YEAR(B50),"0")&"年" -> 2026年 | D50: =TEXT(MONTH(B50),"0")&"月" -> 1月 | E50: ="W"&TEXT(WEEKNUM(B50,2),"0") -> W1 | F50: 2026/01/01 08:03:31 | G50: 2026/01/01 09:36:41 | H50: 93 | I50: 420660 | J50: 598387 | K50: 31085 | L50: 20018.962 | M50: 37162 | N50: 913 | O50: 552 | P50: 0.76 | Q50: 1349 | R50: 0 | S50: 209 | T50: 18 | U50: 0.2268 | V50: 154 | W50: 28823 | X50: 7615 | Y50: 227200 | Z50: 17366 | AA50: 141 | AB50: 84526 | AC50: 83914.8 | AD50: 54041.732 | AE50: 141 | AF50: 129 | AG50: 91 | AH50: 54717.8 | AI50: 85 | AJ50: 0 | AK50: 0.0764 | AL50: 0.2642 | AM50: 0.0081 | AN50: 0.0169 | AO50: 0.0038 | AP50: 0.0041 | AQ50: 0 | AR50: 0 | AS50: 41 | AT50: 2853.69 | AU50: 70132 | AV50: 118 | AW50: 14394 | AX50: 23 | AY50: 0.1703 | AZ50: - | BA50: - | BB50: - | BC50: -
A51: GXG | B51: =DATE(YEAR(F51),MONTH(F51),DAY(F51)) -> 46034 | C51: =TEXT(YEAR(B51),"0")&"年" -> 2026年 | D51: =TEXT(MONTH(B51),"0")&"月" -> 1月 | E51: ="W"&TEXT(WEEKNUM(B51,2),"0") -> W3 | F51: 2026/01/12 13:59:52 | G51: 2026/01/12 19:04:53 | H51: 305 | I51: 161769 | J51: 319896 | K51: 14080 | L51: 2769.6847 | M51: 18610 | N51: 97 | O51: 53 | P51: 0.74 | Q51: 1086 | R51: 1 | S51: 108 | T51: 12 | U51: 0.2964 | V51: 76 | W51: 12973 | X51: 3496 | Y51: 108410 | Z51: 9020 | AA51: 205 | AB51: 79339 | AC51: 78299.83 | AD51: 15402.404 | AE51: 205 | AF51: 188 | AG51: 102 | AH51: 38530.39 | AI51: 98 | AJ51: 0 | AK51: 0.0832 | AL51: 0.2695 | AM51: 0.0227 | AN51: 0.0538 | AO51: 0.011 | AP51: 0.0134 | AQ51: 0 | AR51: 0 | AS51: 46 | AT51: 3462.52 | AU51: 71890 | AV51: 186 | AW51: 7449 | AX51: 19 | AY51: 0.0939 | AZ51: - | BA51: - | BB51: - | BC51: -
A52: GXG | B52: =DATE(YEAR(F52),MONTH(F52),DAY(F52)) -> 46040 | C52: =TEXT(YEAR(B52),"0")&"年" -> 2026年 | D52: =TEXT(MONTH(B52),"0")&"月" -> 1月 | E52: ="W"&TEXT(WEEKNUM(B52,2),"0") -> W3 | F52: 2026/01/18 14:00:14 | G52: 2026/01/18 19:00:44 | H52: 300 | I52: 203425 | J52: 388963 | K52: 20395 | L52: 4072.213 | M52: 25984 | N52: 87 | O52: 58 | P52: 0.53 | Q52: 830 | R52: 0 | S52: 116 | T52: 27 | U52: 0.2355 | V52: 78 | W52: 18171 | X52: 4963 | Y52: 127777 | Z52: 11603 | AA52: 197 | AB52: 74827 | AC52: 70941.7 | AD52: 14164.732 | AE52: 197 | AF52: 174 | AG52: 51 | AH52: 18949.74 | AI52: 48 | AJ52: 0 | AK52: 0.0908 | AL52: 0.2731 | AM52: 0.017 | AN52: 0.0351 | AO52: 0.0076 | AP52: 0.0085 | AQ52: 0 | AR52: 0 | AS52: 36 | AT52: 2875.53 | AU52: 59371.04 | AV52: 158 | AW52: 15455.96 | AX52: 39 | AY52: 0.2066 | AZ52: 45228.42 | BA52: 0.6375435 | BB52: 3042.88 | BC52: 117
A53: GXG | B53: =DATE(YEAR(F53),MONTH(F53),DAY(F53)) -> 46027 | C53: =TEXT(YEAR(B53),"0")&"年" -> 2026年 | D53: =TEXT(MONTH(B53),"0")&"月" -> 1月 | E53: ="W"&TEXT(WEEKNUM(B53,2),"0") -> W2 | F53: 2026/01/05 14:03:03 | G53: 2026/01/05 18:40:06 | H53: 277 | I53: 186601 | J53: 340362 | K53: 14680 | L53: 3179.2095 | M53: 19019 | N53: 86 | O53: 51 | P53: 0.62 | Q53: 873 | R53: 1 | S53: 96 | T53: 19 | U53: 0.2896 | V53: 155 | W53: 13600 | X53: 3416 | Y53: 98281 | Z53: 8225 | AA53: 185 | AB53: 71084 | AC53: 70579.29 | AD53: 15285.174 | AE53: 185 | AF53: 172 | AG53: 89 | AH53: 33257.29 | AI53: 83 | AJ53: 0 | AK53: 0.0837 | AL53: 0.2512 | AM53: 0.0225 | AN53: 0.0504 | AO53: 0.0097 | AP53: 0.0117 | AQ53: 0 | AR53: 0 | AS53: 55 | AT53: 2531.86 | AU53: 64128 | AV53: 167 | AW53: 6956 | AX53: 18 | AY53: 0.0979 | AZ53: - | BA53: - | BB53: - | BC53: -
A54: GXG | B54: =DATE(YEAR(F54),MONTH(F54),DAY(F54)) -> 46036 | C54: =TEXT(YEAR(B54),"0")&"年" -> 2026年 | D54: =TEXT(MONTH(B54),"0")&"月" -> 1月 | E54: ="W"&TEXT(WEEKNUM(B54,2),"0") -> W3 | F54: 2026/01/14 21:13:14 | G54: 2026/01/15 00:30:16 | H54: 197 | I54: 145158 | J54: 274548 | K54: 15846 | L54: 4825.3764 | M54: 19839 | N54: 101 | O54: 69 | P54: 0.55 | Q54: 876 | R54: 2 | S54: 79 | T54: 20 | U54: 0.298 | V54: 76 | W54: 14331 | X54: 3627 | Y54: 106918 | Z54: 8939 | AA54: 164 | AB54: 61823 | AC54: 61476.52 | AD54: 18720.646 | AE54: 164 | AF54: 145 | AG54: 74 | AH54: 26936.76 | AI54: 66 | AJ54: 0 | AK54: 0.0836 | AL54: 0.2531 | AM54: 0.0183 | AN54: 0.04 | AO54: 0.0083 | AP54: 0.0092 | AQ54: 0 | AR54: 0 | AS54: 36 | AT54: 1746.93 | AU54: 53076 | AV54: 141 | AW54: 8747 | AX54: 23 | AY54: 0.1415 | AZ54: - | BA54: - | BB54: - | BC54: -
A55: GXG | B55: =DATE(YEAR(F55),MONTH(F55),DAY(F55)) -> 46028 | C55: =TEXT(YEAR(B55),"0")&"年" -> 2026年 | D55: =TEXT(MONTH(B55),"0")&"月" -> 1月 | E55: ="W"&TEXT(WEEKNUM(B55,2),"0") -> W2 | F55: 2026/01/06 14:14:39 | G55: 2026/01/06 19:00:29 | H55: 285 | I55: 119698 | J55: 248474 | K55: 11266 | L55: 2364.8746 | M55: 15079 | N55: 78 | O55: 43 | P55: 0.66 | Q55: 1020 | R55: 0 | S55: 70 | T55: 19 | U55: 0.3542 | V55: 72 | W55: 10087 | X55: 2539 | Y55: 84724 | Z55: 6096 | AA55: 161 | AB55: 60942.88 | AC55: 60536.48 | AD55: 12707.366 | AE55: 162 | AF55: 140 | AG55: 82 | AH55: 30818.34 | AI55: 74 | AJ55: 0 | AK55: 0.072 | AL55: 0.2517 | AM55: 0.0264 | AN55: 0.0551 | AO55: 0.0107 | AP55: 0.0124 | AQ55: 0 | AR55: 0 | AS55: 32 | AT55: 1833.18 | AU55: 52272.88 | AV55: 138 | AW55: 8670 | AX55: 23 | AY55: 0.1423 | AZ55: - | BA55: - | BB55: - | BC55: -
A56: GXG | B56: =DATE(YEAR(F56),MONTH(F56),DAY(F56)) -> 46027 | C56: =TEXT(YEAR(B56),"0")&"年" -> 2026年 | D56: =TEXT(MONTH(B56),"0")&"月" -> 1月 | E56: ="W"&TEXT(WEEKNUM(B56,2),"0") -> W2 | F56: 2026/01/05 10:37:17 | G56: 2026/01/05 13:20:36 | H56: 163 | I56: 152466 | J56: 261074 | K56: 13496 | L56: 4958.2202 | M56: 17246 | N56: 154 | O56: 82 | P56: 0.67 | Q56: 720 | R56: 0 | S56: 75 | T56: 5 | U56: 0.3439 | V56: 154 | W56: 12555 | X56: 2934 | Y56: 93194 | Z56: 7130 | AA56: 113 | AB56: 55513.94 | AC56: 54923.63 | AD56: 20178.086 | AE56: 113 | AF56: 102 | AG56: 61 | AH56: 30697.64 | AI56: 56 | AJ56: 0 | AK56: 0.0765 | AL56: 0.2337 | AM56: 0.0158 | AN56: 0.0348 | AO56: 0.0066 | AP56: 0.0076 | AQ56: 0 | AR56: 0 | AS56: 34 | AT56: 1985.64 | AU56: 47136.04 | AV56: 97 | AW56: 8377.9 | AX56: 16 | AY56: 0.1509 | AZ56: - | BA56: - | BB56: - | BC56: -
A57: GXG | B57: =DATE(YEAR(F57),MONTH(F57),DAY(F57)) -> 46038 | C57: =TEXT(YEAR(B57),"0")&"年" -> 2026年 | D57: =TEXT(MONTH(B57),"0")&"月" -> 1月 | E57: ="W"&TEXT(WEEKNUM(B57,2),"0") -> W3 | F57: 2026/01/16 14:39:04 | G57: 2026/01/16 18:07:35 | H57: 208 | I57: 160597 | J57: 297737 | K57: 15266 | L57: 4392.7424 | M57: 19811 | N57: 101 | O57: 70 | P57: 0.64 | Q57: 990 | R57: 0 | S57: 111 | T57: 19 | U57: 0.2855 | V57: 79 | W57: 14051 | X57: 3780 | Y57: 98549 | Z57: 9025 | AA57: 141 | AB57: 58700 | AC57: 52909.31 | AD57: 15224.484 | AE57: 141 | AF57: 132 | AG57: 55 | AH57: 19796.48 | AI57: 52 | AJ57: 0 | AK57: 0.0916 | AL57: 0.269 | AM57: 0.0156 | AN57: 0.0349 | AO57: 0.0071 | AP57: 0.0086 | AQ57: 0 | AR57: 0 | AS57: 40 | AT57: 2138.55 | AU57: 51988.08 | AV57: 124 | AW57: 6711.92 | AX57: 17 | AY57: 0.1143 | AZ57: 36406.91 | BA57: 0.68810026 | BB57: 2501.89 | BC57: 94
A58: GXG | B58: =DATE(YEAR(F58),MONTH(F58),DAY(F58)) -> 46027 | C58: =TEXT(YEAR(B58),"0")&"年" -> 2026年 | D58: =TEXT(MONTH(B58),"0")&"月" -> 1月 | E58: ="W"&TEXT(WEEKNUM(B58,2),"0") -> W2 | F58: 2026/01/05 07:54:54 | G58: 2026/01/05 10:15:59 | H58: 141 | I58: 215158 | J58: 315434 | K58: 14454 | L58: 6147.0053 | M58: 17817 | N58: 629 | O58: 119 | P58: 0.69 | Q58: 739 | R58: 1 | S58: 85 | T58: 11 | U58: 0.2661 | V58: 154 | W58: 13419 | X58: 2574 | Y58: 93299 | Z58: 6464 | AA58: 122 | AB58: 46813.3 | AC58: 46630.7 | AD58: 19831.131 | AE58: 122 | AF58: 112 | AG58: 73 | AH58: 28454.1 | AI58: 68 | AJ58: 0 | AK58: 0.0693 | AL58: 0.1918 | AM58: 0.0189 | AN58: 0.0435 | AO58: 0.0068 | AP58: 0.0077 | AQ58: 0 | AR58: 0 | AS58: 27 | AT58: 1732.61 | AU58: 41639.3 | AV58: 109 | AW58: 5174 | AX58: 13 | AY58: 0.1105 | AZ58: - | BA58: - | BB58: - | BC58: -
A59: GXG | B59: =DATE(YEAR(F59),MONTH(F59),DAY(F59)) -> 46024 | C59: =TEXT(YEAR(B59),"0")&"年" -> 2026年 | D59: =TEXT(MONTH(B59),"0")&"月" -> 1月 | E59: ="W"&TEXT(WEEKNUM(B59,2),"0") -> W1 | F59: 2026/01/02 13:59:01 | G59: 2026/01/02 19:01:22 | H59: 302 | I59: 125870 | J59: 269471 | K59: 13713 | L59: 2721.2833 | M59: 18412 | N59: 76 | O59: 44 | P59: 0.64 | Q59: 1394 | R59: 1 | S59: 60 | T59: 28 | U59: 0.3449 | V59: 154 | W59: 12702 | X59: 2836 | Y59: 94981 | Z59: 6859 | AA59: 107 | AB59: 40053 | AC59: 39798 | AD59: 7897.7344 | AE59: 107 | AF59: 99 | AG59: 58 | AH59: 21087 | AI59: 53 | AJ59: 0 | AK59: 0.0722 | AL59: 0.2233 | AM59: 0.0156 | AN59: 0.0349 | AO59: 0.0058 | AP59: 0.0072 | AQ59: 0 | AR59: 0 | AS59: 32 | AT59: 1366.33 | AU59: 33939 | AV59: 91 | AW59: 6114 | AX59: 16 | AY59: 0.1526 | AZ59: - | BA59: - | BB59: - | BC59: -
A60: GXG | B60: =DATE(YEAR(F60),MONTH(F60),DAY(F60)) -> 46023 | C60: =TEXT(YEAR(B60),"0")&"年" -> 2026年 | D60: =TEXT(MONTH(B60),"0")&"月" -> 1月 | E60: ="W"&TEXT(WEEKNUM(B60,2),"0") -> W1 | F60: 2026/01/01 20:15:33 | G60: 2026/01/01 23:45:49 | H60: 210 | I60: 140261 | J60: 278351 | K60: 14590 | L60: 4163.2847 | M60: 19020 | N60: 95 | O60: 57 | P60: 0.5 | Q60: 805 | R60: 1 | S60: 68 | T60: 21 | U60: 0.3491 | V60: 154 | W60: 13478 | X60: 3298 | Y60: 106776 | Z60: 8547 | AA60: 96 | AB60: 37284 | AC60: 37036.1 | AD60: 10568.323 | AE60: 96 | AF60: 86 | AG60: 45 | AH60: 17908.1 | AI60: 40 | AJ60: 0 | AK60: 0.08 | AL60: 0.2447 | AM60: 0.0112 | AN60: 0.0261 | AO60: 0.005 | AP60: 0.0059 | AQ60: 0 | AR60: 0 | AS60: 26 | AT60: 1327.99 | AU60: 31551 | AV60: 81 | AW60: 5733 | AX60: 15 | AY60: 0.1538 | AZ60: - | BA60: - | BB60: - | BC60: -
A61: GXG | B61: =DATE(YEAR(F61),MONTH(F61),DAY(F61)) -> 46036 | C61: =TEXT(YEAR(B61),"0")&"年" -> 2026年 | D61: =TEXT(MONTH(B61),"0")&"月" -> 1月 | E61: ="W"&TEXT(WEEKNUM(B61,2),"0") -> W3 | F61: 2026/01/14 20:00:33 | G61: 2026/01/14 20:55:35 | H61: 55 | I61: 73761 | J61: 109821 | K61: 4931 | L61: 5376.0145 | M61: 5773 | N61: 87 | O61: 64 | P61: 0.49 | Q61: 271 | R61: 0 | S61: 16 | T61: 7 | U61: 0.3176 | V61: 76 | W61: 4562 | X61: 1357 | Y61: 34118 | Z61: 2861 | AA61: 33 | AB61: 13605 | AC61: 13499 | AD61: 14717.262 | AE61: 33 | AF61: 31 | AG61: 14 | AH61: 5877 | AI61: 14 | AJ61: 0 | AK61: 0.0839 | AL61: 0.2975 | AM61: 0.0115 | AN61: 0.0228 | AO61: 0.0057 | AP61: 0.0063 | AQ61: 0 | AR61: 0 | AS61: 12 | AT61: 668.32 | AU61: 12647 | AV61: 31 | AW61: 958 | AX61: 2 | AY61: 0.0704 | AZ61: - | BA61: - | BB61: - | BC61: -
A62: GXG | B62: =DATE(YEAR(F62),MONTH(F62),DAY(F62)) -> 46040 | C62: =TEXT(YEAR(B62),"0")&"年" -> 2026年 | D62: =TEXT(MONTH(B62),"0")&"月" -> 1月 | E62: ="W"&TEXT(WEEKNUM(B62,2),"0") -> W3 | F62: 2026/01/18 20:00:24 | G62: 2026/01/18 20:35:27 | H62: 35 | I62: 45535 | J62: 65831 | K62: 3554 | L62: 6083.8802 | M62: 4073 | N62: 100 | O62: 67 | P62: 0.45 | Q62: 140 | R62: 0 | S62: 27 | T62: 8 | U62: 0.2828 | V62: 78 | W62: 3160 | X62: 946 | Y62: 27136 | Z62: 2487 | AA62: 14 | AB62: 6963 | AC62: 6069.96 | AD62: 10390.802 | AE62: 14 | AF62: 14 | AG62: 2 | AH62: 615.23 | AI62: 2 | AJ62: 0 | AK62: 0.0916 | AL62: 0.2994 | AM62: 0.0056 | AN62: 0.0148 | AO62: 0.0034 | AP62: 0.0039 | AQ62: 0 | AR62: 0 | AS62: 17 | AT62: 311.98 | AU62: 6910 | AV62: 14 | AW62: 53 | AX62: 0 | AY62: 0.0076 | AZ62: 3760.96 | BA62: 0.61960211 | BB62: 247.04 | BC62: 8
A63: GXG | B63: =DATE(YEAR(F63),MONTH(F63),DAY(F63)) -> 46045 | C63: =TEXT(YEAR(B63),"0")&"年" -> 2026年 | D63: =TEXT(MONTH(B63),"0")&"月" -> 1月 | E63: ="W"&TEXT(WEEKNUM(B63,2),"0") -> W4 | F63: 2026/01/23 08:01:49 | G63: 2026/01/23 13:27:38 | H63: 325 | I63: 732491 | J63: 1304223 | K63: 72316 | L63: 13317.182 | M63: 93900 | N63: 973 | O63: 389 | P63: 0.89 | Q63: 4827 | R63: 2 | S63: 654 | T63: 27 | U63: 0.2223 | V63: 105 | W63: 68670 | X63: 20951 | Y63: 528650 | Z63: 49763 | AA63: 674 | AB63: 356000.99 | AC63: 320592.88 | AD63: 59038.026 | AE63: 674 | AF63: 548 | AG63: 156 | AH63: 71632.88 | AI63: 132 | AJ63: 0 | AK63: 0.0941 | AL63: 0.3051 | AM63: 0.0135 | AN63: 0.0262 | AO63: 0.0072 | AP63: 0.0076 | AQ63: 0 | AR63: 0 | AS63: 292 | AT63: 12654.76 | AU63: 310577.82 | AV63: 593 | AW63: 45423.17 | AX63: 81 | AY63: 0.1276 | AZ63: 250121.89 | BA63: 0.78018542 | BB63: 32522.1 | BC63: 461
A64: GXG | B64: =DATE(YEAR(F64),MONTH(F64),DAY(F64)) -> 46047 | C64: =TEXT(YEAR(B64),"0")&"年" -> 2026年 | D64: =TEXT(MONTH(B64),"0")&"月" -> 1月 | E64: ="W"&TEXT(WEEKNUM(B64,2),"0") -> W4 | F64: 2026/01/25 08:00:24 | G64: 2026/01/25 13:01:42 | H64: 301 | I64: 622000 | J64: 1063883 | K64: 55686 | L64: 11089.147 | M64: 70849 | N64: 802 | O64: 302 | P64: 0.84 | Q64: 3892 | R64: 2 | S64: 410 | T64: 36 | U64: 0.2243 | V64: 107 | W64: 52781 | X64: 14185 | Y64: 391421 | Z64: 35661 | AA64: 809 | AB64: 257868 | AC64: 246657.65 | AD64: 49118.682 | AE64: 809 | AF64: 601 | AG64: 140 | AH64: 44830.97 | AI64: 111 | AJ64: 0 | AK64: 0.0911 | AL64: 0.2688 | AM64: 0.0227 | AN64: 0.0424 | AO64: 0.0114 | AP64: 0.0108 | AQ64: 0 | AR64: 0 | AS64: 107 | AT64: 8792.03 | AU64: 222553.41 | AV64: 701 | AW64: 35314.59 | AX64: 108 | AY64: 0.1369 | AZ64: 123826.13 | BA64: 0.50201618 | BB64: 9913.25 | BC64: 320
A65: GXG | B65: =DATE(YEAR(F65),MONTH(F65),DAY(F65)) -> 46043 | C65: =TEXT(YEAR(B65),"0")&"年" -> 2026年 | D65: =TEXT(MONTH(B65),"0")&"月" -> 1月 | E65: ="W"&TEXT(WEEKNUM(B65,2),"0") -> W4 | F65: 2026/01/21 08:05:16 | G65: 2026/01/21 13:26:22 | H65: 321 | I65: 882325 | J65: 1526032 | K65: 83715 | L65: 15642.79 | M65: 110658 | N65: 1129 | O65: 521 | P65: 0.95 | Q65: 6919 | R65: 2 | S65: 940 | T65: 55 | U65: 0.2126 | V65: 104 | W65: 79342 | X65: 15482 | Y65: 455045 | Z65: 36075 | AA65: 667 | AB65: 253538 | AC65: 241898.65 | AD65: 45200.62 | AE65: 672 | AF65: 565 | AG65: 270 | AH65: 100239.78 | AI65: 234 | AJ65: 0 | AK65: 0.0793 | AL65: 0.1951 | AM65: 0.0185 | AN65: 0.0365 | AO65: 0.006 | AP65: 0.0067 | AQ65: 0 | AR65: 0 | AS65: 779 | AT65: 8256.74 | AU65: 200438.97 | AV65: 538 | AW65: 53099.03 | AX65: 129 | AY65: 0.2094 | AZ65: 144673.03 | BA65: 0.59807291 | BB65: 9696.77 | BC65: 351
A66: GXG | B66: =DATE(YEAR(F66),MONTH(F66),DAY(F66)) -> 46044 | C66: =TEXT(YEAR(B66),"0")&"年" -> 2026年 | D66: =TEXT(MONTH(B66),"0")&"月" -> 1月 | E66: ="W"&TEXT(WEEKNUM(B66,2),"0") -> W4 | F66: 2026/01/22 19:59:17 | G66: 2026/01/23 01:45:29 | H66: 346 | I66: 458786 | J66: 912462 | K66: 61859 | L66: 10720.797 | M66: 82639 | N66: 521 | O66: 332 | P66: 0.89 | Q66: 4402 | R66: 2 | S66: 434 | T66: 47 | U66: 0.2452 | V66: 105 | W66: 55591 | X66: 14480 | Y66: 548211 | Z66: 37774 | AA66: 655 | AB66: 250903 | AC66: 240380.53 | AD66: 41660.404 | AE66: 657 | AF66: 578 | AG66: 189 | AH66: 72698.91 | AI66: 172 | AJ66: 0 | AK66: 0.0689 | AL66: 0.2605 | AM66: 0.0173 | AN66: 0.0399 | AO66: 0.0079 | AP66: 0.0093 | AQ66: 0 | AR66: 0 | AS66: 358 | AT66: 7058.65 | AU66: 214320.86 | AV66: 570 | AW66: 36582.14 | AX66: 85 | AY66: 0.1458 | AZ66: 138629.72 | BA66: 0.57670944 | BB66: 8861.27 | BC66: 349
A67: GXG | B67: =DATE(YEAR(F67),MONTH(F67),DAY(F67)) -> 46045 | C67: =TEXT(YEAR(B67),"0")&"年" -> 2026年 | D67: =TEXT(MONTH(B67),"0")&"月" -> 1月 | E67: ="W"&TEXT(WEEKNUM(B67,2),"0") -> W4 | F67: 2026/01/23 20:17:05 | G67: 2026/01/24 02:01:08 | H67: 344 | I67: 455493 | J67: 924948 | K67: 55433 | L67: 9667.1414 | M67: 73341 | N67: 579 | O67: 209 | P67: 0.82 | Q67: 3308 | R67: 1 | S67: 312 | T67: 47 | U67: 0.275 | V67: 106 | W67: 51938 | X67: 18953 | Y67: 523017 | Z67: 46796 | AA67: 474 | AB67: 259365 | AC67: 232983.34 | AD67: 40630.723 | AE67: 476 | AF67: 418 | AG67: 96 | AH67: 52158.8 | AI67: 90 | AJ67: 0 | AK67: 0.0895 | AL67: 0.3649 | AM67: 0.0101 | AN67: 0.0221 | AO67: 0.0065 | AP67: 0.0075 | AQ67: 0 | AR67: 0 | AS67: 147 | AT67: 8196.87 | AU67: 221249 | AV67: 411 | AW67: 38116 | AX67: 63 | AY67: 0.147 | AZ67: 182989.25 | BA67: 0.78541775 | BB67: 24066.73 | BC67: 331
A68: GXG | B68: =DATE(YEAR(F68),MONTH(F68),DAY(F68)) -> 46047 | C68: =TEXT(YEAR(B68),"0")&"年" -> 2026年 | D68: =TEXT(MONTH(B68),"0")&"月" -> 1月 | E68: ="W"&TEXT(WEEKNUM(B68,2),"0") -> W4 | F68: 2026/01/25 20:00:01 | G68: 2026/01/26 01:31:17 | H68: 331 | I68: 522136 | J68: 990512 | K68: 53603 | L68: 9708.7342 | M68: 69946 | N68: 632 | O68: 290 | P68: 0.76 | Q68: 2696 | R68: 1 | S68: 230 | T68: 0 | U68: 0.2253 | V68: 107 | W68: 50030 | X68: 15725 | Y68: 454276 | Z68: 42305 | AA68: 662 | AB68: 235465 | AC68: 224525.63 | AD68: 40666.747 | AE68: 672 | AF68: 569 | AG68: 113 | AH68: 42281.89 | AI68: 101 | AJ68: 0 | AK68: 0.0931 | AL68: 0.3143 | AM68: 0.0156 | AN68: 0.0362 | AO68: 0.0095 | AP68: 0.0106 | AQ68: 0 | AR68: 0 | AS68: 94 | AT68: 8319.64 | AU68: 201027.12 | AV68: 576 | AW68: 34437.88 | AX68: 86 | AY68: 0.1463 | AZ68: 119803.03 | BA68: 0.53358287 | BB68: 8766.32 | BC68: 325
A69: GXG | B69: =DATE(YEAR(F69),MONTH(F69),DAY(F69)) -> 46044 | C69: =TEXT(YEAR(B69),"0")&"年" -> 2026年 | D69: =TEXT(MONTH(B69),"0")&"月" -> 1月 | E69: ="W"&TEXT(WEEKNUM(B69,2),"0") -> W4 | F69: 2026/01/22 08:01:54 | G69: 2026/01/22 13:28:59 | H69: 327 | I69: 665524 | J69: 1159329 | K69: 67560 | L69: 12393.172 | M69: 88345 | N69: 1025 | O69: 423 | P69: 0.99 | Q69: 7144 | R69: 4 | S69: 843 | T69: 49 | U69: 0.2065 | V69: 104 | W69: 62656 | X69: 12815 | Y69: 402158 | Z69: 30388 | AA69: 603 | AB69: 232160 | AC69: 222934.67 | AD69: 40895.022 | AE69: 603 | AF69: 516 | AG69: 229 | AH69: 86245.18 | AI69: 195 | AJ69: 0 | AK69: 0.0756 | AL69: 0.2045 | AM69: 0.0198 | AN69: 0.0403 | AO69: 0.0068 | AP69: 0.0076 | AQ69: 0 | AR69: 0 | AS69: 787 | AT69: 7751.9 | AU69: 183407.54 | AV69: 479 | AW69: 48752.46 | AX69: 124 | AY69: 0.21 | AZ69: 127382.42 | BA69: 0.57138901 | BB69: 7968.82 | BC69: 308
A70: GXG | B70: =DATE(YEAR(F70),MONTH(F70),DAY(F70)) -> 46046 | C70: =TEXT(YEAR(B70),"0")&"年" -> 2026年 | D70: =TEXT(MONTH(B70),"0")&"月" -> 1月 | E70: ="W"&TEXT(WEEKNUM(B70,2),"0") -> W4 | F70: 2026/01/24 08:00:15 | G70: 2026/01/24 13:24:18 | H70: 324 | I70: 478331 | J70: 883241 | K70: 46007 | L70: 8518.5002 | M70: 60264 | N70: 783 | O70: 226 | P70: 0.95 | Q70: 3538 | R70: 3 | S70: 288 | T70: 29 | U70: 0.2803 | V70: 106 | W70: 44615 | X70: 13255 | Y70: 347182 | Z70: 34427 | AA70: 596 | AB70: 244666 | AC70: 221288.79 | AD70: 40973.083 | AE70: 596 | AF70: 440 | AG70: 73 | AH70: 33711.1 | AI70: 62 | AJ70: 0 | AK70: 0.0992 | AL70: 0.2971 | AM70: 0.0173 | AN70: 0.0332 | AO70: 0.0099 | AP70: 0.0096 | AQ70: 0 | AR70: 0 | AS70: 115 | AT70: 8618.77 | AU70: 214796.57 | AV70: 538 | AW70: 29869.43 | AX70: 58 | AY70: 0.1221 | AZ70: 155066.5 | BA70: 0.70237626 | BB70: 20008.95 | BC70: 328
A71: GXG | B71: =DATE(YEAR(F71),MONTH(F71),DAY(F71)) -> 46046 | C71: =TEXT(YEAR(B71),"0")&"年" -> 2026年 | D71: =TEXT(MONTH(B71),"0")&"月" -> 1月 | E71: ="W"&TEXT(WEEKNUM(B71,2),"0") -> W4 | F71: 2026/01/24 21:06:48 | G71: 2026/01/25 02:02:01 | H71: 295 | I71: 502730 | J71: 902358 | K71: 49312 | L71: 10022.198 | M71: 63290 | N71: 607 | O71: 182 | P71: 0.72 | Q71: 2218 | R71: 2 | S71: 232 | T71: 40 | U71: 0.2276 | V71: 106 | W71: 45264 | X71: 14638 | Y71: 435187 | Z71: 37713 | AA71: 621 | AB71: 216303 | AC71: 207242.26 | AD71: 42120.033 | AE71: 622 | AF71: 511 | AG71: 122 | AH71: 42486.3 | AI71: 106 | AJ71: 0 | AK71: 0.0867 | AL71: 0.3234 | AM71: 0.0165 | AN71: 0.0349 | AO71: 0.0098 | AP71: 0.0104 | AQ71: 0 | AR71: 0 | AS71: 93 | AT71: 6622.53 | AU71: 185808.59 | AV71: 536 | AW71: 30494.41 | AX71: 85 | AY71: 0.141 | AZ71: 99994.21 | BA71: 0.48903799 | BB71: 7581.19 | BC71: 266
A72: GXG | B72: =DATE(YEAR(F72),MONTH(F72),DAY(F72)) -> 46043 | C72: =TEXT(YEAR(B72),"0")&"年" -> 2026年 | D72: =TEXT(MONTH(B72),"0")&"月" -> 1月 | E72: ="W"&TEXT(WEEKNUM(B72,2),"0") -> W4 | F72: 2026/01/21 20:01:46 | G72: 2026/01/22 01:19:48 | H72: 318 | I72: 540870 | J72: 1075376 | K72: 64315 | L72: 12133.634 | M72: 87165 | N72: 686 | O72: 409 | P72: 0.92 | Q72: 4749 | R72: 2 | S72: 389 | T72: 51 | U72: 0.2978 | V72: 104 | W72: 60227 | X72: 14921 | Y72: 432369 | Z72: 35885 | AA72: 410 | AB72: 177777 | AC72: 171454.75 | AD72: 32346.562 | AE72: 412 | AF72: 353 | AG72: 137 | AH72: 57650.39 | AI72: 121 | AJ72: 0 | AK72: 0.083 | AL72: 0.2477 | AM72: 0.0114 | AN72: 0.0237 | AO72: 0.0047 | AP72: 0.0055 | AQ72: 0 | AR72: 0 | AS72: 399 | AT72: 6524.63 | AU72: 149079.24 | AV72: 343 | AW72: 28697.76 | AX72: 67 | AY72: 0.1614 | AZ72: 90692.55 | BA72: 0.53289079 | BB72: 5384.33 | BC72: 198
A73: GXG | B73: =DATE(YEAR(F73),MONTH(F73),DAY(F73)) -> 46046 | C73: =TEXT(YEAR(B73),"0")&"年" -> 2026年 | D73: =TEXT(MONTH(B73),"0")&"月" -> 1月 | E73: ="W"&TEXT(WEEKNUM(B73,2),"0") -> W4 | F73: 2026/01/24 14:00:13 | G73: 2026/01/24 19:09:21 | H73: 309 | I73: 302634 | J73: 549612 | K73: 25697 | L73: 4987.5566 | M73: 32947 | N73: 142 | O73: 74 | P73: 0.58 | Q73: 1630 | R73: 0 | S73: 125 | T73: 29 | U73: 0.206 | V73: 106 | W73: 23208 | X73: 7474 | Y73: 199277 | Z73: 17950 | AA73: 436 | AB73: 164453 | AC73: 159703.89 | AD73: 30997.089 | AE73: 439 | AF73: 374 | AG73: 86 | AH73: 34546.44 | AI73: 76 | AJ73: 0 | AK73: 0.0901 | AL73: 0.322 | AM73: 0.0243 | AN73: 0.05 | AO73: 0.0132 | AP73: 0.0146 | AQ73: 0 | AR73: 0 | AS73: 43 | AT73: 6196.66 | AU73: 138800.77 | AV73: 374 | AW73: 25652.23 | AX73: 62 | AY73: 0.156 | AZ73: 49457.82 | BA73: 0.3096845 | BB73: 3766.47 | BC73: 113
... A82: GXG | B82: =DATE(YEAR(F82),MONTH(F82),DAY(F82)) -> 46045 | C82: =TEXT(YEAR(B82),"0")&"年" -> 2026年 | D82: =TEXT(MONTH(B82),"0")&"月" -> 1月 | E82: ="W"&TEXT(WEEKNUM(B82,2),"0") -> W4 | F82: 2026/01/23 19:54:10 | G82: 2026/01/23 20:05:24 | H82: 11 | I82: 24683 | J82: 34012 | K82: 2852 | L82: 15233.234 | M82: 3177 | N82: 644 | O82: 298 | P82: 0.64 | Q82: 283 | R82: 0 | S82: 23 | T82: 5 | U82: 0.2973 | V82: 105 | W82: 2705 | X82: 631 | Y82: 16907 | Z82: 1290 | AA82: 3 | AB82: 748 | AC82: 668 | AD82: 3567.9525 | AE82: 3 | AF82: 1 | AG82: 0 | AH82: 0 | AI82: 0 | AJ82: 0 | AK82: 0.0763 | AL82: 0.2333 | AM82: 0.0023 | AN82: 0.0016 | AO82: 0.0009 | AP82: 0.0004 | AQ82: 0 | AR82: 0 | AS82: 20 | AT82: 157.14 | AU82: 748 | AV82: 3 | AW82: 0 | AX82: 0 | AY82: 0 | AZ82: 668 | BA82: 1 | BB82: 80 | BC82: 1

Sheet DAZZLE-日报
A1: 品牌 | B1: 日期 | C1: 年份 | D1: 月份 | E1: 周数 | F1: GMV | G1: 成交退款金额(退款时间) | H1: NET | I1: 商品卡GMV | J1: 直播GMV | K1: 投放消耗金额 | L1: ROI
A2: DAZZLE | B2: 46023 | C2: =TEXT(YEAR(B2),"0")&"年" -> 2026年 | D2: =TEXT(MONTH(B2),"0")&"月" -> 1月 | E2: ="W"&TEXT(WEEKNUM(B2,2),"0") -> W1 | F2: 611208 | G2: 615446.42 | H2: =F2-G2 -> -4238.42 | I2: 147432.43 | J2: 457178.87 | K2: 2615.01 | L2: =J2/K2 -> 174.82873
A3: DAZZLE | B3: 46024 | C3: =TEXT(YEAR(B3),"0")&"年" -> 2026年 | D3: =TEXT(MONTH(B3),"0")&"月" -> 1月 | E3: ="W"&TEXT(WEEKNUM(B3,2),"0") -> W1 | F3: 605695 | G3: 641783.68 | H3: =F3-G3 -> -36088.68 | I3: 163345.05 | J3: 427632.95 | K3: 2332.31 | L3: =J3/K3 -> 183.35168
A4: DAZZLE | B4: 46025 | C4: =TEXT(YEAR(B4),"0")&"年" -> 2026年 | D4: =TEXT(MONTH(B4),"0")&"月" -> 1月 | E4: ="W"&TEXT(WEEKNUM(B4,2),"0") -> W1 | F4: 658154 | G4: 551374.13 | H4: =F4-G4 -> 106779.87 | I4: 199464.45 | J4: 441752.55 | K4: 2504.1 | L4: =J4/K4 -> 176.4117
A5: DAZZLE | B5: 46026 | C5: =TEXT(YEAR(B5),"0")&"年" -> 2026年 | D5: =TEXT(MONTH(B5),"0")&"月" -> 1月 | E5: ="W"&TEXT(WEEKNUM(B5,2),"0") -> W1 | F5: 429059 | G5: 508225.07 | H5: =F5-G5 -> -79166.07 | I5: 139438 | J5: 280422 | K5: 1544.41 | L5: =J5/K5 -> 181.57225
A6: DAZZLE | B6: 46027 | C6: =TEXT(YEAR(B6),"0")&"年" -> 2026年 | D6: =TEXT(MONTH(B6),"0")&"月" -> 1月 | E6: ="W"&TEXT(WEEKNUM(B6,2),"0") -> W2 | F6: 501427 | G6: 538925.03 | H6: =F6-G6 -> -37498.03 | I6: 124047.4 | J6: 369100.6 | K6: 1756.23 | L6: =J6/K6 -> 210.16644
A7: DAZZLE | B7: 46028 | C7: =TEXT(YEAR(B7),"0")&"年" -> 2026年 | D7: =TEXT(MONTH(B7),"0")&"月" -> 1月 | E7: ="W"&TEXT(WEEKNUM(B7,2),"0") -> W2 | F7: 447262 | G7: 503767.37 | H7: =F7-G7 -> -56505.37 | I7: 118256 | J7: 328187 | K7: 1656.67 | L7: =J7/K7 -> 198.10041
A8: DAZZLE | B8: 46029 | C8: =TEXT(YEAR(B8),"0")&"年" -> 2026年 | D8: =TEXT(MONTH(B8),"0")&"月" -> 1月 | E8: ="W"&TEXT(WEEKNUM(B8,2),"0") -> W2 | F8: 472046 | G8: 531634.36 | H8: =F8-G8 -> -59588.36 | I8: 119038 | J8: 344204 | K8: 1724.34 | L8: =J8/K8 -> 199.61493
A9: DAZZLE | B9: 46030 | C9: =TEXT(YEAR(B9),"0")&"年" -> 2026年 | D9: =TEXT(MONTH(B9),"0")&"月" -> 1月 | E9: ="W"&TEXT(WEEKNUM(B9,2),"0") -> W2 | F9: 806121 | G9: 615470.05 | H9: =F9-G9 -> 190650.95 | I9: 187028.44 | J9: 604616.56 | K9: 2817.16 | L9: =J9/K9 -> 214.61918
A10: DAZZLE | B10: 46031 | C10: =TEXT(YEAR(B10),"0")&"年" -> 2026年 | D10: =TEXT(MONTH(B10),"0")&"月" -> 1月 | E10: ="W"&TEXT(WEEKNUM(B10,2),"0") -> W2 | F10: 673851 | G10: 472453.19 | H10: =F10-G10 -> 201397.81 | I10: 124434.35 | J10: 537092.65 | K10: 2650.73 | L10: =J10/K10 -> 202.62066
A11: DAZZLE | B11: 46032 | C11: =TEXT(YEAR(B11),"0")&"年" -> 2026年 | D11: =TEXT(MONTH(B11),"0")&"月" -> 1月 | E11: ="W"&TEXT(WEEKNUM(B11,2),"0") -> W2 | F11: 609678 | G11: 473479.19 | H11: =F11-G11 -> 136198.81 | I11: 129680.05 | J11: 466303.95 | K11: 2276.75 | L11: =J11/K11 -> 204.81122
A12: DAZZLE | B12: 46033 | C12: =TEXT(YEAR(B12),"0")&"年" -> 2026年 | D12: =TEXT(MONTH(B12),"0")&"月" -> 1月 | E12: ="W"&TEXT(WEEKNUM(B12,2),"0") -> W2 | F12: 1033873 | G12: 573781.21 | H12: =F12-G12 -> 460091.79 | I12: 169485.84 | J12: 854885.16 | K12: 3929.56 | L12: =J12/K12 -> 217.55239
A13: DAZZLE | B13: 46034 | C13: =TEXT(YEAR(B13),"0")&"年" -> 2026年 | D13: =TEXT(MONTH(B13),"0")&"月" -> 1月 | E13: ="W"&TEXT(WEEKNUM(B13,2),"0") -> W3 | F13: 561854 | G13: 442793.47 | H13: =F13-G13 -> 119060.53 | I13: 115242.81 | J13: 435077.19 | K13: 2225.42 | L13: =J13/K13 -> 195.50341
... A68: DAZZLE | B68: 46089 | C68: =TEXT(YEAR(B68),"0")&"年" -> 2026年 | D68: =TEXT(MONTH(B68),"0")&"月" -> 3月 | E68: ="W"&TEXT(WEEKNUM(B68,2),"0") -> W10 | F68: 997253.65 | G68: 782254.08 | H68: =F68-G68 -> 214999.57 | I68: 491118.48 | J68: 415117.76 | K68: 2023.27 | L68: =J68/K68 -> 205.17171

Sheet DAZZLE（视频号）-日报
A1: 品牌 | B1: 日期 | C1: 年份 | D1: 月份 | E1: 周数 | F1: GMV | G1: NET | H1: 退款金额
A2: DAZZLE | B2: 46023 | C2: =TEXT(YEAR(B2),"0")&"年" -> 2026年 | D2: =TEXT(MONTH(B2),"0")&"月" -> 1月 | E2: ="W"&TEXT(WEEKNUM(B2,2),"0") -> W1 | F2: 62158 | G2: =F2-H2 -> 17303 | H2: 44855
A3: DAZZLE | B3: 46024 | C3: =TEXT(YEAR(B3),"0")&"年" -> 2026年 | D3: =TEXT(MONTH(B3),"0")&"月" -> 1月 | E3: ="W"&TEXT(WEEKNUM(B3,2),"0") -> W1 | F3: 28151 | G3: =F3-H3 -> -18404.97 | H3: 46555.97
A4: DAZZLE | B4: 46025 | C4: =TEXT(YEAR(B4),"0")&"年" -> 2026年 | D4: =TEXT(MONTH(B4),"0")&"月" -> 1月 | E4: ="W"&TEXT(WEEKNUM(B4,2),"0") -> W1 | F4: 51943 | G4: =F4-H4 -> 14569 | H4: 37374
A5: DAZZLE | B5: 46026 | C5: =TEXT(YEAR(B5),"0")&"年" -> 2026年 | D5: =TEXT(MONTH(B5),"0")&"月" -> 1月 | E5: ="W"&TEXT(WEEKNUM(B5,2),"0") -> W1 | F5: 26173 | G5: =F5-H5 -> -6115 | H5: 32288
A6: DAZZLE | B6: 46027 | C6: =TEXT(YEAR(B6),"0")&"年" -> 2026年 | D6: =TEXT(MONTH(B6),"0")&"月" -> 1月 | E6: ="W"&TEXT(WEEKNUM(B6,2),"0") -> W2 | F6: 64752 | G6: =F6-H6 -> 17968 | H6: 46784
A7: DAZZLE | B7: 46028 | C7: =TEXT(YEAR(B7),"0")&"年" -> 2026年 | D7: =TEXT(MONTH(B7),"0")&"月" -> 1月 | E7: ="W"&TEXT(WEEKNUM(B7,2),"0") -> W2 | F7: 70629 | G7: =F7-H7 -> 19446 | H7: 51183
A8: DAZZLE | B8: 46029 | C8: =TEXT(YEAR(B8),"0")&"年" -> 2026年 | D8: =TEXT(MONTH(B8),"0")&"月" -> 1月 | E8: ="W"&TEXT(WEEKNUM(B8,2),"0") -> W2 | F8: 47334 | G8: =F8-H8 -> 9110 | H8: 38224
A9: DAZZLE | B9: 46030 | C9: =TEXT(YEAR(B9),"0")&"年" -> 2026年 | D9: =TEXT(MONTH(B9),"0")&"月" -> 1月 | E9: ="W"&TEXT(WEEKNUM(B9,2),"0") -> W2 | F9: 56806 | G9: =F9-H9 -> 9882 | H9: 46924
A10: DAZZLE | B10: 46031 | C10: =TEXT(YEAR(B10),"0")&"年" -> 2026年 | D10: =TEXT(MONTH(B10),"0")&"月" -> 1月 | E10: ="W"&TEXT(WEEKNUM(B10,2),"0") -> W2 | F10: 105132 | G10: =F10-H10 -> 53417 | H10: 51715
A11: DAZZLE | B11: 46032 | C11: =TEXT(YEAR(B11),"0")&"年" -> 2026年 | D11: =TEXT(MONTH(B11),"0")&"月" -> 1月 | E11: ="W"&TEXT(WEEKNUM(B11,2),"0") -> W2 | F11: 42097 | G11: =F11-H11 -> 2983 | H11: 39114
A12: DAZZLE | B12: 46033 | C12: =TEXT(YEAR(B12),"0")&"年" -> 2026年 | D12: =TEXT(MONTH(B12),"0")&"月" -> 1月 | E12: ="W"&TEXT(WEEKNUM(B12,2),"0") -> W2 | F12: 65197 | G12: =F12-H12 -> 13123 | H12: 52074
A13: DAZZLE | B13: 46034 | C13: =TEXT(YEAR(B13),"0")&"年" -> 2026年 | D13: =TEXT(MONTH(B13),"0")&"月" -> 1月 | E13: ="W"&TEXT(WEEKNUM(B13,2),"0") -> W3 | F13: 71671 | G13: =F13-H13 -> 34190 | H13: 37481
... A68: DAZZLE | B68: 46089 | C68: =TEXT(YEAR(B68),"0")&"年" -> 2026年 | D68: =TEXT(MONTH(B68),"0")&"月" -> 3月 | E68: ="W"&TEXT(WEEKNUM(B68,2),"0") -> W10 | F68: 43822 | G68: =F68-H68 -> -368 | H68: 44190

Sheet DAZZLE-直播明细
A1: 品牌 | B1: 直播日期 | C1: 年份 | D1: 月份 | E1: 周数 | F1: 直播开始时间 | G1: 直播结束时间 | H1: 直播时长(分钟) | I1: 直播间曝光人数 | J1: 直播间曝光次数 | K1: 直播间观看人数 | L1: 单小时观看人数 | M1: 直播间观看次数 | N1: 最高在线人数 | O1: 平均在线人数 | P1: 人均观看时长(分钟) | Q1: 评论次数 | R1: 新加直播团人数 | S1: 新增粉丝数 | T1: 取关粉丝数 | U1: 观看老粉占比 | V1: 带货商品数 | W1: 直播间商品曝光人数 | X1: 直播间商品点击人数 | Y1: 直播间商品曝光次数 | Z1: 直播间商品点击次数 | AA1: 直播间成交订单数 | AB1: 直播间成交金额 | AC1: 直播间用户支付金额 | AD1: 单小时用户支付金额 | AE1: 直播间成交件数 | AF1: 直播间成交人数 | AG1: 直播间退款订单数 | AH1: 直播间退款金额 | AI1: 直播间退款人数 | AJ1: 预估佣金支出 | AK1: 商品曝光-点击率(次数) | AL1: 商品曝光-点击率(人数) | AM1: 商品点击-成交率(次数) | AN1: 商品点击-成交率(人数) | AO1: 观看-成交率(次数) | AP1: 观看-成交率(人数) | AQ1: 预售订单数 | AR1: 预售全款金额 | AS1: 新加购物团人数 | AT1: 直播间投放消耗 | AU1: 净成交金额 | AV1: 净成交订单数 | AW1: 1小时退款金额 | AX1: 1小时退款订单数 | AY1: 1小时退款率 | AZ1: 消费券引导支付金额 | BA1: 消费券引导支付占比 | BB1: 消费券补贴金额 | BC1: 消费券使用量
A2: DAZZLE | B2: =DATE(YEAR(F2),MONTH(F2),DAY(F2)) -> 46033 | C2: =TEXT(YEAR(B2),"0")&"年" -> 2026年 | D2: =TEXT(MONTH(B2),"0")&"月" -> 1月 | E2: ="W"&TEXT(WEEKNUM(B2,2),"0") -> W2 | F2: 2026/01/11 08:15:20 | G2: 2026/01/11 13:15:30 | H2: 300 | I2: 92565 | J2: 186068 | K2: 13538 | L2: 2706.0966 | M2: 18033 | N2: 72 | O2: 53 | P2: 0.73 | Q2: 385 | R2: 0 | S2: 71 | T2: 8 | U2: 0.5314 | V2: 200 | W2: 12939 | X2: 4398 | Y2: 200235 | Z2: 15682 | AA2: 159 | AB2: 455504.3 | AC2: 455078.3 | AD2: 90965.124 | AE2: 159 | AF2: 132 | AG2: 132 | AH2: 386772 | AI2: 107 | AJ2: 0 | AK2: 0.0783 | AL2: 0.3399 | AM2: 0.0101 | AN2: 0.03 | AO2: 0.0088 | AP2: 0.0098 | AQ2: 0 | AR2: 0 | AS2: 2 | AT2: 1795.98 | AU2: 367332.3 | AV2: 127 | AW2: 88172 | AX2: 32 | AY2: 0.1936 | AZ2: - | BA2: - | BB2: - | BC2: -
A3: DAZZLE | B3: =DATE(YEAR(F3),MONTH(F3),DAY(F3)) -> 46040 | C3: =TEXT(YEAR(B3),"0")&"年" -> 2026年 | D3: =TEXT(MONTH(B3),"0")&"月" -> 1月 | E3: ="W"&TEXT(WEEKNUM(B3,2),"0") -> W3 | F3: 2026/01/18 07:57:35 | G3: 2026/01/18 13:07:37 | H3: 310 | I3: 187244 | J3: 337731 | K3: 16448 | L3: 3183.1416 | M3: 20932 | N3: 110 | O3: 69 | P3: 0.85 | Q3: 580 | R3: 0 | S3: 160 | T3: 13 | U3: 0.4441 | V3: 199 | W3: 16205 | X3: 7776 | Y3: 269769 | Z3: 23513 | AA3: 342 | AB3: 429752.53 | AC3: 411838.73 | AD3: 79702.152 | AE3: 342 | AF3: 286 | AG3: 119 | AH3: 144374.07 | AI3: 95 | AJ3: 0 | AK3: 0.0872 | AL3: 0.4799 | AM3: 0.0145 | AN3: 0.0368 | AO3: 0.0163 | AP3: 0.0174 | AQ3: 0 | AR3: 0 | AS3: 4 | AT3: 1467.67 | AU3: 367234.28 | AV3: 292 | AW3: 62518.25 | AX3: 50 | AY3: 0.1455 | AZ3: 270779.17 | BA3: 0.65748836 | BB3: 17757.4 | BC3: 216
A4: DAZZLE | B4: =DATE(YEAR(F4),MONTH(F4),DAY(F4)) -> 46030 | C4: =TEXT(YEAR(B4),"0")&"年" -> 2026年 | D4: =TEXT(MONTH(B4),"0")&"月" -> 1月 | E4: ="W"&TEXT(WEEKNUM(B4,2),"0") -> W2 | F4: 2026/01/08 19:58:38 | G4: 2026/01/09 00:00:03 | H4: 241 | I4: 61759 | J4: 168154 | K4: 11637 | L4: 2892.1781 | M4: 17749 | N4: 148 | O4: 83 | P4: 1.16 | Q4: 779 | R4: 0 | S4: 44 | T4: 9 | U4: 0.6588 | V4: 200 | W4: 11432 | X4: 5024 | Y4: 293838 | Z4: 26817 | AA4: 161 | AB4: 303862.5 | AC4: 303486.27 | AD4: 75426.343 | AE4: 161 | AF4: 101 | AG4: 132 | AH4: 248319.49 | AI4: 78 | AJ4: 0 | AK4: 0.0913 | AL4: 0.4395 | AM4: 0.006 | AN4: 0.0201 | AO4: 0.0091 | AP4: 0.0087 | AQ4: 0 | AR4: 0 | AS4: 0 | AT4: 1396.82 | AU4: 259552.5 | AV4: 138 | AW4: 44310 | AX4: 23 | AY4: 0.1458 | AZ4: - | BA4: - | BB4: - | BC4: -
A5: DAZZLE | B5: =DATE(YEAR(F5),MONTH(F5),DAY(F5)) -> 46036 | C5: =TEXT(YEAR(B5),"0")&"年" -> 2026年 | D5: =TEXT(MONTH(B5),"0")&"月" -> 1月 | E5: ="W"&TEXT(WEEKNUM(B5,2),"0") -> W3 | F5: 2026/01/14 14:02:16 | G5: 2026/01/14 19:03:21 | H5: 301 | I5: 67326 | J5: 157953 | K5: 9369 | L5: 1867.0578 | M5: 13192 | N5: 65 | O5: 38 | P5: 0.68 | Q5: 271 | R5: 0 | S5: 33 | T5: 4 | U5: 0.5937 | V5: 206 | W5: 8949 | X5: 3421 | Y5: 154651 | Z5: 11755 | AA5: 105 | AB5: 260733 | AC5: 260531 | AD5: 51918.716 | AE5: 105 | AF5: 79 | AG5: 65 | AH5: 161695 | AI5: 50 | AJ5: 0 | AK5: 0.076 | AL5: 0.3823 | AM5: 0.0089 | AN5: 0.0231 | AO5: 0.008 | AP5: 0.0084 | AQ5: 0 | AR5: 0 | AS5: 3 | AT5: 1140.63 | AU5: 214499 | AV5: 89 | AW5: 46234 | AX5: 16 | AY5: 0.1773 | AZ5: - | BA5: - | BB5: - | BC5: -
A6: DAZZLE | B6: =DATE(YEAR(F6),MONTH(F6),DAY(F6)) -> 46034 | C6: =TEXT(YEAR(B6),"0")&"年" -> 2026年 | D6: =TEXT(MONTH(B6),"0")&"月" -> 1月 | E6: ="W"&TEXT(WEEKNUM(B6,2),"0") -> W3 | F6: 2026/01/12 08:03:33 | G6: 2026/01/12 13:11:37 | H6: 308 | I6: 67366 | J6: 145363 | K6: 10002 | L6: 1948.0199 | M6: 13752 | N6: 66 | O6: 41 | P6: 0.77 | Q6: 378 | R6: 0 | S6: 38 | T6: 2 | U6: 0.5773 | V6: 198 | W6: 9455 | X6: 3183 | Y6: 152864 | Z6: 11302 | AA6: 122 | AB6: 255970 | AC6: 255673 | AD6: 49795.65 | AE6: 122 | AF6: 101 | AG6: 96 | AH6: 205274 | AI6: 82 | AJ6: 0 | AK6: 0.0739 | AL6: 0.3366 | AM6: 0.0108 | AN6: 0.0317 | AO6: 0.0089 | AP6: 0.0101 | AQ6: 0 | AR6: 0 | AS6: 1 | AT6: 1317.97 | AU6: 218845 | AV6: 103 | AW6: 37125 | AX6: 19 | AY6: 0.145 | AZ6: - | BA6: - | BB6: - | BC6: -
A7: DAZZLE | B7: =DATE(YEAR(F7),MONTH(F7),DAY(F7)) -> 46041 | C7: =TEXT(YEAR(B7),"0")&"年" -> 2026年 | D7: =TEXT(MONTH(B7),"0")&"月" -> 1月 | E7: ="W"&TEXT(WEEKNUM(B7,2),"0") -> W4 | F7: 2026/01/19 20:11:57 | G7: 2026/01/20 00:17:17 | H7: 245 | I7: 117636 | J7: 226305 | K7: 15952 | L7: 3901.3043 | M7: 20571 | N7: 126 | O7: 64 | P7: 0.59 | Q7: 440 | R7: 0 | S7: 71 | T7: 10 | U7: 0.4789 | V7: 201 | W7: 14889 | X7: 4920 | Y7: 205011 | Z7: 15969 | AA7: 151 | AB7: 263237.09 | AC7: 254849.94 | AD7: 62327.431 | AE7: 151 | AF7: 117 | AG7: 58 | AH7: 101396.24 | AI7: 50 | AJ7: 0 | AK7: 0.0779 | AL7: 0.3304 | AM7: 0.0095 | AN7: 0.0238 | AO7: 0.0073 | AP7: 0.0073 | AQ7: 0 | AR7: 0 | AS7: 2 | AT7: 889.7 | AU7: 185758.59 | AV7: 109 | AW7: 77478.5 | AX7: 42 | AY7: 0.2943 | AZ7: 116229.85 | BA7: 0.45607172 | BB7: 8130.15 | BC7: 65
A8: DAZZLE | B8: =DATE(YEAR(F8),MONTH(F8),DAY(F8)) -> 46031 | C8: =TEXT(YEAR(B8),"0")&"年" -> 2026年 | D8: =TEXT(MONTH(B8),"0")&"月" -> 1月 | E8: ="W"&TEXT(WEEKNUM(B8,2),"0") -> W2 | F8: 2026/01/09 14:07:31 | G8: 2026/01/09 19:07:46 | H8: 300 | I8: 77743 | J8: 177990 | K8: 10811 | L8: 2160.3997 | M8: 15046 | N8: 75 | O8: 50 | P8: 0.83 | Q8: 331 | R8: 0 | S8: 45 | T8: 7 | U8: 0.6053 | V8: 195 | W8: 10416 | X8: 4237 | Y8: 183780 | Z8: 15223 | AA8: 97 | AB8: 239601 | AC8: 239372 | AD8: 47834.538 | AE8: 97 | AF8: 75 | AG8: 79 | AH8: 202850.5 | AI8: 62 | AJ8: 0 | AK8: 0.0828 | AL8: 0.4068 | AM8: 0.0064 | AN8: 0.0177 | AO8: 0.0064 | AP8: 0.0069 | AQ8: 0 | AR8: 0 | AS8: 1 | AT8: 1077.96 | AU8: 205167 | AV8: 84 | AW8: 34434 | AX8: 13 | AY8: 0.1437 | AZ8: - | BA8: - | BB8: - | BC8: -
A9: DAZZLE | B9: =DATE(YEAR(F9),MONTH(F9),DAY(F9)) -> 46023 | C9: =TEXT(YEAR(B9),"0")&"年" -> 2026年 | D9: =TEXT(MONTH(B9),"0")&"月" -> 1月 | E9: ="W"&TEXT(WEEKNUM(B9,2),"0") -> W1 | F9: 2026/01/01 16:12:17 | G9: 2026/01/01 19:13:21 | H9: 181 | I9: 78859 | J9: 157409 | K9: 9956 | L9: 3299.1163 | M9: 13221 | N9: 121 | O9: 64 | P9: 0.72 | Q9: 357 | R9: 0 | S9: 40 | T9: 3 | U9: 0.5833 | V9: 199 | W9: 9568 | X9: 3680 | Y9: 176285 | Z9: 13829 | AA9: 118 | AB9: 223587.78 | AC9: 223175.78 | AD9: 73953.683 | AE9: 118 | AF9: 92 | AG9: 96 | AH9: 182897.48 | AI9: 77 | AJ9: 0 | AK9: 0.0784 | AL9: 0.3846 | AM9: 0.0085 | AN9: 0.025 | AO9: 0.0089 | AP9: 0.0092 | AQ9: 0 | AR9: 0 | AS9: 0 | AT9: 1047 | AU9: 200264.78 | AV9: 102 | AW9: 23323 | AX9: 16 | AY9: 0.1043 | AZ9: - | BA9: - | BB9: - | BC9: -
A10: DAZZLE | B10: =DATE(YEAR(F10),MONTH(F10),DAY(F10)) -> 46032 | C10: =TEXT(YEAR(B10),"0")&"年" -> 2026年 | D10: =TEXT(MONTH(B10),"0")&"月" -> 1月 | E10: ="W"&TEXT(WEEKNUM(B10,2),"0") -> W2 | F10: 2026/01/10 20:04:40 | G10: 2026/01/11 01:06:15 | H10: 301 | I10: 63138 | J10: 169817 | K10: 10600 | L10: 2108.8699 | M10: 15327 | N10: 83 | O10: 50 | P10: 0.94 | Q10: 371 | R10: 0 | S10: 42 | T10: 7 | U10: 0.6562 | V10: 200 | W10: 10223 | X10: 3494 | Y10: 207754 | Z10: 13890 | AA10: 78 | AB10: 219910 | AC10: 219732 | AD10: 43715.678 | AE10: 78 | AF10: 65 | AG10: 60 | AH10: 167630 | AI10: 49 | AJ10: 0 | AK10: 0.0669 | AL10: 0.3418 | AM10: 0.0056 | AN10: 0.0186 | AO10: 0.0051 | AP10: 0.0061 | AQ10: 0 | AR10: 0 | AS10: 1 | AT10: 987.34 | AU10: 174168 | AV10: 63 | AW10: 45742 | AX10: 15 | AY10: 0.208 | AZ10: - | BA10: - | BB10: - | BC10: -
A11: DAZZLE | B11: =DATE(YEAR(F11),MONTH(F11),DAY(F11)) -> 46038 | C11: =TEXT(YEAR(B11),"0")&"年" -> 2026年 | D11: =TEXT(MONTH(B11),"0")&"月" -> 1月 | E11: ="W"&TEXT(WEEKNUM(B11,2),"0") -> W3 | F11: 2026/01/16 20:03:15 | G11: 2026/01/17 01:05:11 | H11: 301 | I11: 81740 | J11: 187183 | K11: 9831 | L11: 1953.6101 | M11: 13533 | N11: 74 | O11: 51 | P11: 1.06 | Q11: 479 | R11: 0 | S11: 57 | T11: 6 | U11: 0.5979 | V11: 202 | W11: 9577 | X11: 4000 | Y11: 211286 | Z11: 16527 | AA11: 113 | AB11: 217316 | AC11: 216132.2 | AD11: 42949.653 | AE11: 113 | AF11: 80 | AG11: 36 | AH11: 72576 | AI11: 30 | AJ11: 0 | AK11: 0.0782 | AL11: 0.4177 | AM11: 0.0068 | AN11: 0.02 | AO11: 0.0083 | AP11: 0.0081 | AQ11: 0 | AR11: 0 | AS11: 3 | AT11: 916.76 | AU11: 184818 | AV11: 97 | AW11: 32498 | AX11: 16 | AY11: 0.1495 | AZ11: 11516.05 | BA11: 0.053282435 | BB11: 908.95 | BC11: 8
A12: DAZZLE | B12: =DATE(YEAR(F12),MONTH(F12),DAY(F12)) -> 46040 | C12: =TEXT(YEAR(B12),"0")&"年" -> 2026年 | D12: =TEXT(MONTH(B12),"0")&"月" -> 1月 | E12: ="W"&TEXT(WEEKNUM(B12,2),"0") -> W3 | F12: 2026/01/18 14:00:17 | G12: 2026/01/18 19:01:20 | H12: 301 | I12: 128678 | J12: 253062 | K12: 11117 | L12: 2215.6452 | M12: 14890 | N12: 90 | O12: 44 | P12: 0.74 | Q12: 343 | R12: 0 | S12: 79 | T12: 11 | U12: 0.5146 | V12: 202 | W12: 10734 | X12: 4706 | Y12: 195631 | Z12: 14542 | AA12: 122 | AB12: 211518.87 | AC12: 207151 | AD12: 41285.7 | AE12: 122 | AF12: 107 | AG12: 31 | AH12: 54350.67 | AI12: 30 | AJ12: 0 | AK12: 0.0743 | AL12: 0.4384 | AM12: 0.0084 | AN12: 0.0227 | AO12: 0.0082 | AP12: 0.0096 | AQ12: 0 | AR12: 0 | AS12: 1 | AT12: 1169.64 | AU12: 186567.64 | AV12: 108 | AW12: 24951.23 | AX12: 14 | AY12: 0.118 | AZ12: 59327.39 | BA12: 0.28639683 | BB12: 4035.87 | BC12: 44
A13: DAZZLE | B13: =DATE(YEAR(F13),MONTH(F13),DAY(F13)) -> 46037 | C13: =TEXT(YEAR(B13),"0")&"年" -> 2026年 | D13: =TEXT(MONTH(B13),"0")&"月" -> 1月 | E13: ="W"&TEXT(WEEKNUM(B13,2),"0") -> W3 | F13: 2026/01/15 20:05:00 | G13: 2026/01/16 00:08:18 | H13: 243 | I13: 72541 | J13: 149850 | K13: 8622 | L13: 2126.2639 | M13: 11426 | N13: 70 | O13: 43 | P13: 0.76 | Q13: 357 | R13: 1 | S13: 40 | T13: 5 | U13: 0.6138 | V13: 201 | W13: 8234 | X13: 3436 | Y13: 160309 | Z13: 12412 | AA13: 91 | AB13: 204899 | AC13: 204333.42 | AD13: 50390.486 | AE13: 91 | AF13: 77 | AG13: 45 | AH13: 94789.42 | AI13: 40 | AJ13: 0 | AK13: 0.0774 | AL13: 0.4173 | AM13: 0.0073 | AN13: 0.0224 | AO13: 0.008 | AP13: 0.0089 | AQ13: 0 | AR13: 0 | AS13: 0 | AT13: 906.87 | AU13: 167809.72 | AV13: 74 | AW13: 37089.28 | AX13: 17 | AY13: 0.181 | AZ13: - | BA13: - | BB13: - | BC13: -
A14: DAZZLE | B14: =DATE(YEAR(F14),MONTH(F14),DAY(F14)) -> 46035 | C14: =TEXT(YEAR(B14),"0")&"年" -> 2026年 | D14: =TEXT(MONTH(B14),"0")&"月" -> 1月 | E14: ="W"&TEXT(WEEKNUM(B14,2),"0") -> W3 | F14: 2026/01/13 14:00:28 | G14: 2026/01/13 19:00:31 | H14: 300 | I14: 53183 | J14: 127511 | K14: 7473 | L14: 1494.3509 | M14: 10473 | N14: 60 | O14: 33 | P14: 0.75 | Q14: 207 | R14: 0 | S14: 21 | T14: 9 | U14: 0.6458 | V14: 200 | W14: 7043 | X14: 2500 | Y14: 125149 | Z14: 8856 | AA14: 91 | AB14: 198057.66 | AC14: 197661.58 | AD14: 39525.728 | AE14: 91 | AF14: 76 | AG14: 63 | AH14: 133210.58 | AI14: 53 | AJ14: 0 | AK14: 0.0708 | AL14: 0.355 | AM14: 0.0103 | AN14: 0.0304 | AO14: 0.0087 | AP14: 0.0102 | AQ14: 0 | AR14: 0 | AS14: 2 | AT14: 684.89 | AU14: 154169.66 | AV14: 71 | AW14: 43888 | AX14: 20 | AY14: 0.2216 | AZ14: - | BA14: - | BB14: - | BC14: -
A15: DAZZLE | B15: =DATE(YEAR(F15),MONTH(F15),DAY(F15)) -> 46024 | C15: =TEXT(YEAR(B15),"0")&"年" -> 2026年 | D15: =TEXT(MONTH(B15),"0")&"月" -> 1月 | E15: ="W"&TEXT(WEEKNUM(B15,2),"0") -> W1 | F15: 2026/01/02 19:54:55 | G15: 2026/01/03 00:58:27 | H15: 303 | I15: 67379 | J15: 169132 | K15: 11324 | L15: 2238.4362 | M15: 16370 | N15: 81 | O15: 51 | P15: 0.84 | Q15: 396 | R15: 0 | S15: 39 | T15: 8 | U15: 0.6307 | V15: 200 | W15: 10822 | X15: 3819 | Y15: 219708 | Z15: 15368 | AA15: 78 | AB15: 193426 | AC15: 193150 | AD15: 38180.321 | AE15: 78 | AF15: 66 | AG15: 60 | AH15: 150612 | AI15: 49 | AJ15: 0 | AK15: 0.0699 | AL15: 0.3529 | AM15: 0.0051 | AN15: 0.0173 | AO15: 0.0048 | AP15: 0.0058 | AQ15: 0 | AR15: 0 | AS15: 2 | AT15: 1012.86 | AU15: 166476 | AV15: 68 | AW15: 26950 | AX15: 10 | AY15: 0.1393 | AZ15: - | BA15: - | BB15: - | BC15: -
A16: DAZZLE | B16: =DATE(YEAR(F16),MONTH(F16),DAY(F16)) -> 46037 | C16: =TEXT(YEAR(B16),"0")&"年" -> 2026年 | D16: =TEXT(MONTH(B16),"0")&"月" -> 1月 | E16: ="W"&TEXT(WEEKNUM(B16,2),"0") -> W3 | F16: 2026/01/15 14:03:12 | G16: 2026/01/15 19:05:18 | H16: 302 | I16: 69508 | J16: 148178 | K16: 7114 | L16: 1412.9096 | M16: 9542 | N16: 54 | O16: 32 | P16: 0.82 | Q16: 309 | R16: 0 | S16: 44 | T16: 9 | U16: 0.6209 | V16: 210 | W16: 6848 | X16: 2710 | Y16: 124777 | Z16: 8647 | AA16: 91 | AB16: 192128 | AC16: 191696.49 | AD16: 38072.788 | AE16: 91 | AF16: 78 | AG16: 56 | AH16: 112281.49 | AI16: 50 | AJ16: 0 | AK16: 0.0693 | AL16: 0.3957 | AM16: 0.0105 | AN16: 0.0288 | AO16: 0.0095 | AP16: 0.011 | AQ16: 0 | AR16: 0 | AS16: 1 | AT16: 760.55 | AU16: 152313 | AV16: 69 | AW16: 39815 | AX16: 22 | AY16: 0.2072 | AZ16: - | BA16: - | BB16: - | BC16: -
A17: DAZZLE | B17: =DATE(YEAR(F17),MONTH(F17),DAY(F17)) -> 46039 | C17: =TEXT(YEAR(B17),"0")&"年" -> 2026年 | D17: =TEXT(MONTH(B17),"0")&"月" -> 1月 | E17: ="W"&TEXT(WEEKNUM(B17,2),"0") -> W3 | F17: 2026/01/17 19:59:33 | G17: 2026/01/18 01:01:07 | H17: 301 | I17: 102863 | J17: 211437 | K17: 10804 | L17: 2149.5744 | M17: 14390 | N17: 67 | O17: 46 | P17: 0.82 | Q17: 350 | R17: 0 | S17: 88 | T17: 14 | U17: 0.5911 | V17: 204 | W17: 10351 | X17: 4244 | Y17: 197058 | Z17: 15178 | AA17: 154 | AB17: 184755.85 | AC17: 176461.05 | AD17: 35108.864 | AE17: 154 | AF17: 136 | AG17: 59 | AH17: 62175.57 | AI17: 52 | AJ17: 0 | AK17: 0.077 | AL17: 0.41 | AM17: 0.0101 | AN17: 0.032 | AO17: 0.0107 | AP17: 0.0126 | AQ17: 0 | AR17: 0 | AS17: 6 | AT17: 994.93 | AU17: 153714.85 | AV17: 125 | AW17: 31041 | AX17: 29 | AY17: 0.168 | AZ17: 87339.45 | BA17: 0.4949503 | BB17: 8063.4 | BC17: 89
A18: DAZZLE | B18: =DATE(YEAR(F18),MONTH(F18),DAY(F18)) -> 46040 | C18: =TEXT(YEAR(B18),"0")&"年" -> 2026年 | D18: =TEXT(MONTH(B18),"0")&"月" -> 1月 | E18: ="W"&TEXT(WEEKNUM(B18,2),"0") -> W3 | F18: 2026/01/18 20:00:45 | G18: 2026/01/19 00:05:59 | H18: 245 | I18: 84271 | J18: 170929 | K18: 9871 | L18: 2415.0877 | M18: 12920 | N18: 78 | O18: 46 | P18: 0.69 | Q18: 215 | R18: 0 | S18: 47 | T18: 12 | U18: 0.5854 | V18: 196 | W18: 9302 | X18: 4263 | Y18: 166284 | Z18: 14744 | AA18: 94 | AB18: 176346.44 | AC18: 174942.44 | AD18: 42802.282 | AE18: 94 | AF18: 72 | AG18: 18 | AH18: 38420 | AI18: 16 | AJ18: 0 | AK18: 0.0887 | AL18: 0.4583 | AM18: 0.0064 | AN18: 0.0169 | AO18: 0.0073 | AP18: 0.0073 | AQ18: 0 | AR18: 0 | AS18: 1 | AT18: 209.54 | AU18: 159909.44 | AV18: 84 | AW18: 16437 | AX18: 10 | AY18: 0.0932 | AZ18: 17579 | BA18: 0.10048448 | BB18: 1380 | BC18: 14
A19: DAZZLE | B19: =DATE(YEAR(F19),MONTH(F19),DAY(F19)) -> 46042 | C19: =TEXT(YEAR(B19),"0")&"年" -> 2026年 | D19: =TEXT(MONTH(B19),"0")&"月" -> 1月 | E19: ="W"&TEXT(WEEKNUM(B19,2),"0") -> W4 | F19: 2026/01/20 14:00:46 | G19: 2026/01/20 19:07:53 | H19: 307 | I19: 79903 | J19: 175156 | K19: 10676 | L19: 2085.722 | M19: 14405 | N19: 65 | O19: 38 | P19: 0.69 | Q19: 334 | R19: 0 | S19: 44 | T19: 3 | U19: 0.551 | V19: 203 | W19: 10042 | X19: 3758 | Y19: 154653 | Z19: 11758 | AA19: 140 | AB19: 181967.3 | AC19: 174616.6 | AD19: 34114.059 | AE19: 140 | AF19: 115 | AG19: 47 | AH19: 60203.16 | AI19: 35 | AJ19: 0 | AK19: 0.076 | AL19: 0.3742 | AM19: 0.0119 | AN19: 0.0306 | AO19: 0.0097 | AP19: 0.0108 | AQ19: 0 | AR19: 0 | AS19: 2 | AT19: 645.18 | AU19: 132402.82 | AV19: 102 | AW19: 49564.48 | AX19: 38 | AY19: 0.2724 | AZ19: 75375.85 | BA19: 0.43166486 | BB19: 7218.45 | BC19: 67
A20: DAZZLE | B20: =DATE(YEAR(F20),MONTH(F20),DAY(F20)) -> 46032 | C20: =TEXT(YEAR(B20),"0")&"年" -> 2026年 | D20: =TEXT(MONTH(B20),"0")&"月" -> 1月 | E20: ="W"&TEXT(WEEKNUM(B20,2),"0") -> W2 | F20: 2026/01/10 14:00:40 | G20: 2026/01/10 19:00:43 | H20: 300 | I20: 50883 | J20: 130564 | K20: 8239 | L20: 1647.5254 | M20: 11857 | N20: 80 | O20: 38 | P20: 0.82 | Q20: 215 | R20: 0 | S20: 24 | T20: 6 | U20: 0.6649 | V20: 200 | W20: 7795 | X20: 2853 | Y20: 154012 | Z20: 10827 | AA20: 75 | AB20: 172657.5 | AC20: 172498.7 | AD20: 34493.991 | AE20: 75 | AF20: 62 | AG20: 56 | AH20: 126680.02 | AI20: 47 | AJ20: 0 | AK20: 0.0703 | AL20: 0.366 | AM20: 0.0069 | AN20: 0.0217 | AO20: 0.0063 | AP20: 0.0075 | AQ20: 0 | AR20: 0 | AS20: 2 | AT20: 724.24 | AU20: 151761.5 | AV20: 66 | AW20: 20896 | AX20: 9 | AY20: 0.121 | AZ20: - | BA20: - | BB20: - | BC20: -
A21: DAZZLE | B21: =DATE(YEAR(F21),MONTH(F21),DAY(F21)) -> 46038 | C21: =TEXT(YEAR(B21),"0")&"年" -> 2026年 | D21: =TEXT(MONTH(B21),"0")&"月" -> 1月 | E21: ="W"&TEXT(WEEKNUM(B21,2),"0") -> W3 | F21: 2026/01/16 08:00:22 | G21: 2026/01/16 13:00:25 | H21: 300 | I21: 45811 | J21: 108614 | K21: 5138 | L21: 1027.4288 | M21: 7190 | N21: 51 | O21: 29 | P21: 1.1 | Q21: 224 | R21: 0 | S21: 32 | T21: 3 | U21: 0.6355 | V21: 195 | W21: 4954 | X21: 1816 | Y21: 107921 | Z21: 6716 | AA21: 74 | AB21: 175048.85 | AC21: 169458.63 | AD21: 33886.078 | AE21: 74 | AF21: 55 | AG21: 41 | AH21: 95207.32 | AI21: 28 | AJ21: 0 | AK21: 0.0622 | AL21: 0.3666 | AM21: 0.011 | AN21: 0.0303 | AO21: 0.0103 | AP21: 0.0107 | AQ21: 0 | AR21: 0 | AS21: 1 | AT21: 955.58 | AU21: 144542.85 | AV21: 60 | AW21: 30506 | AX21: 14 | AY21: 0.1743 | AZ21: 53768.7 | BA21: 0.31729691 | BB21: 5436.22 | BC21: 24
A22: DAZZLE | B22: =DATE(YEAR(F22),MONTH(F22),DAY(F22)) -> 46033 | C22: =TEXT(YEAR(B22),"0")&"年" -> 2026年 | D22: =TEXT(MONTH(B22),"0")&"月" -> 1月 | E22: ="W"&TEXT(WEEKNUM(B22,2),"0") -> W2 | F22: 2026/01/11 14:00:51 | G22: 2026/01/11 19:02:05 | H22: 301 | I22: 61664 | J22: 144519 | K22: 9462 | L22: 1884.652 | M22: 13531 | N22: 79 | O22: 40 | P22: 0.76 | Q22: 335 | R22: 0 | S22: 43 | T22: 2 | U22: 0.6031 | V22: 203 | W22: 8798 | X22: 2826 | Y22: 165062 | Z22: 10832 | AA22: 73 | AB22: 169476 | AC22: 169307 | AD22: 33722.762 | AE22: 73 | AF22: 56 | AG22: 56 | AH22: 134133 | AI22: 44 | AJ22: 0 | AK22: 0.0656 | AL22: 0.3212 | AM22: 0.0067 | AN22: 0.0198 | AO22: 0.0054 | AP22: 0.0059 | AQ22: 0 | AR22: 0 | AS22: 4 | AT22: 1018.11 | AU22: 138049 | AV22: 60 | AW22: 31427 | AX22: 13 | AY22: 0.1854 | AZ22: - | BA22: - | BB22: - | BC22: -
A23: DAZZLE | B23: =DATE(YEAR(F23),MONTH(F23),DAY(F23)) -> 46031 | C23: =TEXT(YEAR(B23),"0")&"年" -> 2026年 | D23: =TEXT(MONTH(B23),"0")&"月" -> 1月 | E23: ="W"&TEXT(WEEKNUM(B23,2),"0") -> W2 | F23: 2026/01/09 20:01:26 | G23: 2026/01/10 01:05:36 | H23: 304 | I23: 73580 | J23: 173646 | K23: 11425 | L23: 2253.6986 | M23: 16473 | N23: 87 | O23: 53 | P23: 0.9 | Q23: 392 | R23: 0 | S23: 48 | T23: 10 | U23: 0.6249 | V23: 196 | W23: 10944 | X23: 3939 | Y23: 219957 | Z23: 16288 | AA23: 67 | AB23: 168343.95 | AC23: 168199.95 | AD23: 33179.168 | AE23: 67 | AF23: 49 | AG23: 59 | AH23: 146620.95 | AI23: 46 | AJ23: 0 | AK23: 0.0741 | AL23: 0.3599 | AM23: 0.0041 | AN23: 0.0124 | AO23: 0.0041 | AP23: 0.0043 | AQ23: 0 | AR23: 0 | AS23: 3 | AT23: 882.3 | AU23: 133625.95 | AV23: 54 | AW23: 34718 | AX23: 13 | AY23: 0.2062 | AZ23: - | BA23: - | BB23: - | BC23: -
A24: DAZZLE | B24: =DATE(YEAR(F24),MONTH(F24),DAY(F24)) -> 46029 | C24: =TEXT(YEAR(B24),"0")&"年" -> 2026年 | D24: =TEXT(MONTH(B24),"0")&"月" -> 1月 | E24: ="W"&TEXT(WEEKNUM(B24,2),"0") -> W2 | F24: 2026/01/07 14:00:40 | G24: 2026/01/07 19:10:50 | H24: 310 | I24: 63468 | J24: 139145 | K24: 8959 | L24: 1733.0682 | M24: 12229 | N24: 75 | O24: 38 | P24: 0.82 | Q24: 296 | R24: 0 | S24: 30 | T24: 8 | U24: 0.6155 | V24: 212 | W24: 8460 | X24: 3180 | Y24: 152017 | Z24: 12208 | AA24: 82 | AB24: 167923 | AC24: 167741 | AD24: 32448.555 | AE24: 82 | AF24: 64 | AG24: 63 | AH24: 135720 | AI24: 46 | AJ24: 0 | AK24: 0.0803 | AL24: 0.3759 | AM24: 0.0067 | AN24: 0.0201 | AO24: 0.0067 | AP24: 0.0071 | AQ24: 0 | AR24: 0 | AS24: 0 | AT24: 516.81 | AU24: 122318 | AV24: 60 | AW24: 45605 | AX24: 22 | AY24: 0.2716 | AZ24: - | BA24: - | BB24: - | BC24: -
A25: DAZZLE | B25: =DATE(YEAR(F25),MONTH(F25),DAY(F25)) -> 46035 | C25: =TEXT(YEAR(B25),"0")&"年" -> 2026年 | D25: =TEXT(MONTH(B25),"0")&"月" -> 1月 | E25: ="W"&TEXT(WEEKNUM(B25,2),"0") -> W3 | F25: 2026/01/13 20:04:45 | G25: 2026/01/14 00:05:31 | H25: 240 | I25: 80740 | J25: 161314 | K25: 10983 | L25: 2737.0068 | M25: 14334 | N25: 80 | O25: 46 | P25: 0.63 | Q25: 344 | R25: 0 | S25: 51 | T25: 5 | U25: 0.5282 | V25: 202 | W25: 10430 | X25: 3447 | Y25: 152254 | Z25: 11242 | AA25: 91 | AB25: 165002.03 | AC25: 164533.16 | AD25: 41002.31 | AE25: 91 | AF25: 69 | AG25: 70 | AH25: 128952 | AI25: 54 | AJ25: 0 | AK25: 0.0738 | AL25: 0.3305 | AM25: 0.0081 | AN25: 0.02 | AO25: 0.0063 | AP25: 0.0063 | AQ25: 0 | AR25: 0 | AS25: 0 | AT25: 725.37 | AU25: 96300.03 | AV25: 56 | AW25: 68702 | AX25: 35 | AY25: 0.4164 | AZ25: - | BA25: - | BB25: - | BC25: -
A26: DAZZLE | B26: =DATE(YEAR(F26),MONTH(F26),DAY(F26)) -> 46025 | C26: =TEXT(YEAR(B26),"0")&"年" -> 2026年 | D26: =TEXT(MONTH(B26),"0")&"月" -> 1月 | E26: ="W"&TEXT(WEEKNUM(B26,2),"0") -> W1 | F26: 2026/01/03 14:00:19 | G26: 2026/01/03 19:00:21 | H26: 300 | I26: 58115 | J26: 144019 | K26: 9013 | L26: 1802.3997 | M26: 12947 | N26: 55 | O26: 37 | P26: 0.68 | Q26: 246 | R26: 0 | S26: 34 | T26: 2 | U26: 0.6345 | V26: 201 | W26: 8453 | X26: 2823 | Y26: 147598 | Z26: 10230 | AA26: 84 | AB26: 162986 | AC26: 162805.42 | AD26: 32557.467 | AE26: 84 | AF26: 68 | AG26: 70 | AH26: 135405.52 | AI26: 58 | AJ26: 0 | AK26: 0.0693 | AL26: 0.334 | AM26: 0.0082 | AN26: 0.0241 | AO26: 0.0065 | AP26: 0.0075 | AQ26: 0 | AR26: 0 | AS26: 2 | AT26: 815.72 | AU26: 139498 | AV26: 72 | AW26: 23488 | AX26: 12 | AY26: 0.1441 | AZ26: - | BA26: - | BB26: - | BC26: -
A27: DAZZLE | B27: =DATE(YEAR(F27),MONTH(F27),DAY(F27)) -> 46041 | C27: =TEXT(YEAR(B27),"0")&"年" -> 2026年 | D27: =TEXT(MONTH(B27),"0")&"月" -> 1月 | E27: ="W"&TEXT(WEEKNUM(B27,2),"0") -> W4 | F27: 2026/01/19 14:01:08 | G27: 2026/01/19 19:04:14 | H27: 303 | I27: 88330 | J27: 193350 | K27: 9617 | L27: 1903.7281 | M27: 13191 | N27: 68 | O27: 44 | P27: 0.9 | Q27: 377 | R27: 0 | S27: 51 | T27: 4 | U27: 0.585 | V27: 200 | W27: 9385 | X27: 4087 | Y27: 173090 | Z27: 13164 | AA27: 76 | AB27: 161871.47 | AC27: 156836.3 | AD27: 31046.447 | AE27: 76 | AF27: 65 | AG27: 41 | AH27: 86793.63 | AI27: 36 | AJ27: 0 | AK27: 0.0761 | AL27: 0.4355 | AM27: 0.0058 | AN27: 0.0159 | AO27: 0.0058 | AP27: 0.0068 | AQ27: 0 | AR27: 0 | AS27: 1 | AT27: 529.33 | AU27: 107906.36 | AV27: 52 | AW27: 53965.11 | AX27: 24 | AY27: 0.3334 | AZ27: 64040.03 | BA27: 0.40832403 | BB27: 4865.97 | BC27: 34
A28: DAZZLE | B28: =DATE(YEAR(F28),MONTH(F28),DAY(F28)) -> 46031 | C28: =TEXT(YEAR(B28),"0")&"年" -> 2026年 | D28: =TEXT(MONTH(B28),"0")&"月" -> 1月 | E28: ="W"&TEXT(WEEKNUM(B28,2),"0") -> W2 | F28: 2026/01/09 08:18:28 | G28: 2026/01/09 13:07:34 | H28: 289 | I28: 37129 | J28: 100484 | K28: 6361 | L28: 1320.166 | M28: 9270 | N28: 56 | O28: 38 | P28: 1.16 | Q28: 312 | R28: 0 | S28: 18 | T28: 9 | U28: 0.7038 | V28: 195 | W28: 6056 | X28: 2613 | Y28: 132840 | Z28: 10735 | AA28: 73 | AB28: 149422.16 | AC28: 149241.16 | AD28: 30973.606 | AE28: 73 | AF28: 58 | AG28: 53 | AH28: 113745 | AI28: 41 | AJ28: 0 | AK28: 0.0808 | AL28: 0.4315 | AM28: 0.0068 | AN28: 0.0222 | AO28: 0.0079 | AP28: 0.0091 | AQ28: 0 | AR28: 0 | AS28: 0 | AT28: 793.32 | AU28: 134871.16 | AV28: 65 | AW28: 14551 | AX28: 8 | AY28: 0.0974 | AZ28: - | BA28: - | BB28: - | BC28: -
A29: DAZZLE | B29: =DATE(YEAR(F29),MONTH(F29),DAY(F29)) -> 46030 | C29: =TEXT(YEAR(B29),"0")&"年" -> 2026年 | D29: =TEXT(MONTH(B29),"0")&"月" -> 1月 | E29: ="W"&TEXT(WEEKNUM(B29,2),"0") -> W2 | F29: 2026/01/08 08:15:57 | G29: 2026/01/08 13:16:01 | H29: 300 | I29: 37436 | J29: 92779 | K29: 5829 | L29: 1165.541 | M29: 8139 | N29: 53 | O29: 28 | P29: 0.76 | Q29: 197 | R29: 0 | S29: 21 | T29: 2 | U29: 0.6806 | V29: 193 | W29: 5481 | X29: 1987 | Y29: 94142 | Z29: 7260 | AA29: 60 | AB29: 139657.39 | AC29: 139566.39 | AD29: 27907.076 | AE29: 60 | AF29: 49 | AG29: 53 | AH29: 124897.39 | AI29: 42 | AJ29: 0 | AK29: 0.0771 | AL29: 0.3625 | AM29: 0.0083 | AN29: 0.0247 | AO29: 0.0074 | AP29: 0.0084 | AQ29: 0 | AR29: 0 | AS29: 1 | AT29: 708.95 | AU29: 123414.39 | AV29: 53 | AW29: 16243 | AX29: 7 | AY29: 0.1163 | AZ29: - | BA29: - | BB29: - | BC29: -
A30: DAZZLE | B30: =DATE(YEAR(F30),MONTH(F30),DAY(F30)) -> 46025 | C30: =TEXT(YEAR(B30),"0")&"年" -> 2026年 | D30: =TEXT(MONTH(B30),"0")&"月" -> 1月 | E30: ="W"&TEXT(WEEKNUM(B30,2),"0") -> W1 | F30: 2026/01/03 08:18:04 | G30: 2026/01/03 13:18:10 | H30: 300 | I30: 38212 | J30: 95562 | K30: 6379 | L30: 1275.3749 | M30: 8941 | N30: 62 | O30: 28 | P30: 0.77 | Q30: 151 | R30: 0 | S30: 25 | T30: 2 | U30: 0.6793 | V30: 203 | W30: 6142 | X30: 1801 | Y30: 107702 | Z30: 7276 | AA30: 63 | AB30: 136273.4 | AC30: 136081.16 | AD30: 27207.163 | AE30: 63 | AF30: 46 | AG30: 52 | AH30: 114422.16 | AI30: 37 | AJ30: 0 | AK30: 0.0676 | AL30: 0.2932 | AM30: 0.0087 | AN30: 0.0255 | AO30: 0.007 | AP30: 0.0072 | AQ30: 0 | AR30: 0 | AS30: 3 | AT30: 844.28 | AU30: 111454.4 | AV30: 51 | AW30: 24819 | AX30: 12 | AY30: 0.1821 | AZ30: - | BA30: - | BB30: - | BC30: -
A31: DAZZLE | B31: =DATE(YEAR(F31),MONTH(F31),DAY(F31)) -> 46041 | C31: =TEXT(YEAR(B31),"0")&"年" -> 2026年 | D31: =TEXT(MONTH(B31),"0")&"月" -> 1月 | E31: ="W"&TEXT(WEEKNUM(B31,2),"0") -> W4 | F31: 2026/01/19 09:57:27 | G31: 2026/01/19 13:10:30 | H31: 193 | I31: 71915 | J31: 127242 | K31: 6168 | L31: 1917.0163 | M31: 7965 | N31: 84 | O31: 42 | P31: 0.82 | Q31: 207 | R31: 0 | S31: 46 | T31: 5 | U31: 0.5227 | V31: 197 | W31: 5849 | X31: 2507 | Y31: 98137 | Z31: 7179 | AA31: 75 | AB31: 139333 | AC31: 135159.61 | AD31: 42007.649 | AE31: 75 | AF31: 65 | AG31: 27 | AH31: 49691.07 | AI31: 22 | AJ31: 0 | AK31: 0.0732 | AL31: 0.4286 | AM31: 0.0104 | AN31: 0.0259 | AO31: 0.0094 | AP31: 0.0105 | AQ31: 0 | AR31: 0 | AS31: 3 | AT31: 532.62 | AU31: 102602.96 | AV31: 56 | AW31: 36730.04 | AX31: 19 | AY31: 0.2636 | AZ31: 77529.83 | BA31: 0.57361685 | BB31: 4284.17 | BC31: 45
A32: DAZZLE | B32: =DATE(YEAR(F32),MONTH(F32),DAY(F32)) -> 46025 | C32: =TEXT(YEAR(B32),"0")&"年" -> 2026年 | D32: =TEXT(MONTH(B32),"0")&"月" -> 1月 | E32: ="W"&TEXT(WEEKNUM(B32,2),"0") -> W1 | F32: 2026/01/03 20:01:57 | G32: 2026/01/04 01:04:11 | H32: 302 | I32: 58113 | J32: 146306 | K32: 9613 | L32: 1908.3931 | M32: 13564 | N32: 61 | O32: 43 | P32: 0.88 | Q32: 345 | R32: 0 | S32: 25 | T32: 8 | U32: 0.6668 | V32: 198 | W32: 9122 | X32: 3110 | Y32: 168055 | Z32: 11892 | AA32: 60 | AB32: 135009.09 | AC32: 134756.09 | AD32: 26752.064 | AE32: 60 | AF32: 54 | AG32: 47 | AH32: 105491.09 | AI32: 42 | AJ32: 0 | AK32: 0.0708 | AL32: 0.3409 | AM32: 0.005 | AN32: 0.0174 | AO32: 0.0044 | AP32: 0.0056 | AQ32: 0 | AR32: 0 | AS32: 0 | AT32: 836.26 | AU32: 117489.09 | AV32: 53 | AW32: 17520 | AX32: 7 | AY32: 0.1298 | AZ32: - | BA32: - | BB32: - | BC32: -
A33: DAZZLE | B33: =DATE(YEAR(F33),MONTH(F33),DAY(F33)) -> 46023 | C33: =TEXT(YEAR(B33),"0")&"年" -> 2026年 | D33: =TEXT(MONTH(B33),"0")&"月" -> 1月 | E33: ="W"&TEXT(WEEKNUM(B33,2),"0") -> W1 | F33: 2026/01/01 20:01:04 | G33: 2026/01/02 01:03:22 | H33: 302 | I33: 77483 | J33: 178612 | K33: 12460 | L33: 2473.04 | M33: 17128 | N33: 72 | O33: 46 | P33: 0.68 | Q33: 307 | R33: 1 | S33: 42 | T33: 6 | U33: 0.5951 | V33: 199 | W33: 11900 | X33: 3751 | Y33: 205672 | Z33: 13821 | AA33: 62 | AB33: 134551 | AC33: 134427 | AD33: 26680.847 | AE33: 62 | AF33: 45 | AG33: 52 | AH33: 110469 | AI33: 35 | AJ33: 0 | AK33: 0.0672 | AL33: 0.3152 | AM33: 0.0045 | AN33: 0.012 | AO33: 0.0036 | AP33: 0.0036 | AQ33: 0 | AR33: 0 | AS33: 2 | AT33: 947.07 | AU33: 119975 | AV33: 54 | AW33: 14576 | AX33: 8 | AY33: 0.1083 | AZ33: - | BA33: - | BB33: - | BC33: -
A34: DAZZLE | B34: =DATE(YEAR(F34),MONTH(F34),DAY(F34)) -> 46029 | C34: =TEXT(YEAR(B34),"0")&"年" -> 2026年 | D34: =TEXT(MONTH(B34),"0")&"月" -> 1月 | E34: ="W"&TEXT(WEEKNUM(B34,2),"0") -> W2 | F34: 2026/01/07 20:05:53 | G34: 2026/01/08 00:13:43 | H34: 247 | I34: 72712 | J34: 145515 | K34: 10206 | L34: 2470.8541 | M34: 13588 | N34: 89 | O34: 48 | P34: 0.68 | Q34: 275 | R34: 0 | S34: 40 | T34: 7 | U34: 0.5514 | V34: 202 | W34: 9853 | X34: 3313 | Y34: 161179 | Z34: 12806 | AA34: 80 | AB34: 134172 | AC34: 134102 | AD34: 32465.851 | AE34: 80 | AF34: 67 | AG34: 66 | AH34: 111042 | AI34: 60 | AJ34: 0 | AK34: 0.0795 | AL34: 0.3362 | AM34: 0.0062 | AN34: 0.0202 | AO34: 0.0059 | AP34: 0.0066 | AQ34: 0 | AR34: 0 | AS34: 0 | AT34: 861.44 | AU34: 110831 | AV34: 64 | AW34: 23341 | AX34: 16 | AY34: 0.174 | AZ34: - | BA34: - | BB34: - | BC34: -
A35: DAZZLE | B35: =DATE(YEAR(F35),MONTH(F35),DAY(F35)) -> 46033 | C35: =TEXT(YEAR(B35),"0")&"年" -> 2026年 | D35: =TEXT(MONTH(B35),"0")&"月" -> 1月 | E35: ="W"&TEXT(WEEKNUM(B35,2),"0") -> W2 | F35: 2026/01/11 20:00:40 | G35: 2026/01/12 00:00:49 | H35: 240 | I35: 59258 | J35: 129096 | K35: 9050 | L35: 2261.0868 | M35: 12278 | N35: 70 | O35: 42 | P35: 0.66 | Q35: 202 | R35: 0 | S35: 36 | T35: 4 | U35: 0.6133 | V35: 198 | W35: 8662 | X35: 2615 | Y35: 144846 | Z35: 9614 | AA35: 54 | AB35: 133607 | AC35: 133327.99 | AD35: 33311.178 | AE35: 54 | AF35: 45 | AG35: 31 | AH35: 79460.99 | AI35: 26 | AJ35: 0 | AK35: 0.0664 | AL35: 0.3019 | AM35: 0.0056 | AN35: 0.0172 | AO35: 0.0044 | AP35: 0.005 | AQ35: 0 | AR35: 0 | AS35: 1 | AT35: 863.15 | AU35: 114717 | AV35: 47 | AW35: 18890 | AX35: 7 | AY35: 0.1414 | AZ35: - | BA35: - | BB35: - | BC35: -
A36: DAZZLE | B36: =DATE(YEAR(F36),MONTH(F36),DAY(F36)) -> 46038 | C36: =TEXT(YEAR(B36),"0")&"年" -> 2026年 | D36: =TEXT(MONTH(B36),"0")&"月" -> 1月 | E36: ="W"&TEXT(WEEKNUM(B36,2),"0") -> W3 | F36: 2026/01/16 14:00:10 | G36: 2026/01/16 19:00:54 | H36: 300 | I36: 49494 | J36: 118883 | K36: 5347 | L36: 1066.7923 | M36: 7382 | N36: 45 | O36: 26 | P36: 0.83 | Q36: 201 | R36: 0 | S36: 28 | T36: 4 | U36: 0.6323 | V36: 217 | W36: 5081 | X36: 1969 | Y36: 104340 | Z36: 6877 | AA36: 63 | AB36: 134866.51 | AC36: 133175.64 | AD36: 26570.179 | AE36: 63 | AF36: 49 | AG36: 21 | AH36: 43025.07 | AI36: 18 | AJ36: 0 | AK36: 0.0659 | AL36: 0.3875 | AM36: 0.0092 | AN36: 0.0249 | AO36: 0.0085 | AP36: 0.0092 | AQ36: 0 | AR36: 0 | AS36: 0 | AT36: 666.18 | AU36: 121284.01 | AV36: 57 | AW36: 13582.5 | AX36: 6 | AY36: 0.1007 | AZ36: 14841.04 | BA36: 0.1114396 | BB36: 1447.47 | BC36: 8
A37: DAZZLE | B37: =DATE(YEAR(F37),MONTH(F37),DAY(F37)) -> 46039 | C37: =TEXT(YEAR(B37),"0")&"年" -> 2026年 | D37: =TEXT(MONTH(B37),"0")&"月" -> 1月 | E37: ="W"&TEXT(WEEKNUM(B37,2),"0") -> W3 | F37: 2026/01/17 08:04:10 | G37: 2026/01/17 13:04:17 | H37: 300 | I37: 52896 | J37: 115848 | K37: 5918 | L37: 1183.1399 | M37: 7991 | N37: 84 | O37: 28 | P37: 0.86 | Q37: 193 | R37: 1 | S37: 49 | T37: 4 | U37: 0.6063 | V37: 201 | W37: 5700 | X37: 2029 | Y37: 98102 | Z37: 7553 | AA37: 55 | AB37: 135826.59 | AC37: 132690.83 | AD37: 26527.85 | AE37: 55 | AF37: 45 | AG37: 17 | AH37: 44100.83 | AI37: 12 | AJ37: 0 | AK37: 0.077 | AL37: 0.356 | AM37: 0.0073 | AN37: 0.0222 | AO37: 0.0069 | AP37: 0.0076 | AQ37: 0 | AR37: 0 | AS37: 1 | AT37: 782.72 | AU37: 130703 | AV37: 52 | AW37: 5123.59 | AX37: 3 | AY37: 0.0377 | AZ37: 29367.83 | BA37: 0.22132524 | BB37: 3049.76 | BC37: 11
A38: DAZZLE | B38: =DATE(YEAR(F38),MONTH(F38),DAY(F38)) -> 46030 | C38: =TEXT(YEAR(B38),"0")&"年" -> 2026年 | D38: =TEXT(MONTH(B38),"0")&"月" -> 1月 | E38: ="W"&TEXT(WEEKNUM(B38,2),"0") -> W2 | F38: 2026/01/08 14:15:08 | G38: 2026/01/08 19:16:13 | H38: 301 | I38: 53074 | J38: 134631 | K38: 8357 | L38: 1665.3861 | M38: 12016 | N38: 78 | O38: 40 | P38: 0.87 | Q38: 301 | R38: 0 | S38: 38 | T38: 3 | U38: 0.6291 | V38: 196 | W38: 7947 | X38: 2900 | Y38: 156121 | Z38: 11609 | AA38: 56 | AB38: 130537.97 | AC38: 130468.97 | AD38: 25999.905 | AE38: 56 | AF38: 48 | AG38: 46 | AH38: 107031.97 | AI38: 39 | AJ38: 0 | AK38: 0.0744 | AL38: 0.3649 | AM38: 0.0048 | AN38: 0.0166 | AO38: 0.0047 | AP38: 0.0057 | AQ38: 0 | AR38: 0 | AS38: 1 | AT38: 659.32 | AU38: 115397.97 | AV38: 49 | AW38: 15140 | AX38: 7 | AY38: 0.116 | AZ38: - | BA38: - | BB38: - | BC38: -
A39: DAZZLE | B39: =DATE(YEAR(F39),MONTH(F39),DAY(F39)) -> 46028 | C39: =TEXT(YEAR(B39),"0")&"年" -> 2026年 | D39: =TEXT(MONTH(B39),"0")&"月" -> 1月 | E39: ="W"&TEXT(WEEKNUM(B39,2),"0") -> W2 | F39: 2026/01/06 20:14:32 | G39: 2026/01/07 00:18:43 | H39: 244 | I39: 74013 | J39: 148846 | K39: 11377 | L39: 2795.5225 | M39: 15235 | N39: 95 | O39: 48 | P39: 0.67 | Q39: 278 | R39: 0 | S39: 48 | T39: 6 | U39: 0.5547 | V39: 201 | W39: 10864 | X39: 3535 | Y39: 157446 | Z39: 13559 | AA39: 87 | AB39: 130705 | AC39: 130378 | AD39: 32036.093 | AE39: 87 | AF39: 79 | AG39: 77 | AH39: 115477 | AI39: 69 | AJ39: 0 | AK39: 0.0861 | AL39: 0.3254 | AM39: 0.0064 | AN39: 0.0223 | AO39: 0.0057 | AP39: 0.0069 | AQ39: 0 | AR39: 0 | AS39: 2 | AT39: 688.31 | AU39: 98330 | AV39: 65 | AW39: 32375 | AX39: 22 | AY39: 0.2477 | AZ39: - | BA39: - | BB39: - | BC39: -
A40: DAZZLE | B40: =DATE(YEAR(F40),MONTH(F40),DAY(F40)) -> 46032 | C40: =TEXT(YEAR(B40),"0")&"年" -> 2026年 | D40: =TEXT(MONTH(B40),"0")&"月" -> 1月 | E40: ="W"&TEXT(WEEKNUM(B40,2),"0") -> W2 | F40: 2026/01/10 08:00:49 | G40: 2026/01/10 12:47:57 | H40: 287 | I40: 40014 | J40: 99597 | K40: 6958 | L40: 1453.9587 | M40: 9696 | N40: 72 | O40: 34 | P40: 0.79 | Q40: 153 | R40: 0 | S40: 29 | T40: 3 | U40: 0.6611 | V40: 197 | W40: 6672 | X40: 2195 | Y40: 114272 | Z40: 8149 | AA40: 45 | AB40: 130180.02 | AC40: 129970.83 | AD40: 27158.985 | AE40: 45 | AF40: 43 | AG40: 39 | AH40: 115939.1 | AI40: 37 | AJ40: 0 | AK40: 0.0713 | AL40: 0.329 | AM40: 0.0055 | AN40: 0.0196 | AO40: 0.0046 | AP40: 0.0062 | AQ40: 0 | AR40: 0 | AS40: 2 | AT40: 716.18 | AU40: 117944.02 | AV40: 41 | AW40: 12236 | AX40: 4 | AY40: 0.094 | AZ40: - | BA40: - | BB40: - | BC40: -
A41: DAZZLE | B41: =DATE(YEAR(F41),MONTH(F41),DAY(F41)) -> 46027 | C41: =TEXT(YEAR(B41),"0")&"年" -> 2026年 | D41: =TEXT(MONTH(B41),"0")&"月" -> 1月 | E41: ="W"&TEXT(WEEKNUM(B41,2),"0") -> W2 | F41: 2026/01/05 20:02:50 | G41: 2026/01/06 00:09:39 | H41: 246 | I41: 48818 | J41: 114286 | K41: 8111 | L41: 1971.7469 | M41: 11088 | N41: 60 | O41: 38 | P41: 0.71 | Q41: 195 | R41: 0 | S41: 23 | T41: 3 | U41: 0.642 | V41: 198 | W41: 7777 | X41: 2565 | Y41: 124332 | Z41: 9514 | AA41: 75 | AB41: 127895 | AC41: 127618.56 | AD41: 31023.487 | AE41: 75 | AF41: 67 | AG41: 65 | AH41: 112393 | AI41: 58 | AJ41: 0 | AK41: 0.0765 | AL41: 0.3298 | AM41: 0.0079 | AN41: 0.0261 | AO41: 0.0068 | AP41: 0.0083 | AQ41: 0 | AR41: 0 | AS41: 2 | AT41: 699.33 | AU41: 109563 | AV41: 64 | AW41: 18332 | AX41: 11 | AY41: 0.1433 | AZ41: - | BA41: - | BB41: - | BC41: -
A42: DAZZLE | B42: =DATE(YEAR(F42),MONTH(F42),DAY(F42)) -> 46036 | C42: =TEXT(YEAR(B42),"0")&"年" -> 2026年 | D42: =TEXT(MONTH(B42),"0")&"月" -> 1月 | E42: ="W"&TEXT(WEEKNUM(B42,2),"0") -> W3 | F42: 2026/01/14 08:03:52 | G42: 2026/01/14 13:03:55 | H42: 300 | I42: 33449 | J42: 82678 | K42: 5534 | L42: 1106.6156 | M42: 7674 | N42: 48 | O42: 26 | P42: 0.77 | Q42: 135 | R42: 0 | S42: 16 | T42: 5 | U42: 0.6805 | V42: 202 | W42: 5163 | X42: 1491 | Y42: 84936 | Z42: 5568 | AA42: 56 | AB42: 127471.64 | AC42: 127329.64 | AD42: 25461.684 | AE42: 56 | AF42: 42 | AG42: 42 | AH42: 98792 | AI42: 30 | AJ42: 0 | AK42: 0.0656 | AL42: 0.2888 | AM42: 0.0101 | AN42: 0.0282 | AO42: 0.0073 | AP42: 0.0076 | AQ42: 0 | AR42: 0 | AS42: 1 | AT42: 583.46 | AU42: 101785.64 | AV42: 45 | AW42: 25686 | AX42: 11 | AY42: 0.2015 | AZ42: - | BA42: - | BB42: - | BC42: -
A43: DAZZLE | B43: =DATE(YEAR(F43),MONTH(F43),DAY(F43)) -> 46024 | C43: =TEXT(YEAR(B43),"0")&"年" -> 2026年 | D43: =TEXT(MONTH(B43),"0")&"月" -> 1月 | E43: ="W"&TEXT(WEEKNUM(B43,2),"0") -> W1 | F43: 2026/01/02 08:06:19 | G43: 2026/01/02 13:06:48 | H43: 300 | I43: 37347 | J43: 92662 | K43: 6235 | L43: 1244.9942 | M43: 8761 | N43: 59 | O43: 29 | P43: 0.75 | Q43: 180 | R43: 0 | S43: 17 | T43: 3 | U43: 0.685 | V43: 201 | W43: 5969 | X43: 1811 | Y43: 110498 | Z43: 6945 | AA43: 60 | AB43: 125512 | AC43: 125468 | AD43: 25053.236 | AE43: 60 | AF43: 46 | AG43: 50 | AH43: 109146 | AI43: 40 | AJ43: 0 | AK43: 0.0629 | AL43: 0.3034 | AM43: 0.0086 | AN43: 0.0254 | AO43: 0.0068 | AP43: 0.0074 | AQ43: 0 | AR43: 0 | AS43: 1 | AT43: 749.71 | AU43: 105602 | AV43: 53 | AW43: 19910 | AX43: 7 | AY43: 0.1586 | AZ43: - | BA43: - | BB43: - | BC43: -
A44: DAZZLE | B44: =DATE(YEAR(F44),MONTH(F44),DAY(F44)) -> 46042 | C44: =TEXT(YEAR(B44),"0")&"年" -> 2026年 | D44: =TEXT(MONTH(B44),"0")&"月" -> 1月 | E44: ="W"&TEXT(WEEKNUM(B44,2),"0") -> W4 | F44: 2026/01/20 20:09:23 | G44: 2026/01/21 00:13:25 | H44: 244 | I44: 108744 | J44: 201258 | K44: 16842 | L44: 4140.9097 | M44: 21025 | N44: 104 | O44: 52 | P44: 0.55 | Q44: 309 | R44: 1 | S44: 69 | T44: 0 | U44: 0.4226 | V44: 203 | W44: 15372 | X44: 4349 | Y44: 175894 | Z44: 13533 | AA44: 108 | AB44: 128613.99 | AC44: 124312.43 | AD44: 30564.455 | AE44: 108 | AF44: 98 | AG44: 33 | AH44: 43519.14 | AI44: 31 | AJ44: 0 | AK44: 0.0769 | AL44: 0.2829 | AM44: 0.008 | AN44: 0.0225 | AO44: 0.0051 | AP44: 0.0058 | AQ44: 0 | AR44: 0 | AS44: 1 | AT44: 609.46 | AU44: 91974.37 | AV44: 81 | AW44: 36639.62 | AX44: 27 | AY44: 0.2849 | AZ44: 49729.43 | BA44: 0.40003586 | BB44: 4256.36 | BC44: 47
A45: DAZZLE | B45: =DATE(YEAR(F45),MONTH(F45),DAY(F45)) -> 46026 | C45: =TEXT(YEAR(B45),"0")&"年" -> 2026年 | D45: =TEXT(MONTH(B45),"0")&"月" -> 1月 | E45: ="W"&TEXT(WEEKNUM(B45,2),"0") -> W1 | F45: 2026/01/04 08:08:02 | G45: 2026/01/04 13:08:05 | H45: 300 | I45: 44359 | J45: 110187 | K45: 7457 | L45: 1491.1515 | M45: 10451 | N45: 53 | O45: 34 | P45: 0.83 | Q45: 269 | R45: 0 | S45: 26 | T45: 4 | U45: 0.643 | V45: 223 | W45: 6997 | X45: 2518 | Y45: 134327 | Z45: 8830 | AA45: 65 | AB45: 117889 | AC45: 117834 | AD45: 23562.873 | AE45: 65 | AF45: 54 | AG45: 54 | AH45: 97892 | AI45: 44 | AJ45: 0 | AK45: 0.0657 | AL45: 0.3599 | AM45: 0.0074 | AN45: 0.0214 | AO45: 0.0062 | AP45: 0.0072 | AQ45: 0 | AR45: 0 | AS45: 1 | AT45: 696.85 | AU45: 93676 | AV45: 52 | AW45: 24213 | AX45: 13 | AY45: 0.2054 | AZ45: - | BA45: - | BB45: - | BC45: -
A46: DAZZLE | B46: =DATE(YEAR(F46),MONTH(F46),DAY(F46)) -> 46039 | C46: =TEXT(YEAR(B46),"0")&"年" -> 2026年 | D46: =TEXT(MONTH(B46),"0")&"月" -> 1月 | E46: ="W"&TEXT(WEEKNUM(B46,2),"0") -> W3 | F46: 2026/01/17 17:16:40 | G46: 2026/01/17 19:24:42 | H46: 128 | I46: 75265 | J46: 121120 | K46: 6278 | L46: 2942.0463 | M46: 7601 | N46: 85 | O46: 52 | P46: 0.66 | Q46: 183 | R46: 0 | S46: 60 | T46: 3 | U46: 0.5304 | V46: 201 | W46: 6007 | X46: 2661 | Y46: 98393 | Z46: 8286 | AA46: 126 | AB46: 123283 | AC46: 116750.43 | AD46: 54712.516 | AE46: 126 | AF46: 111 | AG46: 59 | AH46: 51252.03 | AI46: 52 | AJ46: 0 | AK46: 0.0842 | AL46: 0.443 | AM46: 0.0152 | AN46: 0.0417 | AO46: 0.0166 | AP46: 0.0177 | AQ46: 0 | AR46: 0 | AS46: 3 | AT46: 412.09 | AU46: 103583 | AV46: 106 | AW46: 19700 | AX46: 20 | AY46: 0.1598 | AZ46: 72458.17 | BA46: 0.62062444 | BB46: 6352.57 | BC46: 81
A47: DAZZLE | B47: =DATE(YEAR(F47),MONTH(F47),DAY(F47)) -> 46024 | C47: =TEXT(YEAR(B47),"0")&"年" -> 2026年 | D47: =TEXT(MONTH(B47),"0")&"月" -> 1月 | E47: ="W"&TEXT(WEEKNUM(B47,2),"0") -> W1 | F47: 2026/01/02 14:19:08 | G47: 2026/01/02 18:45:13 | H47: 266 | I47: 44893 | J47: 107294 | K47: 6795 | L47: 1532.2267 | M47: 9483 | N47: 69 | O47: 31 | P47: 0.68 | Q47: 154 | R47: 0 | S47: 17 | T47: 5 | U47: 0.6781 | V47: 203 | W47: 6402 | X47: 2242 | Y47: 117626 | Z47: 7553 | AA47: 54 | AB47: 114345.95 | AC47: 114086.94 | AD47: 25725.837 | AE47: 54 | AF47: 45 | AG47: 45 | AH47: 94181.95 | AI47: 37 | AJ47: 0 | AK47: 0.0642 | AL47: 0.3502 | AM47: 0.0071 | AN47: 0.0201 | AO47: 0.0057 | AP47: 0.0066 | AQ47: 0 | AR47: 0 | AS47: 2 | AT47: 627.72 | AU47: 96418.95 | AV47: 46 | AW47: 17927 | AX47: 8 | AY47: 0.1568 | AZ47: - | BA47: - | BB47: - | BC47: -
A48: DAZZLE | B48: =DATE(YEAR(F48),MONTH(F48),DAY(F48)) -> 46027 | C48: =TEXT(YEAR(B48),"0")&"年" -> 2026年 | D48: =TEXT(MONTH(B48),"0")&"月" -> 1月 | E48: ="W"&TEXT(WEEKNUM(B48,2),"0") -> W2 | F48: 2026/01/05 14:06:05 | G48: 2026/01/05 19:06:14 | H48: 300 | I48: 52367 | J48: 121419 | K48: 8278 | L48: 1654.7726 | M48: 11261 | N48: 59 | O48: 34 | P48: 0.72 | Q48: 227 | R48: 0 | S48: 18 | T48: 2 | U48: 0.6028 | V48: 200 | W48: 7773 | X48: 2702 | Y48: 126181 | Z48: 8797 | AA48: 51 | AB48: 112594 | AC48: 112461 | AD48: 22480.96 | AE48: 51 | AF48: 44 | AG48: 42 | AH48: 93993 | AI48: 36 | AJ48: 0 | AK48: 0.0697 | AL48: 0.3476 | AM48: 0.0058 | AN48: 0.0163 | AO48: 0.0045 | AP48: 0.0053 | AQ48: 0 | AR48: 0 | AS48: 0 | AT48: 432.33 | AU48: 79646 | AV48: 37 | AW48: 32948 | AX48: 14 | AY48: 0.2926 | AZ48: - | BA48: - | BB48: - | BC48: -
A49: DAZZLE | B49: =DATE(YEAR(F49),MONTH(F49),DAY(F49)) -> 46042 | C49: =TEXT(YEAR(B49),"0")&"年" -> 2026年 | D49: =TEXT(MONTH(B49),"0")&"月" -> 1月 | E49: ="W"&TEXT(WEEKNUM(B49,2),"0") -> W4 | F49: 2026/01/20 08:10:48 | G49: 2026/01/20 13:10:55 | H49: 300 | I49: 49156 | J49: 111962 | K49: 7194 | L49: 1438.2407 | M49: 9554 | N49: 51 | O49: 29 | P49: 0.75 | Q49: 154 | R49: 0 | S49: 27 | T49: 3 | U49: 0.5859 | V49: 200 | W49: 6639 | X49: 2036 | Y49: 102410 | Z49: 6890 | AA49: 57 | AB49: 114803 | AC49: 111156.23 | AD49: 22222.604 | AE49: 57 | AF49: 45 | AG49: 20 | AH49: 47910.97 | AI49: 17 | AJ49: 0 | AK49: 0.0673 | AL49: 0.3067 | AM49: 0.0083 | AN49: 0.0221 | AO49: 0.006 | AP49: 0.0063 | AQ49: 0 | AR49: 0 | AS49: 1 | AT49: 717.64 | AU49: 84226 | AV49: 44 | AW49: 30577 | AX49: 13 | AY49: 0.2663 | AZ49: 41090.23 | BA49: 0.36966196 | BB49: 3457.77 | BC49: 22
A50: DAZZLE | B50: =DATE(YEAR(F50),MONTH(F50),DAY(F50)) -> 46028 | C50: =TEXT(YEAR(B50),"0")&"年" -> 2026年 | D50: =TEXT(MONTH(B50),"0")&"月" -> 1月 | E50: ="W"&TEXT(WEEKNUM(B50,2),"0") -> W2 | F50: 2026/01/06 08:16:47 | G50: 2026/01/06 13:16:56 | H50: 300 | I50: 34639 | J50: 87538 | K50: 5961 | L50: 1191.6042 | M50: 8494 | N50: 54 | O50: 27 | P50: 0.8 | Q50: 166 | R50: 0 | S50: 29 | T50: 6 | U50: 0.697 | V50: 200 | W50: 5704 | X50: 1945 | Y50: 88726 | Z50: 6443 | AA50: 66 | AB50: 109772 | AC50: 109476 | AD50: 21884.258 | AE50: 66 | AF50: 51 | AG50: 55 | AH50: 94206 | AI50: 43 | AJ50: 0 | AK50: 0.0726 | AL50: 0.341 | AM50: 0.0102 | AN50: 0.0262 | AO50: 0.0078 | AP50: 0.0086 | AQ50: 0 | AR50: 0 | AS50: 0 | AT50: 594.78 | AU50: 90421 | AV50: 54 | AW50: 19351 | AX50: 12 | AY50: 0.1763 | AZ50: - | BA50: - | BB50: - | BC50: -
